Workbook

Sheet INFO
A1: Scenario Description | B1: Example scenario
A3: This Excel file defines an oemof energy system.
A4: The components are defined in the several sheets.
A6: Sheet | B6: Notes
A7: buses | B7: Defines the buses used in the energy system
B8: -If excess or shortage flag is set (=1), an additional sink resp. source is added AUTOMATICALLY
A9: commodity_sources | B9: Defines the commodity sources such as oil, gas etc.
A10: demand | B10: Defines demand components such as heat demand
A11: powerlines | B11: Defines power lines between 2 buses
B12: -Creates 2 oemof transformers (A->B, B->A)
A13: renewables | B13: Defines the renewable sources (fixed generation)
A14: storages | B14: Defines storages
B15: Initial capacity: set between 0 (empty) and 1 (full)
A16: transformers | B16: Defines the transformers like power2gas plants etc.
B17: -variable costs refer to input values!
B18: - capacity is the nominal value of the output; "max nom in" is the maximum input which is multiplied with the timeseries transformer.max
B19: -Power lines are defined in the sheet "powerlines"
A20: time_series | B20: Time series
B21: -Format of column must follow the format NODE.PARAMETER (e.g. wind.actual_value)
B22: time series are implemented for renewables, demands and transformer inputs
A24: General notes
A25: -For details on how this data is used (and to alter) during creation of the energy system refer to function "create_nodes()".
A26: -Unit of values is kW / kWh and €
A27: -If column "active" is set to 0, the component will not be created in the energy system

Sheet buses
A1: label | B1: active | C1: excess | D1: shortage | E1: unit | F1: shortage_costs | G1: shortage_env | H1: excess_costs | I1: excess_env | J1: excess_env_conversion | K1: warnings | L1: Dropdown list | N1: c_avar_25 | O1: c_avar_30 | P1: c_avar_35 | Q1: c_avar_40 | R1: c_avar_45 | S1: c_avar_50 | T1: c_avar_55 | U1: c_avar_60 | V1: c_avar_65 | W1: c_avar_70
A2: bus_el | B2: 1 | C2: 1 | D2: 0 | E2: kWh | F2: 0 | G2: empty | H2: 0 | I2: empty | J2: 0 | K2: =IF(AND(I2<>"empty",J2=0),"define excess_env_conversion","") | L2: empty | M2: electricity excess, low voltage, DE, commodity_kWh
A3: bus_el-over | B3: 1 | C3: 1 | D3: 0 | E3: kWh | F3: 0 | G3: empty | H3: 0 | I3: empty | J3: 0 | K3: =IF(AND(I3<>"empty",J3=0),"define excess_env_conversion","") | L3: empty
A4: bus_el-h2 | B4: 1 | C4: 1 | D4: 0 | E4: kWh | F4: 0 | G4: empty | H4: 0 | I4: empty | J4: 0 | K4: =IF(AND(I4<>"empty",J4=0),"define excess_env_conversion","") | L4: empty
A5: bus_el-re | B5: 1 | C5: 1 | D5: 0 | E5: kWh | F5: 0 | G5: empty | H5: 0 | I5: empty | J5: 0 | K5: =IF(AND(I5<>"empty",J5=0),"define excess_env_conversion","") | L5: empty
A6: bus_el-stor | B6: 1 | C6: 1 | D6: 0 | E6: kWh | F6: 0 | G6: empty | H6: 0 | I6: empty | J6: 0 | K6: =IF(AND(I6<>"empty",J6=0),"define excess_env_conversion","") | L6: empty
A7: bus_el-out | B7: 1 | C7: 0 | D7: 0 | E7: kWh | F7: 0 | G7: empty | H7: 0 | I7: empty | J7: 0 | K7: =IF(AND(I7<>"empty",J7=0),"define excess_env_conversion","") | L7: empty
A8: bus_el-grid | B8: 1 | C8: 0 | D8: 0 | E8: kWh | F8: 0 | G8: empty | H8: 0 | I8: empty | J8: 0 | K8: =IF(AND(I8<>"empty",J8=0),"define excess_env_conversion","") | L8: empty
A9: bus_el-transformed | B9: 1 | C9: 1 | D9: 0 | E9: kWh | F9: 0 | G9: empty | H9: 0 | I9: empty | J9: 0 | K9: =IF(AND(I9<>"empty",J9=0),"define excess_env_conversion","") | L9: empty
A10: bus_th | B10: 0 | C10: 0 | D10: 0 | E10: kWh | F10: 0 | G10: empty | H10: 0 | I10: empty | J10: 0 | K10: =IF(AND(I10<>"empty",J10=0),"define excess_env_conversion","") | L10: empty
A11: bus_th_low | B11: 0 | C11: 0 | D11: 0 | E11: kWh | F11: 1000000000 | G11: empty | H11: 0 | I11: empty | J11: 0 | K11: =IF(AND(I11<>"empty",J11=0),"define excess_env_conversion","") | L11: empty
A12: bus_th_high | B12: 0 | C12: 0 | D12: 0 | E12: kWh | F12: 0 | G12: empty | H12: 0 | I12: empty | J12: 0 | K12: =IF(AND(I12<>"empty",J12=0),"define excess_env_conversion","") | L12: empty
A13: bus_th_households | B13: 0 | C13: 0 | D13: 0 | E13: kWh | F13: 0 | G13: empty | H13: 0 | I13: empty | J13: 0 | K13: =IF(AND(I13<>"empty",J13=0),"define excess_env_conversion","") | L13: empty
A14: bus_logs | B14: 0 | C14: 0 | D14: 0 | E14: kWh | F14: 0 | G14: empty | H14: 0 | I14: empty | J14: 0 | K14: =IF(AND(I14<>"empty",J14=0),"define excess_env_conversion","") | L14: empty
... A22: bus_hydrogen_proxy | B22: 1 | C22: 1 | D22: 0 | E22: kg | F22: 0 | G22: empty | H22: 0 | I22: empty | J22: 0 | K22: =IF(AND(I22<>"empty",J22=0),"define excess_env_conversion","") | L22: empty
A23: bus_biogas | B23: 0 | C23: 0 | D23: 0 | E23: kWh | F23: 0 | G23: empty | H23: 0 | I23: empty | J23: 0 | L23: empty
A24: bus_biometh | B24: 1 | C24: 1 | D24: 0 | E24: kWh | F24: 0 | G24: empty | H24: 0 | I24: empty | J24: 0 | L24: empty
A25: bus_oxygen | B25: 1 | C25: 1 | D25: 0 | E25: kg | F25: 0 | G25: empty | H25: 0 | I25: empty | J25: 0 | K25: =IF(AND(I25<>"empty",J25=0),"define excess_env_conversion","") | L25: empty
A26: bus_water_ultrapure | B26: 1 | C26: 1 | D26: 0 | E26: kg | F26: 0 | G26: empty | H26: 0 | I26: empty | J26: 0 | K26: =IF(AND(I26<>"empty",J26=0),"define excess_env_conversion","") | L26: empty
A27: bus_water_deionized | B27: 1 | C27: 1 | D27: 0 | E27: kg | F27: 0 | G27: empty | H27: 0 | I27: empty | J27: 0 | K27: =IF(AND(I27<>"empty",J27=0),"define excess_env_conversion","") | L27: empty
A28: bus_th60 | B28: 1 | C28: 1 | D28: 0 | E28: kWh | F28: 0 | G28: empty | H28: 0 | I28: empty | J28: 0 | L28: empty
A29: bus_th120 | B29: 1 | C29: 0 | D29: 0 | E29: kWh | F29: 0 | G29: empty | H29: 0 | I29: empty | J29: 0 | L29: empty
A30: bus_th200 | B30: 1 | C30: 0 | D30: 0 | E30: kWh | F30: 0 | G30: empty | H30: 0 | I30: empty | J30: 0 | L30: empty
A31: bus_th400 | B31: 1 | C31: 0 | D31: 0 | E31: kWh | F31: 0 | G31: empty | H31: 0 | I31: empty | J31: 0 | L31: empty
A32: bus_lohc | B32: 1 | C32: 1 | D32: 0 | E32: kg | F32: 0 | G32: empty | H32: 0 | I32: empty | J32: 0 | L32: empty
A33: bus_nh3 | B33: 1 | C33: 1 | D33: 0 | E33: kg | F33: 0 | G33: empty | H33: 0 | I33: empty | J33: 0 | L33: empty
A34: bus_atr-exhaust | B34: 1 | C34: 0 | D34: 0 | E34: kg | F34: 0 | G34: empty | H34: 0 | I34: empty | J34: 0 | L34: empty
A35: bus_smr-exhaust | B35: 1 | C35: 0 | D35: 0 | E35: kg | F35: 0 | G35: empty | H35: 0 | I35: empty | J35: 0 | L35: empty
A36: bus_co2_emission | B36: 1 | C36: 1 | D36: 0 | E36: kg | F36: 0 | G36: empty | H36: c_avar | I36: co2_emission | J36: 1 | L36: empty | M36: co2_emission | N36: 0.075 | O36: 0.15 | P36: 0.225 | Q36: 0.3 | R36: 0.3 | S36: 0.3 | T36: 0.3 | U36: 0.3 | V36: 0.3 | W36: 0.3
A37: bus_co2 | B37: 1 | C37: 1 | D37: 0 | E37: kg | F37: 0 | G37: empty | H37: c_avar | I37: empty | J37: 0 | L37: empty | N37: =0.4*N36 -> 0.03 | O37: =0.4*O36 -> 0.06 | P37: =0.4*P36 -> 0.09 | Q37: =0.4*Q36 -> 0.12 | R37: =0.4*R36 -> 0.12 | S37: =0.4*S36 -> 0.12 | T37: =0.4*T36 -> 0.12 | U37: =0.4*U36 -> 0.12 | ... W37: =0.4*W36 -> 0.12
A38: bus_carbon | B38: 1 | C38: 1 | D38: 0 | E38: kWh | F38: 0 | G38: empty | H38: 0 | I38: empty | J38: 0 | L38: empty
A39: bus_co | B39: 0 | C39: 0 | D39: 0 | E39: kg | F39: 0 | G39: empty | H39: 0 | I39: empty | J39: 0 | L39: empty
A40: bus_steam7,5bar | B40: 1 | C40: 1 | D40: 0 | E40: kWh | F40: 0 | G40: empty | H40: 0 | I40: empty | J40: 0 | L40: empty
A41: bus_ch3oh | B41: 0 | C41: 0 | D41: 0 | E41: kg | F41: 0 | G41: empty | H41: 0 | I41: empty | J41: 0 | L41: empty
A42: bus_smre | B42: 1 | C42: 0 | D42: 0 | E42: kg | F42: 0 | G42: empty | H42: 0 | I42: empty | J42: 0 | L42: empty
A43: bus_smre_po1 | B43: 1 | C43: 0 | D43: 0 | E43: kg | F43: 0 | G43: empty | H43: 0 | I43: empty | J43: 0 | L43: empty
A44: bus_smr_pi1 | B44: 1 | C44: 0 | D44: 0 | E44: kg | F44: 0 | G44: empty | H44: 0 | I44: empty | J44: 0 | L44: empty
A45: bus_smr_pi2 | B45: 1 | C45: 0 | D45: 0 | E45: kg | F45: 0 | G45: empty | H45: 0 | I45: empty | J45: 0 | L45: empty
A46: bus_smr_po1 | B46: 1 | C46: 0 | D46: 0 | E46: kg | F46: 0 | G46: empty | H46: 0 | I46: empty | J46: 0 | L46: empty
A47: bus_pem | B47: 1 | C47: 0 | D47: 0 | E47: kg | F47: 0 | G47: empty | H47: 0 | I47: empty | J47: 0 | L47: empty
A48: bus_pem_po1 | B48: 1 | C48: 0 | D48: 0 | E48: kg | F48: 0 | G48: empty | H48: 0 | I48: empty | J48: 0 | L48: empty
A49: bus_ael | B49: 1 | C49: 0 | D49: 0 | E49: kg | F49: 0 | G49: empty | H49: 0 | I49: empty | J49: 0 | L49: empty
... A78: bus_chp-h2 | B78: 1 | C78: 0 | D78: 0 | E78: kWh | F78: 0 | G78: empty | H78: 0 | I78: empty | J78: 0 | L78: empty

Sheet commodity_sources
A1: label | B1: active | C1: to | D1: unit | E1: year_of_availability | F1: end_of_availability | G1: variable_costs | H1: var_env1 | I1: var_env1_conversion | J1: timevariable_costs | K1: max | L1: comment | M1: fuel_based | N1: comment
A2: resource_grid_25 | B2: 1 | C2: bus_el-grid | D2: kWh | E2: 2025 | F2: 2030 | G2: 0.1 | H2: el_mix_DE_2025_kWh | I2: 1 | J2: 0 | M2: 1 | N2: baseline assumptions: Langfristszenarien; bdew2023a p. 44 (Futures 2026: 0,112); Prognos
A3: resource_grid_30 | B3: 1 | C3: bus_el-grid | D3: kWh | E3: 2030 | F3: 2035 | G3: 0.08 | H3: el_mix_DE_2030_kWh | I3: 1 | J3: 0
A4: resource_grid_35 | B4: 1 | C4: bus_el-grid | D4: kWh | E4: 2035 | F4: 2040 | G4: 0.07 | H4: el_mix_DE_2035_kWh | I4: 1 | J4: 0
A5: resource_grid_40 | B5: 1 | C5: bus_el-grid | D5: kWh | E5: 2040 | F5: 2045 | G5: 0.06 | H5: el_mix_DE_2040_kWh | I5: 1 | J5: 0
A6: resource_grid_45 | B6: 1 | C6: bus_el-grid | D6: kWh | E6: 2045 | F6: 2050 | G6: 0.055 | H6: el_mix_DE_2045_kWh | I6: 1 | J6: 0
A7: resource_grid_50 | B7: 1 | C7: bus_el-grid | D7: kWh | E7: 2050 | F7: 2055 | G7: 0.055 | H7: el_mix_DE_2045_kWh | I7: 1 | J7: 0
A8: resource_grid_55 | B8: 0 | C8: bus_el-grid | D8: kWh | E8: 2055 | F8: 2060 | G8: 0.055 | H8: el_mix_DE_2045_kWh | I8: 1 | J8: 0
A9: resource_grid_60 | B9: 0 | C9: bus_el-grid | D9: kWh | E9: 2060 | F9: 2065 | G9: 0.055 | H9: el_mix_DE_2045_kWh | I9: 1 | J9: 0
A10: resource_grid_65 | B10: 0 | C10: bus_el-grid | D10: kWh | E10: 2065 | F10: 2070 | G10: 0.055 | H10: el_mix_DE_2045_kWh | I10: 1 | J10: 0
A11: resource_grid_70 | B11: 0 | C11: bus_el-grid | D11: kWh | E11: 2070 | F11: 1000000000000 | G11: 0.055 | H11: el_mix_DE_2045_kWh | I11: 1 | J11: 0
A13: resource_nat_gas_25 | B13: 0 | C13: bus_nat_gas | D13: kWh | E13: 2025 | F13: 2030 | G13: 0.042 | H13: market for natural gas, high pressure_commodity_DE_m3 | I13: =1/(36/3.6) -> 0.1 | J13: 0 | L13: 36 MJ/m3 [ecoinvent database] | M13: 1 | N13: based on Bundesnetzagentur für Elektrizität…2022 p. 460, statista (download), TradingHub.eu and Langfristszenarien; bdew2023b;
A14: resource_nat_gas_30 | B14: 0 | C14: bus_nat_gas | D14: kWh | E14: 2030 | F14: 2035 | G14: 0.03 | H14: market for natural gas, high pressure_commodity_DE_m3 | I14: =1/(36/3.6) -> 0.1 | J14: 0 | M14: 1 | N14: based on Langfristszenarien
A15: resource_nat_gas_35 | B15: 0 | C15: bus_nat_gas | D15: kWh | E15: 2035 | F15: 2040 | G15: 0.019 | H15: market for natural gas, high pressure_commodity_DE_m3 | I15: =1/(36/3.6) -> 0.1 | J15: 0 | M15: 1 | N15: based on Langfristszenarien
A16: resource_nat_gas_40 | B16: 0 | C16: bus_nat_gas | D16: kWh | E16: 2040 | F16: 2045 | G16: 0.019 | H16: market for natural gas, high pressure_commodity_DE_m3 | I16: =1/(36/3.6) -> 0.1 | J16: 0 | M16: 1 | N16: based on Langfristszenarien
A17: resource_nat_gas_45 | B17: 0 | C17: bus_nat_gas | D17: kWh | E17: 2045 | F17: 2050 | G17: 10 | H17: market for natural gas, high pressure_commodity_DE_m3 | I17: =1/(36/3.6) -> 0.1 | J17: 0 | M17: 1 | N17: based on Langfristszenarien
A18: resource_nat_gas_50 | B18: 0 | C18: bus_nat_gas | D18: kWh | E18: 2050 | F18: 2055 | G18: 10 | H18: market for natural gas, high pressure_commodity_DE_m3 | I18: =1/(36/3.6) -> 0.1 | J18: 0
A19: resource_nat_gas_55 | B19: 0 | C19: bus_nat_gas | D19: kWh | E19: 2055 | F19: 2060 | G19: 10 | H19: market for natural gas, high pressure_commodity_DE_m3 | I19: =1/(36/3.6) -> 0.1 | J19: 0
A20: resource_nat_gas_60 | B20: 0 | C20: bus_nat_gas | D20: kWh | E20: 2060 | F20: 2065 | G20: 10 | H20: market for natural gas, high pressure_commodity_DE_m3 | I20: =1/(36/3.6) -> 0.1 | J20: 0
A21: resource_nat_gas_65 | B21: 0 | C21: bus_nat_gas | D21: kWh | E21: 2065 | F21: 2070 | G21: 10 | H21: market for natural gas, high pressure_commodity_DE_m3 | I21: =1/(36/3.6) -> 0.1 | J21: 0
A22: resource_nat_gas_70 | B22: 0 | C22: bus_nat_gas | D22: kWh | E22: 2070 | F22: 2075 | G22: 10 | H22: market for natural gas, high pressure_commodity_DE_m3 | I22: =1/(36/3.6) -> 0.1 | J22: 0
A24: resource_biogas_25 | B24: 0 | C24: bus_biogas | D24: kWh | E24: 2025 | F24: 2030 | G24: 0.09 | H24: empty | I24: 1 | J24: 0 | L24: biomethane price, biogas could be cheaper to a small extent | M24: 0 | N24: Alberici2023,
A25: resource_biogas_30 | B25: 0 | C25: bus_biogas | D25: kWh | E25: 2030 | F25: 2035 | G25: 0.09 | H25: empty | I25: 1 | J25: 0 | L25: biomethane price, biogas could be cheaper to a small extent | M25: 0
A26: resource_biogas_35 | B26: 0 | C26: bus_biogas | D26: kWh | E26: 2035 | F26: 2040 | G26: 0.09 | H26: empty | I26: 1 | J26: 0 | L26: biomethane price, biogas could be cheaper to a small extent | M26: 0
A27: resource_biogas_40 | B27: 0 | C27: bus_biogas | D27: kWh | E27: 2040 | F27: 2045 | G27: 0.09 | H27: empty | I27: 1 | J27: 0 | L27: biomethane price, biogas could be cheaper to a small extent | M27: 0
A28: resource_biogas_45 | B28: 0 | C28: bus_biogas | D28: kWh | E28: 2045 | F28: 1000000000000 | G28: 0.09 | H28: empty | I28: 1 | J28: 0 | L28: biomethane price, biogas could be cheaper to a small extent | M28: 0
A29: resource_biogas | B29: 0 | C29: bus_biogas | D29: kWh | G29: 0.09 | H29: empty | I29: 1 | J29: 0 | L29: biomethane price, biogas could be cheaper to a small extent | M29: 0
A30: resource_biometh_industry | B30: 0 | C30: bus_biometh | D30: kWh | E30: 0 | F30: 1000000000000 | G30: 0.1152 | H30: empty | I30: 3.6 | J30: 0 | L30: 3.6 MJ/kWh | M30: 1
A31: resource_pellets | B31: 0 | C31: bus_pellets | D31: kWh | E31: 0 | F31: 1000000000000 | G31: 0.32 | H31: market for wood pellet, measured as dry mass, commodity_kg | I31: =1/18.7*3.6 -> 0.19251337 | J31: 0 | L31: LHV 18.7 MJ/kg (dry mass) [ecoinvent database] | M31: 1
A32: resource_w_chips | B32: 0 | C32: bus_w_chips | D32: kWh | E32: 0 | F32: 1000000000000 | G32: =315/1000*(1/0.9)*(1/18.7)*3.6 -> 0.067379679 | H32: market for wood chips, measured as dry mass_commodity_kg | I32: =1/18.9*3.6 -> 0.19047619 | J32: 0 | L32: LHV 18.9 MJ/kg (dry mass) | M32: 1
A33: resource_hw_chips | B33: 0 | C33: bus_hw_chips | D33: kWh | E33: 0 | F33: 1000000000000 | G33: =121.6/1000*(1/0.8)*(1/18.9)*3.6 -> 0.028952381 | H33: market for hard_softwood chips from forest, wet, measured as dry mass, commodity_kg | I33: =1/18.3*3.6 -> 0.19672131 | J33: 0 | L33: LHV (oven-dry) 18.3 MJ/kg [ecoinvent database] | M33: 1
A34: resource_sw_chips | B34: 0 | C34: bus_sw_chips | D34: kWh | E34: 0 | F34: 1000000000000 | G34: =305*4/3580*(1/0.8)*(1/18.55)*3.6 -> 0.082669518 | H34: market for hard_softwood chips from forest, wet, measured as dry mass, commodity_kg | I34: =1/19.1*3.6 -> 0.18848168 | J34: 0 | L34: LHV (oven-dry) 19.1 MJ/kg [ecoinvent database] | M34: 1
A35: resource_logs | B35: 0 | C35: bus_logs | D35: kWh | E35: 0 | F35: 1000000000000 | G35: =77.73/1000*(1/0.65)*(1/18.3)*3.6 -> 0.023524842 | H35: market for cleft timber, measured as dry mass, commodity_DE_kg | I35: =1/18.55*3.6 -> 0.19407008 | J35: 0 | L35: LHV 18.55 MJ/kg (dry mass) [ecoinvent database] | M35: 1
A36: resource_water_ultrapure | B36: 1 | C36: bus_water_ultrapure | D36: kg | E36: 0 | F36: 1000000000000 | G36: 0.003 | H36: market for water, ultrapure | I36: 1 | J36: 0 | M36: 0
A37: resource_water_deionized | B37: 1 | C37: bus_water_deionized | D37: kg | E37: 0 | F37: 1000000000000 | G37: 0.003 | H37: market for water, deionised | I37: 1 | J37: 0 | M37: 0
A38: resource_th60-wasteheat | B38: 0 | C38: bus_th60 | D38: kWh | E38: 0 | F38: 2100 | G38: 0 | H38: empty | I38: 1 | J38: 0
A40: resource_h2-pipeline_25 | B40: 0 | C40: bus_hydrogen | D40: kg | E40: 2025 | F40: 2030 | G40: 1e+20 | H40: hydrogen pipeline import, Morocco-Germany_kg | I40: 1 | J40: 0 | L40: solely Levelized Cost of Fuel but no taxes or other charges are considered | M40: 0 | N40: extensive literature research: Aurora2023, Lux2021, Lux2020, within range of Wietschel2023; LCA based on Kanz2023
A41: resource_h2-pipeline_30 | B41: 0 | C41: bus_hydrogen | D41: kg | E41: 2030 | F41: 2035 | G41: 1e+20 | H41: hydrogen pipeline import, Morocco-Germany_kg | I41: 1 | J41: 0 | L41: solely Levelized Cost of Fuel but no taxes or other charges are considered | M41: 0 | N41: 5.16
A42: resource_h2-pipeline_35 | B42: 0 | C42: bus_hydrogen | D42: kg | E42: 2035 | F42: 2040 | G42: 4.87 | H42: hydrogen pipeline import, Morocco-Germany_kg | I42: 1 | J42: 0 | L42: solely Levelized Cost of Fuel but no taxes or other charges are considered | M42: 0 | N42: 4.87
A43: resource_h2-pipeline_40 | B43: 0 | C43: bus_hydrogen | D43: kg | E43: 2040 | F43: 2045 | G43: 4.58 | H43: hydrogen pipeline import, Morocco-Germany_kg | I43: 1 | J43: 0 | L43: solely Levelized Cost of Fuel but no taxes or other charges are considered | M43: 0 | N43: 4.58
A44: resource_h2-pipeline_45 | B44: 0 | C44: bus_hydrogen | D44: kg | E44: 2045 | F44: 2050 | G44: 4.29 | H44: hydrogen pipeline import, Morocco-Germany_kg | I44: 1 | J44: 0 | L44: solely Levelized Cost of Fuel but no taxes or other charges are considered | M44: 0 | N44: 4.29
A45: resource_h2-pipeline_50 | B45: 0 | C45: bus_hydrogen | D45: kg | E45: 2050 | F45: 2055 | G45: 4 | H45: hydrogen pipeline import, Morocco-Germany_kg | I45: 1 | J45: 0 | L45: solely Levelized Cost of Fuel but no taxes or other charges are considered | M45: 0 | N45: 4
A46: resource_h2-pipeline_55 | B46: 0 | C46: bus_hydrogen | D46: kg | E46: 2055 | F46: 2060 | G46: 4 | H46: hydrogen pipeline import, Morocco-Germany_kg | I46: 1 | J46: 0 | L46: solely Levelized Cost of Fuel but no taxes or other charges are considered | M46: 0
A47: resource_h2-pipeline_60 | B47: 0 | C47: bus_hydrogen | D47: kg | E47: 2060 | F47: 2065 | G47: 4 | H47: hydrogen pipeline import, Morocco-Germany_kg | I47: 1 | J47: 0 | L47: solely Levelized Cost of Fuel but no taxes or other charges are considered | M47: 0
A48: resource_h2-pipeline_65 | B48: 0 | C48: bus_hydrogen | D48: kg | E48: 2065 | F48: 2070 | G48: 4 | H48: hydrogen pipeline import, Morocco-Germany_kg | I48: 1 | J48: 0 | L48: solely Levelized Cost of Fuel but no taxes or other charges are considered | M48: 0
A49: resource_h2-pipeline_70 | B49: 0 | C49: bus_hydrogen | D49: kg | E49: 2070 | F49: 2075 | G49: 4 | H49: hydrogen pipeline import, Morocco-Germany_kg | I49: 1 | J49: 0 | L49: solely Levelized Cost of Fuel but no taxes or other charges are considered | M49: 0
A51: resource_ammonia_25 | B51: 0 | C51: bus_nh3 | D51: kg | E51: 2025 | F51: 2030 | G51: 0.76 | H51: NH3 wind esp-de_commodity_kg | I51: 1 | J51: 0 | L51: solely Levelized Cost of Fuel but no taxes or other charges are considered | M51: 0 | N51: LCA/Carbon Footprint rather optimistic (solely based on wind)
A52: resource_ammonia_30 | B52: 0 | C52: bus_nh3 | D52: kg | E52: 2030 | F52: 2035 | G52: 0.72 | H52: NH3 wind esp-de_commodity_kg | I52: 1 | J52: 0 | L52: solely Levelized Cost of Fuel but no taxes or other charges are considered | M52: 0
A53: resource_ammonia_35 | B53: 0 | C53: bus_nh3 | D53: kg | E53: 2035 | F53: 2040 | G53: 0.68 | H53: NH3 wind esp-de_commodity_kg | I53: 1 | J53: 0 | L53: solely Levelized Cost of Fuel but no taxes or other charges are considered | M53: 0
A54: resource_ammonia_40 | B54: 0 | C54: bus_nh3 | D54: kg | E54: 2040 | F54: 2045 | G54: 0.64 | H54: NH3 wind esp-de_commodity_kg | I54: 1 | J54: 0 | L54: solely Levelized Cost of Fuel but no taxes or other charges are considered | M54: 0
A55: resource_ammonia_45 | B55: 0 | C55: bus_nh3 | D55: kg | E55: 2045 | F55: 2050 | G55: 0.59 | H55: NH3 wind esp-de_commodity_kg | I55: 1 | J55: 0 | L55: solely Levelized Cost of Fuel but no taxes or other charges are considered | M55: 0
A56: resource_ammonia_50 | B56: 0 | C56: bus_nh3 | D56: kg | E56: 2050 | F56: 2055 | G56: 0.55 | H56: NH3 wind esp-de_commodity_kg | I56: 1 | J56: 0 | L56: solely Levelized Cost of Fuel but no taxes or other charges are considered | M56: 0
A57: resource_ammonia_55 | B57: 0 | C57: bus_nh3 | D57: kg | E57: 2055 | F57: 2060 | G57: 0.55 | H57: NH3 wind esp-de_commodity_kg | I57: 1 | J57: 0 | L57: solely Levelized Cost of Fuel but no taxes or other charges are considered | M57: 0
A58: resource_ammonia_60 | B58: 0 | C58: bus_nh3 | D58: kg | E58: 2060 | F58: 2065 | G58: 0.55 | H58: NH3 wind esp-de_commodity_kg | I58: 1 | J58: 0 | L58: solely Levelized Cost of Fuel but no taxes or other charges are considered | M58: 0
A59: resource_ammonia_65 | B59: 0 | C59: bus_nh3 | D59: kg | E59: 2065 | F59: 2070 | G59: 0.55 | H59: NH3 wind esp-de_commodity_kg | I59: 1 | J59: 0 | L59: solely Levelized Cost of Fuel but no taxes or other charges are considered | M59: 0
A60: resource_ammonia_70 | B60: 0 | C60: bus_nh3 | D60: kg | E60: 2070 | F60: 2075 | G60: 0.55 | H60: NH3 wind esp-de_commodity_kg | I60: 1 | J60: 0 | L60: solely Levelized Cost of Fuel but no taxes or other charges are considered | M60: 0
A62: resource_lohc_25 | B62: 0 | C62: bus_lohc | D62: kg | E62: 2025 | F62: 2030 | G62: 0.26 | H62: LOHC wind esp-de_commodity_kg | I62: 1 | J62: 0 | L62: solely Levelized Cost of Fuel but no taxes or other charges are considered | M62: 0 | N62: LCA/Carbon Footprint rather optimistic (solely based on wind)
A63: resource_lohc_30 | B63: 0 | C63: bus_lohc | D63: kg | E63: 2030 | F63: 2035 | G63: 0.25 | H63: LOHC wind esp-de_commodity_kg | I63: 1 | J63: 0 | L63: solely Levelized Cost of Fuel but no taxes or other charges are considered | M63: 0
A64: resource_lohc_35 | B64: 0 | C64: bus_lohc | D64: kg | E64: 2035 | F64: 2040 | G64: 0.24 | H64: LOHC wind esp-de_commodity_kg | I64: 1 | J64: 0 | L64: solely Levelized Cost of Fuel but no taxes or other charges are considered | M64: 0
A65: resource_lohc_40 | B65: 0 | C65: bus_lohc | D65: kg | E65: 2040 | F65: 2045 | G65: 0.23 | H65: LOHC wind esp-de_commodity_kg | I65: 1 | J65: 0 | L65: solely Levelized Cost of Fuel but no taxes or other charges are considered | M65: 0
A66: resource_lohc_45 | B66: 0 | C66: bus_lohc | D66: kg | E66: 2045 | F66: 2050 | G66: 0.22 | H66: LOHC wind esp-de_commodity_kg | I66: 1 | J66: 0 | L66: solely Levelized Cost of Fuel but no taxes or other charges are considered | M66: 0
A67: resource_lohc_50 | B67: 0 | C67: bus_lohc | D67: kg | E67: 2050 | F67: 2055 | G67: 0.21 | H67: LOHC wind esp-de_commodity_kg | I67: 1 | J67: 0 | L67: solely Levelized Cost of Fuel but no taxes or other charges are considered | M67: 0
A68: resource_lohc_55 | B68: 0 | C68: bus_lohc | D68: kg | E68: 2055 | F68: 2060 | G68: 0.21 | H68: LOHC wind esp-de_commodity_kg | I68: 1 | J68: 0 | L68: solely Levelized Cost of Fuel but no taxes or other charges are considered | M68: 0
A69: resource_lohc_60 | B69: 0 | C69: bus_lohc | D69: kg | E69: 2060 | F69: 2065 | G69: 0.21 | H69: LOHC wind esp-de_commodity_kg | I69: 1 | J69: 0 | L69: solely Levelized Cost of Fuel but no taxes or other charges are considered | M69: 0
A70: resource_lohc_65 | B70: 0 | C70: bus_lohc | D70: kg | E70: 2065 | F70: 2070 | G70: 0.21 | H70: LOHC wind esp-de_commodity_kg | I70: 1 | J70: 0 | L70: solely Levelized Cost of Fuel but no taxes or other charges are considered | M70: 0
A71: resource_lohc_70 | B71: 0 | C71: bus_lohc | D71: kg | E71: 2070 | F71: 2075 | G71: 0.21 | H71: LOHC wind esp-de_commodity_kg | I71: 1 | J71: 0 | L71: solely Levelized Cost of Fuel but no taxes or other charges are considered | M71: 0
A73: resource_ch3oh | B73: 0 | C73: bus_ch3oh | D73: kg | E73: 2025 | F73: 1000000000000 | G73: 0.36 | H73: empty | I73: 1 | J73: 0 | L73: ? | M73: 1
A75: resource_co2 | B75: 0 | C75: bus_co2 | D75: kg | E75: 2025 | F75: 1000000000000 | G75: 0 | H75: empty | I75: 1 | J75: 0 | L75: ? | M75: 1

Sheet demand
A1: label | B1: active | C1: from | D1: nominal value | E1: fixed-flow_periodically_variable | F1: comment
A2: load_el | B2: 1 | C2: bus_el | D2: 1 | E2: 0
A3: load_th_high | B3: 0 | C3: bus_th_high | D3: 1 | E3: 0
A4: load_th_low | B4: 0 | C4: bus_th_low | D4: 1 | E4: 0
A5: load_th | B5: 0 | C5: bus_th | D5: 1 | E5: 0
A7: load_hydrogen | B7: 1 | C7: bus_hydrogen | D7: 1 | E7: 0
A8: load_h2_export | B8: 0 | C8: bus_h2_300bar | D8: 1 | E8: 0
A9: load_steamSite | B9: 1 | C9: bus_steam7,5bar | D9: 1 | E9: 0
A10: load_methanol | B10: 0 | C10: bus_ch3oh | D10: 1 | E10: 0
A12: load-households_el | B12: 0 | C12: bus_el | D12: 1 | E12: 0
A13: load-households_th | B13: 0 | C13: bus_th_households | D13: 1 | E13: 0

Sheet renewables
A1: label | B1: active | C1: to | D1: unit | E1: initial_existance | F1: initially_installed_capacity | G1: year_of_availability | H1: end_of_availability | I1: variable_costs | J1: var_env1 | K1: var_env1_conversion | L1: om | M1: invest | N1: lifetime | O1: max_capacity_invest | P1: max_total_capacity | Q1: inv1 | R1: inv1_conversion | S1: fixed | T1: fixed-flow_periodically_variable | U1: info1 | V1: info2 | W1: info3 | Y1: comment | AA1: Dropdown list | AB1: Dropdown list | AC1: Dropdown list
U2: eg. turbine type | V2: e.g. hub height | W2: e.g. WPP capacity
A3: PV_flat_roof | B3: 0 | C3: bus_el | D3: kWp | E3: 0 | F3: 0 | G3: 0 | H3: 1000000000000 | I3: 0 | J3: empty | K3: 1 | L3: =0.02*M3 -> 41.174 | M3: =(1730*1.19) -> 2058.7 | N3: 25 | O3: 1000000000000 | P3: 1000000 | Q3: production, PV, flat-roof installation, 156kWp, cryst_2021_kW | R3: 1 | S3: 1 | AB3: construction, wind turbine, 6kW, onshore_kW | AC3: production, PV, facade installation, 3kWp, cryst_2021_kW
A5: PV_facade | B5: 0 | C5: bus_el | D5: kWp | E5: 0 | F5: 0 | G5: 0 | H5: 1000000000000 | I5: 0 | J5: empty | K5: 1 | L5: =L3 -> 41.174 | M5: =2*M3 -> 4117.4 | N5: 25 | O5: 1000000000000 | P5: 1000000 | Q5: production, PV, facade installation, 3kWp, crist_kW | R5: 1 | S5: 1 | AB5: construction, wind turbine, 3.2MW, DDPMSG, onshore_kW | AC5: production, PV, slanted-roof installation, 3kWp, cryst_2021_kW
A6: PV_roof | B6: 0 | C6: bus_el | D6: kW | E6: 0 | F6: 0 | G6: 0 | H6: 1000000000000 | I6: 0 | J6: empty | K6: 1 | L6: =0.02*M6 -> 41.174 | M6: =(1730*1.19) -> 2058.7 | N6: 25 | O6: 1000000000000 | P6: 1000000 | Q6: production, PV, slanted-roof installation, 3kWp, cryst_2021_kW | R6: 1 | S6: 1 | AB6: construction, wind turbine, 3.3MW, DFIG, onshore_kW | AC6: production, ,PV, slanted-roof installation, 3kWp, CIS_kW
A7: ambient_heat_ground | B7: 0 | C7: bus_th_ambient | D7: kW | E7: 0 | F7: 0 | G7: 0 | H7: 1000000000000 | I7: 0 | J7: empty | K7: 1 | L7: 0 | M7: =100*R7 -> 1818.1818 | N7: 50 | O7: 1000000000000 | P7: 1000000 | Q7: construction, borehole heat exchanger, investment_m | R7: =1/Y7 -> 18.181818 | S7: 0 | Y7: 0.055 | Z7: kW/m lt. Energiekonzept "Am Horn" S. 20 | AB7: construction, wind turbne, 3.2 MW, DDSG, DDPMSG, DFIG, onshore_kW | AC7: production, PV, slanted-roof installation, 3kWp, CdTe_kW
A8: solar_thermal_FPC | B8: 0 | C8: bus_th | D8: m² | E8: 0 | F8: 0 | G8: 0 | H8: 1000000000000 | I8: 0 | J8: empty | K8: 1 | L8: 11 | M8: 526 | N8: 20 | O8: 1000000000000 | P8: 1000000 | Q8: production, solar collector system, Cu flat plate collector, multiple dwelling, for combined system, investment_m2 | R8: 1 | S8: 1 | Y8: 0.5 kW/m² | Z8: invest: invest kosten + maintenance/leistung | AB8: construction, wind turbine, onshore_kW | AC8: construction, photovoltaic plant, 570kWp open ground, cryst_2021_kW
A9: solar_thermal_FPC_low | B9: 0 | C9: bus_th_low | D9: m² | E9: 0 | F9: 0 | G9: 0 | H9: 1000000000000 | I9: 0 | J9: empty | K9: 1 | L9: 11 | M9: 526 | N9: 20 | O9: 1000000000000 | P9: 1000000 | Q9: production, solar collector system, Cu flat plate collector, multiple dwelling, for combined system, investment_m2 | R9: 1 | S9: 1 | AC9: construction, photovoltaic plant, 570kWp open ground, CdTE_kW
A10: solar_thermal_FPC_high | B10: 0 | C10: bus_th_high | D10: m² | E10: 0 | F10: 0 | G10: 0 | H10: 1000000000000 | I10: 0 | J10: empty | K10: 1 | L10: 11 | M10: 526 | N10: 20 | O10: 1000000000000 | P10: 1000000 | Q10: production, solar collector system, Cu flat plate collector, multiple dwelling, for combined system, investment_m2 | R10: 1 | S10: 1 | AC10: construction, photovoltaic plant, 1.3MWp, open ground, cryst-Si_2021_kW
AC11: construction, photovoltaic plant, 1.3MWp open ground, CdTe_kW
A12: PV_og_existing | B12: 0 | C12: bus_el | D12: kWp | E12: 1 | F12: 1000 | G12: 0 | H12: 1000000000000 | I12: 0 | J12: empty | K12: 1 | L12: =0.025*M12 -> 0 | M12: 0 | N12: 3 | O12: 0 | P12: 1000 | Q12: empty | R12: =1/3 -> 0.33333333 | S12: 1 | T12: 0
A14: PV_og_25 | B14: 1 | C14: bus_el-re | D14: kWp | E14: 0 | F14: 0 | G14: 0 | H14: 2030 | I14: 0 | J14: empty | K14: 1 | L14: =$L$23 -> 10.7 | M14: 509 | N14: =$N$23 -> 20 | O14: 1000000 | P14: =$P$23 -> 1000000 | Q14: PV_og plant construction, 570kWp, multi-Si | R14: =1/570 -> 0.001754386 | S14: 1 | T14: 0 | Y14: source costs: Langfristszenarien, 750 kW plant | AB14: construction, wind turbine, 3MW, DDSG, onshore_kW | AC14: production, PV, facade installation, 3kWp, cryst_2021_kW_minus_facade_mat
A15: PV_og_30 | B15: 1 | C15: bus_el-re | D15: kWp | E15: 0 | F15: 0 | G15: 2030 | H15: 2035 | I15: 0 | J15: empty | K15: 1 | L15: =$L$23 -> 10.7 | M15: 430 | N15: =$N$23 -> 20 | O15: 1000000 | P15: =$P$23 -> 1000000 | Q15: PV_og plant construction, 570kWp, multi-Si | R15: =1/570 -> 0.001754386 | S15: 1 | T15: 0 | Y15: construction LCA is probably too pessimistic
A16: PV_og_35 | B16: 1 | C16: bus_el-re | D16: kWp | E16: 0 | F16: 0 | G16: 2035 | H16: 2040 | I16: 0 | J16: empty | K16: 1 | L16: =$L$23 -> 10.7 | M16: 392 | N16: =$N$23 -> 20 | O16: 1000000 | P16: =$P$23 -> 1000000 | Q16: PV_og plant construction, 570kWp, multi-Si | R16: =1/570 -> 0.001754386 | S16: 1 | T16: 0
A17: PV_og_40 | B17: 1 | C17: bus_el-re | D17: kWp | E17: 0 | F17: 0 | G17: 2040 | H17: 2045 | I17: 0 | J17: empty | K17: 1 | L17: =$L$23 -> 10.7 | M17: 369 | N17: =$N$23 -> 20 | O17: 1000000 | P17: =$P$23 -> 1000000 | Q17: PV_og plant construction, 570kWp, multi-Si | R17: =1/570 -> 0.001754386 | S17: 1 | T17: 0
A18: PV_og_45 | B18: 1 | C18: bus_el-re | D18: kWp | E18: 0 | F18: 0 | G18: 2045 | H18: 2050 | I18: 0 | J18: empty | K18: 1 | L18: =$L$23 -> 10.7 | M18: 356 | N18: =$N$23 -> 20 | O18: 1000000 | P18: =$P$23 -> 1000000 | Q18: PV_og plant construction, 570kWp, multi-Si | R18: =1/570 -> 0.001754386 | S18: 1 | T18: 0
A19: PV_og_50 | B19: 1 | C19: bus_el-re | D19: kWp | E19: 0 | F19: 0 | G19: 2050 | H19: 2055 | I19: 0 | J19: empty | K19: 1 | L19: =$L$23 -> 10.7 | M19: 347 | N19: =$N$23 -> 20 | O19: 1000000 | P19: =$P$23 -> 1000000 | Q19: PV_og plant construction, 570kWp, multi-Si | R19: =1/570 -> 0.001754386 | S19: 1 | T19: 0
A20: PV_og_55 | B20: 1 | C20: bus_el-re | D20: kWp | E20: 0 | F20: 0 | G20: 2055 | H20: 2060 | I20: 0 | J20: empty | K20: 1 | L20: =$L$23 -> 10.7 | M20: 347 | N20: =$N$23 -> 20 | O20: 1000000 | P20: =$P$23 -> 1000000 | Q20: PV_og plant construction, 570kWp, multi-Si | R20: =1/570 -> 0.001754386 | S20: 1 | T20: 0
A21: PV_og_60 | B21: 1 | C21: bus_el-re | D21: kWp | E21: 0 | F21: 0 | G21: 2060 | H21: 2065 | I21: 0 | J21: empty | K21: 1 | L21: =$L$23 -> 10.7 | M21: 347 | N21: =$N$23 -> 20 | O21: 1000000 | P21: =$P$23 -> 1000000 | Q21: PV_og plant construction, 570kWp, multi-Si | R21: =1/570 -> 0.001754386 | S21: 1 | T21: 0
A22: PV_og_65 | B22: 1 | C22: bus_el-re | D22: kWp | E22: 0 | F22: 0 | G22: 2065 | H22: 2070 | I22: 0 | J22: empty | K22: 1 | L22: =$L$23 -> 10.7 | M22: 347 | N22: =$N$23 -> 20 | O22: 1000000 | P22: =$P$23 -> 1000000 | Q22: PV_og plant construction, 570kWp, multi-Si | R22: =1/570 -> 0.001754386 | S22: 1 | T22: 0
A23: PV_og_70 | B23: 1 | C23: bus_el-re | D23: kWp | E23: 0 | F23: 0 | G23: 2070 | H23: 2075 | I23: 0 | J23: empty | K23: 1 | L23: 10.7 | M23: 347 | N23: 20 | O23: 1000000 | P23: 1000000 | Q23: PV_og plant construction, 570kWp, multi-Si | R23: =1/570 -> 0.001754386 | S23: 1 | T23: 0
A25: windon_25 | B25: 1 | C25: bus_el-re | D25: kW | E25: 0 | F25: 0 | G25: 0 | H25: 2030 | I25: 0 | J25: =IF(Q25=AB25,AA25,"empty") -> empty | K25: 1 | L25: =$L$34 -> 20.6 | M25: 1453 | N25: =$N$34 -> 20 | O25: =$P$34 -> 50000 | P25: =$P$34 -> 50000 | Q25: market for wind turbine, 4.5MW, onshore | R25: =1/4500 -> 0.00022222222 | S25: 1 | U25: V126/3300 | V25: 150 | W25: 3300 | Y25: source costs: Langfristszenarien, 150m hub height, 280 W/m² | AA25: electricity, wind, max 1MW turbine, onshore, variable_kWh | AB25: construction, wind, max 1MW turbine, onshore, investment_kW | AC25: procution, PV, flat-roof installation, 156kWp, cryst_2021_kW
A26: windon_30 | B26: 1 | C26: bus_el-re | D26: kW | E26: 0 | F26: 0 | G26: 2030 | H26: 2035 | I26: 0 | J26: empty | K26: 1 | L26: =$L$34 -> 20.6 | M26: 1387 | N26: =$N$34 -> 20 | O26: =$P$34 -> 50000 | P26: =$P$34 -> 50000 | Q26: market for wind turbine, 4.5MW, onshore | R26: =1/4500 -> 0.00022222222 | S26: 1 | U26: V126/3300 | V26: 150 | W26: 3300 | Y26: construction LCA is probably too pessimistic
A27: windon_35 | B27: 1 | C27: bus_el-re | D27: kW | E27: 0 | F27: 0 | G27: 2035 | H27: 2040 | I27: 0 | J27: empty | K27: 1 | L27: =$L$34 -> 20.6 | M27: 1349 | N27: =$N$34 -> 20 | O27: =$P$34 -> 50000 | P27: =$P$34 -> 50000 | Q27: market for wind turbine, 4.5MW, onshore | R27: =1/4500 -> 0.00022222222 | S27: 1 | U27: V126/3300 | V27: 150 | W27: 3300
A28: windon_40 | B28: 1 | C28: bus_el-re | D28: kW | E28: 0 | F28: 0 | G28: 2040 | H28: 2045 | I28: 0 | J28: empty | K28: 1 | L28: =$L$34 -> 20.6 | M28: 1326 | N28: =$N$34 -> 20 | O28: =$P$34 -> 50000 | P28: =$P$34 -> 50000 | Q28: market for wind turbine, 4.5MW, onshore | R28: =1/4500 -> 0.00022222222 | S28: 1 | U28: V126/3300 | V28: 150 | W28: 3300
A29: windon_45 | B29: 1 | C29: bus_el-re | D29: kW | E29: 0 | F29: 0 | G29: 2045 | H29: 2050 | I29: 0 | J29: empty | K29: 1 | L29: =$L$34 -> 20.6 | M29: 1311 | N29: =$N$34 -> 20 | O29: =$P$34 -> 50000 | P29: =$P$34 -> 50000 | Q29: market for wind turbine, 4.5MW, onshore | R29: =1/4500 -> 0.00022222222 | S29: 1 | U29: V126/3300 | V29: 150 | W29: 3300
A30: windon_50 | B30: 1 | C30: bus_el-re | D30: kW | E30: 0 | F30: 0 | G30: 2050 | H30: 2055 | I30: 0 | J30: empty | K30: 1 | L30: =$L$34 -> 20.6 | M30: 1301 | N30: =$N$34 -> 20 | O30: =$P$34 -> 50000 | P30: =$P$34 -> 50000 | Q30: market for wind turbine, 4.5MW, onshore | R30: =1/4500 -> 0.00022222222 | S30: 1 | U30: V126/3300 | V30: 150 | W30: 3300
A31: windon_55 | B31: 1 | C31: bus_el-re | D31: kW | E31: 0 | F31: 0 | G31: 2055 | H31: 2060 | I31: 0 | J31: empty | K31: 1 | L31: =$L$34 -> 20.6 | M31: 1301 | N31: =$N$34 -> 20 | O31: =$P$34 -> 50000 | P31: =$P$34 -> 50000 | Q31: market for wind turbine, 4.5MW, onshore | R31: =1/4500 -> 0.00022222222 | S31: 1 | U31: V126/3300 | V31: 150 | W31: 3300
A32: windon_60 | B32: 1 | C32: bus_el-re | D32: kW | E32: 0 | F32: 0 | G32: 2060 | H32: 2065 | I32: 0 | J32: empty | K32: 1 | L32: =$L$34 -> 20.6 | M32: 1301 | N32: =$N$34 -> 20 | O32: =$P$34 -> 50000 | P32: =$P$34 -> 50000 | Q32: market for wind turbine, 4.5MW, onshore | R32: =1/4500 -> 0.00022222222 | S32: 1 | U32: V126/3300 | V32: 150 | W32: 3300
A33: windon_65 | B33: 1 | C33: bus_el-re | D33: kW | E33: 0 | F33: 0 | G33: 2065 | H33: 2070 | I33: 0 | J33: empty | K33: 1 | L33: =$L$34 -> 20.6 | M33: 1301 | N33: =$N$34 -> 20 | O33: =$P$34 -> 50000 | P33: =$P$34 -> 50000 | Q33: market for wind turbine, 4.5MW, onshore | R33: =1/4500 -> 0.00022222222 | S33: 1 | U33: V126/3300 | V33: 150 | W33: 3300
A34: windon_70 | B34: 1 | C34: bus_el-re | D34: kW | E34: 0 | F34: 0 | G34: 2070 | H34: 2075 | I34: 0 | J34: empty | K34: 1 | L34: 20.6 | M34: 1301 | N34: 20 | O34: =$P$34 -> 50000 | P34: 50000 | Q34: market for wind turbine, 4.5MW, onshore | R34: =1/4500 -> 0.00022222222 | S34: 1 | U34: V126/3300 | V34: 150 | W34: 3300
A36: windoff_25 | B36: 1 | C36: bus_el-over | D36: kW | E36: 0 | F36: 0 | G36: 0 | H36: 2030 | I36: 0 | J36: empty | K36: 1 | L36: =$L$45 -> 58.9 | M36: 3466 | N36: =$N$45 -> 20 | O36: 1000000 | P36: =$P$45 -> 1000000 | Q36: wind turbine offshore, 2MW | R36: =1/2000 -> 0.0005 | S36: 1 | U36: V164/8000 | V36: 150 | W36: 8000 | Y36: source costs: Langfristszenarien, 160m hub height, 350 W/m²
A37: windoff_30 | B37: 1 | C37: bus_el-over | D37: kW | E37: 0 | F37: 0 | G37: 2030 | H37: 2035 | I37: 0 | J37: empty | K37: 1 | L37: =$L$45 -> 58.9 | M37: 3438 | N37: =$N$45 -> 20 | O37: 1000000 | P37: =$P$45 -> 1000000 | Q37: wind turbine offshore, 2MW | R37: =1/2000 -> 0.0005 | S37: 1 | U37: V164/8000 | V37: 150 | W37: 8000 | Y37: attention: actually, price is also dependent on water depth and distance to next coast
A38: windoff_35 | B38: 1 | C38: bus_el-over | D38: kW | E38: 0 | F38: 0 | G38: 2035 | H38: 2040 | I38: 0 | J38: empty | K38: 1 | L38: =$L$45 -> 58.9 | M38: 3394 | N38: =$N$45 -> 20 | O38: 1000000 | P38: =$P$45 -> 1000000 | Q38: wind turbine offshore, 2MW | R38: =1/2000 -> 0.0005 | S38: 1 | U38: V164/8000 | V38: 150 | W38: 8000
A39: windoff_40 | B39: 1 | C39: bus_el-over | D39: kW | E39: 0 | F39: 0 | G39: 2040 | H39: 2045 | I39: 0 | J39: empty | K39: 1 | L39: =$L$45 -> 58.9 | M39: 3348 | N39: =$N$45 -> 20 | O39: 1000000 | P39: =$P$45 -> 1000000 | Q39: wind turbine offshore, 2MW | R39: =1/2000 -> 0.0005 | S39: 1 | U39: V164/8000 | V39: 150 | W39: 8000
A40: windoff_45 | B40: 1 | C40: bus_el-over | D40: kW | E40: 0 | F40: 0 | G40: 2045 | H40: 2050 | I40: 0 | J40: empty | K40: 1 | L40: =$L$45 -> 58.9 | M40: 3309 | N40: =$N$45 -> 20 | O40: 1000000 | P40: =$P$45 -> 1000000 | Q40: wind turbine offshore, 2MW | R40: =1/2000 -> 0.0005 | S40: 1 | U40: V164/8000 | V40: 150 | W40: 8000
A41: windoff_50 | B41: 1 | C41: bus_el-over | D41: kW | E41: 0 | F41: 0 | G41: 2050 | H41: 2055 | I41: 0 | J41: empty | K41: 1 | L41: =$L$45 -> 58.9 | M41: 3271 | N41: =$N$45 -> 20 | O41: 1000000 | P41: =$P$45 -> 1000000 | Q41: wind turbine offshore, 2MW | R41: =1/2000 -> 0.0005 | S41: 1 | U41: V164/8000 | V41: 150 | W41: 8000
A42: windoff_55 | B42: 1 | C42: bus_el-over | D42: kW | E42: 0 | F42: 0 | G42: 2055 | H42: 2060 | I42: 0 | J42: empty | K42: 1 | L42: =$L$45 -> 58.9 | M42: 3271 | N42: =$N$45 -> 20 | O42: 1000000 | P42: =$P$45 -> 1000000 | Q42: wind turbine offshore, 2MW | R42: =1/2000 -> 0.0005 | S42: 1 | U42: V164/8000 | V42: 150 | W42: 8000
A43: windoff_60 | B43: 1 | C43: bus_el-over | D43: kW | E43: 0 | F43: 0 | G43: 2060 | H43: 2065 | I43: 0 | J43: empty | K43: 1 | L43: =$L$45 -> 58.9 | M43: 3271 | N43: =$N$45 -> 20 | O43: 1000000 | P43: =$P$45 -> 1000000 | Q43: wind turbine offshore, 2MW | R43: =1/2000 -> 0.0005 | S43: 1 | U43: V164/8000 | V43: 150 | W43: 8000
A44: windoff_65 | B44: 1 | C44: bus_el-over | D44: kW | E44: 0 | F44: 0 | G44: 2065 | H44: 2070 | I44: 0 | J44: empty | K44: 1 | L44: =$L$45 -> 58.9 | M44: 3271 | N44: =$N$45 -> 20 | O44: 1000000 | P44: =$P$45 -> 1000000 | Q44: wind turbine offshore, 2MW | R44: =1/2000 -> 0.0005 | S44: 1 | U44: V164/8000 | V44: 150 | W44: 8000
A45: windoff_70 | B45: 1 | C45: bus_el-over | D45: kW | E45: 0 | F45: 0 | G45: 2070 | H45: 2075 | I45: 0 | J45: empty | K45: 1 | L45: 58.9 | M45: 3271 | N45: 20 | O45: 1000000 | P45: 1000000 | Q45: wind turbine offshore, 2MW | R45: =1/2000 -> 0.0005 | S45: 1 | U45: V164/8000 | V45: 150 | W45: 8000
A47: band-pip_25 | B47: 1 | C47: bus_hydrogen | D47: kg/h | E47: 0 | F47: 0 | G47: 0 | H47: 2030 | I47: 0 | J47: hydrogen pipeline import, Morocco-Germany_kg | K47: 1 | L47: 0 | M47: 200000 | N47: 5 | O47: 0 | P47: =$P$53 -> 1000000 | Q47: empty | R47: 1 | S47: 1 | T47: 0
A48: band-pip_30 | B48: 1 | C48: bus_hydrogen | D48: kg/h | E48: 0 | F48: 0 | G48: 2030 | H48: 2035 | I48: 0 | J48: hydrogen pipeline import, Morocco-Germany_kg | K48: 1 | L48: 0 | M48: 200000 | N48: 5 | O48: 0 | P48: =$P$53 -> 1000000 | Q48: empty | R48: 1 | S48: 1 | T48: 0
A49: band-pip_35 | B49: 1 | C49: bus_hydrogen | D49: kg/h | E49: 0 | F49: 0 | G49: 2035 | H49: 2040 | I49: 0 | J49: hydrogen pipeline import, Morocco-Germany_kg | K49: 1 | L49: 0 | M49: 170783.7 | N49: 5 | O49: 1000000 | P49: =$P$53 -> 1000000 | Q49: empty | R49: 1 | S49: 1 | T49: 0
A50: band-pip_40 | B50: 1 | C50: bus_hydrogen | D50: kg/h | E50: 0 | F50: 0 | G50: 2040 | H50: 2045 | I50: 0 | J50: hydrogen pipeline import, Morocco-Germany_kg | K50: 1 | L50: 0 | M50: 160613.8 | N50: 5 | O50: 1000000 | P50: =$P$53 -> 1000000 | Q50: empty | R50: 1 | S50: 1 | T50: 0
A51: band-pip_45 | B51: 1 | C51: bus_hydrogen | D51: kg/h | E51: 0 | F51: 0 | G51: 2045 | H51: 2050 | I51: 0 | J51: hydrogen pipeline import, Morocco-Germany_kg | K51: 1 | L51: 0 | M51: 150444 | N51: 5 | O51: 1000000 | P51: =$P$53 -> 1000000 | Q51: empty | R51: 1 | S51: 1 | T51: 0
A52: band-pip_50 | B52: 1 | C52: bus_hydrogen | D52: kg/h | E52: 0 | F52: 0 | G52: 2050 | H52: 2055 | I52: 0 | J52: hydrogen pipeline import, Morocco-Germany_kg | K52: 1 | L52: 0 | M52: 140274 | N52: 5 | O52: 1000000 | P52: =$P$53 -> 1000000 | Q52: empty | R52: 1 | S52: 1 | T52: 0
A53: band-pip_55 | B53: 1 | C53: bus_hydrogen | D53: kg/h | E53: 0 | F53: 0 | G53: 2055 | H53: 2060 | I53: 0 | J53: hydrogen pipeline import, Morocco-Germany_kg | K53: 1 | L53: 0 | M53: 140274 | N53: 5 | O53: 1000000 | P53: 1000000 | Q53: empty | R53: 1 | S53: 1 | T53: 0
A55: band-nh3_25 | B55: 1 | C55: bus_nh3 | D55: kg/h | E55: 0 | F55: 0 | G55: 0 | H55: 2030 | I55: 0 | J55: NH3 wind esp-de_commodity_kg | K55: 1 | L55: 0 | M55: 26652.1 | N55: 5 | O55: 1000000 | P55: =$P$60 -> 1000000 | Q55: empty | R55: 1 | S55: 1 | T55: 0
A56: band-nh3_30 | B56: 1 | C56: bus_nh3 | D56: kg/h | E56: 0 | F56: 0 | G56: 2030 | H56: 2035 | I56: 0 | J56: NH3 wind esp-de_commodity_kg | K56: 1 | L56: 0 | M56: 25249.3 | N56: 5 | O56: 1000000 | P56: =$P$60 -> 1000000 | Q56: empty | R56: 1 | S56: 1 | T56: 0
A57: band-nh3_35 | B57: 1 | C57: bus_nh3 | D57: kg/h | E57: 0 | F57: 0 | G57: 2035 | H57: 2040 | I57: 0 | J57: NH3 wind esp-de_commodity_kg | K57: 1 | L57: 0 | M57: 23846.6 | N57: 5 | O57: 1000000 | P57: =$P$60 -> 1000000 | Q57: empty | R57: 1 | S57: 1 | T57: 0
A58: band-nh3_40 | B58: 1 | C58: bus_nh3 | D58: kg/h | E58: 0 | F58: 0 | G58: 2040 | H58: 2045 | I58: 0 | J58: NH3 wind esp-de_commodity_kg | K58: 1 | L58: 0 | M58: 22443.9 | N58: 5 | O58: 1000000 | P58: =$P$60 -> 1000000 | Q58: empty | R58: 1 | S58: 1 | T58: 0
A59: band-nh3_45 | B59: 1 | C59: bus_nh3 | D59: kg/h | E59: 0 | F59: 0 | G59: 2045 | H59: 2050 | I59: 0 | J59: NH3 wind esp-de_commodity_kg | K59: 1 | L59: 0 | M59: 20690.4 | N59: 5 | O59: 1000000 | P59: =$P$60 -> 1000000 | Q59: empty | R59: 1 | S59: 1 | T59: 0
A60: band-nh3_50 | B60: 1 | C60: bus_nh3 | D60: kg/h | E60: 0 | F60: 0 | G60: 2050 | H60: 2055 | I60: 0 | J60: NH3 wind esp-de_commodity_kg | K60: 1 | L60: 0 | M60: 19287.7 | N60: 5 | O60: 1000000 | P60: 1000000 | Q60: empty | R60: 1 | S60: 1 | T60: 0
A62: band-lohc_25 | B62: 1 | C62: bus_lohc | D62: kg/h | E62: 0 | F62: 0 | G62: 0 | H62: 2030 | I62: 0 | J62: LOHC wind esp-de_commodity_kg | K62: 1 | L62: 0 | M62: 9117.8 | N62: 5 | O62: 1000000 | P62: =$P$67 -> 1000000 | Q62: empty | R62: 1 | S62: 1 | T62: 0
A63: band-lohc_30 | B63: 1 | C63: bus_lohc | D63: kg/h | E63: 0 | F63: 0 | G63: 2030 | H63: 2035 | I63: 0 | J63: LOHC wind esp-de_commodity_kg | K63: 1 | L63: 0 | M63: 8767.1 | N63: 5 | O63: 1000000 | P63: =$P$67 -> 1000000 | Q63: empty | R63: 1 | S63: 1 | T63: 0
A64: band-lohc_35 | B64: 1 | C64: bus_lohc | D64: kg/h | E64: 0 | F64: 0 | G64: 2035 | H64: 2040 | I64: 0 | J64: LOHC wind esp-de_commodity_kg | K64: 1 | L64: 0 | M64: 8416.4 | N64: 5 | O64: 1000000 | P64: =$P$67 -> 1000000 | Q64: empty | R64: 1 | S64: 1 | T64: 0
A65: band-lohc_40 | B65: 1 | C65: bus_lohc | D65: kg/h | E65: 0 | F65: 0 | G65: 2040 | H65: 2045 | I65: 0 | J65: LOHC wind esp-de_commodity_kg | K65: 1 | L65: 0 | M65: 8065.8 | N65: 5 | O65: 1000000 | P65: =$P$67 -> 1000000 | Q65: empty | R65: 1 | S65: 1 | T65: 0
A66: band-lohc_45 | B66: 1 | C66: bus_lohc | D66: kg/h | E66: 0 | F66: 0 | G66: 2045 | H66: 2050 | I66: 0 | J66: LOHC wind esp-de_commodity_kg | K66: 1 | L66: 0 | M66: 7715 | N66: 5 | O66: 1000000 | P66: =$P$67 -> 1000000 | Q66: empty | R66: 1 | S66: 1 | T66: 0
A67: band-lohc_50 | B67: 1 | C67: bus_lohc | D67: kg/h | E67: 0 | F67: 0 | G67: 2050 | H67: 2055 | I67: 0 | J67: LOHC wind esp-de_commodity_kg | K67: 1 | L67: 0 | M67: 7364.4 | N67: 5 | O67: 1000000 | P67: 1000000 | Q67: empty | R67: 1 | S67: 1 | T67: 0
A69: band-ch4_25 | B69: 1 | C69: bus_nat_gas | D69: kWh | E69: 0 | F69: 0 | G69: 0 | H69: 2030 | I69: 0 | J69: market for natural gas, high pressure_commodity_DE_m3 | K69: =1/(36/3.6) -> 0.1 | L69: 0 | M69: =-PV(0.079,N69,commodity_sources!G13*8760) -> 1472.8778 | N69: 5 | O69: 1000000 | P69: =$P$74 -> 1000000 | Q69: empty | R69: 1 | S69: 1 | T69: 0
A70: band-ch4_30 | B70: 1 | C70: bus_nat_gas | D70: kWh | E70: 0 | F70: 0 | G70: 2030 | H70: 2035 | I70: 0 | J70: market for natural gas, high pressure_commodity_DE_m3 | K70: =1/(36/3.6) -> 0.1 | L70: 0 | M70: =-PV(0.079,N70,commodity_sources!G14*8760) -> 1052.0555 | N70: 5 | O70: 1000000 | P70: =$P$74 -> 1000000 | Q70: empty | R70: 1 | S70: 1 | T70: 0
A71: band-ch4_35 | B71: 1 | C71: bus_nat_gas | D71: kWh | E71: 0 | F71: 0 | G71: 2035 | H71: 2040 | I71: 0 | J71: market for natural gas, high pressure_commodity_DE_m3 | K71: =1/(36/3.6) -> 0.1 | L71: 0 | M71: =-PV(0.079,N71,commodity_sources!G15*8760) -> 666.30184 | N71: 5 | O71: 1000000 | P71: =$P$74 -> 1000000 | Q71: empty | R71: 1 | S71: 1 | T71: 0
A72: band-ch4_40 | B72: 1 | C72: bus_nat_gas | D72: kWh | E72: 0 | F72: 0 | G72: 2040 | H72: 2045 | I72: 0 | J72: market for natural gas, high pressure_commodity_DE_m3 | K72: =1/(36/3.6) -> 0.1 | L72: 0 | M72: =-PV(0.079,N72,commodity_sources!G16*8760) -> 666.30184 | N72: 5 | O72: 1000000 | P72: =$P$74 -> 1000000 | Q72: empty | R72: 1 | S72: 1 | T72: 0
A73: band-ch4_45 | B73: 1 | C73: bus_nat_gas | D73: kWh | E73: 0 | F73: 0 | G73: 2045 | H73: 2050 | I73: 0 | J73: market for natural gas, high pressure_commodity_DE_m3 | K73: =1/(36/3.6) -> 0.1 | L73: 0 | M73: 5000 | N73: 5 | O73: 0 | P73: =$P$74 -> 1000000 | Q73: empty | R73: 1 | S73: 1 | T73: 0
A74: band-ch4_50 | B74: 1 | C74: bus_nat_gas | D74: kWh | E74: 0 | F74: 0 | G74: 2050 | H74: 2055 | I74: 0 | J74: market for natural gas, high pressure_commodity_DE_m3 | K74: =1/(36/3.6) -> 0.1 | L74: 0 | M74: 5000 | N74: 5 | O74: 0 | P74: 1000000 | Q74: empty | R74: 1 | S74: 1 | T74: 0
A76: band-el_25 | B76: 0 | C76: bus_el-grid | D76: kWh | E76: 0 | F76: 0 | G76: 0 | H76: 2030 | I76: 0 | J76: el_mix_DE_2025_kWh | K76: 1 | L76: 0 | M76: =-PV(0.079,N76,commodity_sources!G2*8760) -> 3506.8518 | N76: 5 | O76: 1000000 | P76: =$P$81 -> 1000000 | Q76: empty | R76: 1 | S76: 1 | T76: 0
A77: band-el_30 | B77: 0 | C77: bus_el-grid | D77: kWh | E77: 0 | F77: 0 | G77: 2030 | H77: 2035 | I77: 0 | J77: el_mix_DE_2030_kWh | K77: 1 | L77: 0 | M77: =-PV(0.079,N77,commodity_sources!G3*8760) -> 2805.4814 | N77: 5 | O77: 1000000 | P77: =$P$81 -> 1000000 | Q77: empty | R77: 1 | S77: 1 | T77: 0
A78: band-el_35 | B78: 0 | C78: bus_el-grid | D78: kWh | E78: 0 | F78: 0 | G78: 2035 | H78: 2040 | I78: 0 | J78: el_mix_DE_2035_kWh | K78: 1 | L78: 0 | M78: =-PV(0.079,N78,commodity_sources!G4*8760) -> 2454.7963 | N78: 5 | O78: 1000000 | P78: =$P$81 -> 1000000 | Q78: empty | R78: 1 | S78: 1 | T78: 0
A79: band-el_40 | B79: 0 | C79: bus_el-grid | D79: kWh | E79: 0 | F79: 0 | G79: 2040 | H79: 2045 | I79: 0 | J79: el_mix_DE_2040_kWh | K79: 1 | L79: 0 | M79: =-PV(0.079,N79,commodity_sources!G5*8760) -> 2104.1111 | N79: 5 | O79: 1000000 | P79: =$P$81 -> 1000000 | Q79: empty | R79: 1 | S79: 1 | T79: 0
A80: band-el_45 | B80: 0 | C80: bus_el-grid | D80: kWh | E80: 0 | F80: 0 | G80: 2045 | H80: 2050 | I80: 0 | J80: el_mix_DE_2045_kWh | K80: 1 | L80: 0 | M80: =-PV(0.079,N80,commodity_sources!G6*8760) -> 1928.7685 | N80: 5 | O80: 1000000 | P80: =$P$81 -> 1000000 | Q80: empty | R80: 1 | S80: 1 | T80: 0
A81: band-el_50 | B81: 0 | C81: bus_el-grid | D81: kWh | E81: 0 | F81: 0 | G81: 2050 | H81: 2055 | I81: 0 | J81: el_mix_DE_2045_kWh | K81: 1 | L81: 0 | M81: =-PV(0.079,N81,commodity_sources!G7*8760) -> 1928.7685 | N81: 5 | O81: 1000000 | P81: 1000000 | Q81: empty | R81: 1 | S81: 1 | T81: 0

Sheet storages
A1: label | B1: active | C1: bus | D1: unit | E1: initial_existance | F1: initially_installed_capacity | G1: year_of_availability | H1: end_of_availability | I1: balanced | J1: capacity loss | K1: efficiency inflow | L1: efficiency outflow | M1: initial capacity | N1: capacity min | O1: capacity max | P1: invest_relation_input_capacity | Q1: invest_relation_output_capacity | R1: variable_input_costs | S1: variable_output_costs | T1: max_capacity_invest | U1: max_total_capacity | V1: inv1 | W1: inv1_conversion | X1: om | Y1: invest | Z1: lifetime | AA1: comment
A2: batt_VRF | B2: 0 | C2: bus_el | D2: kWh | E2: 0 | F2: 0 | G2: 0 | H2: 1000000 | I2: 0 | J2: 0.02 | K2: 0.965 | L2: =0.83*K2 -> 0.80095 | M2: 0 | N2: 0.15 | O2: 0.85 | P2: 0.25 | Q2: 0.25 | R2: 0 | S2: 0 | T2: 1000000 | U2: 1000000 | V2: production, stationary battery, VRF (19.4 Wh effective per kg), investment_kWh | W2: 1 | X2: 25 | Y2: 833 | Z2: 20
A3: heat_storage_high | B3: 0 | C3: bus_th_high | D3: kWh | E3: 0 | F3: 0 | G3: 0 | H3: 1000000 | I3: 0 | J3: 0.00015850428 | K3: 1 | L3: =0.81^0.5 -> 0.9 | M3: 0 | N3: 0 | O3: 1 | P3: =1/72 -> 0.013888889 | Q3: =1/72 -> 0.013888889 | R3: 0 | S3: 0 | T3: 1000000 | U3: 1000000 | V3: production, heat storage, 2000l_unit | W3: =1/AA3 -> 0.01076555 | X3: 0 | Y3: 41 | Z3: 30 | AA3: =2000*(95-55)*(4.18/1000/3.6) -> 92.888889
A4: heat_storage_low | B4: 0 | C4: bus_th_low | D4: kWh | E4: 0 | F4: 0 | G4: 0 | H4: 1000000 | I4: 0 | J4: 0.00011991014 | K4: 1 | L4: =0.81^0.5 -> 0.9 | M4: 0 | N4: 0 | O4: 1 | P4: =1/72 -> 0.013888889 | Q4: =1/72 -> 0.013888889 | R4: 0 | S4: 0 | T4: 1000000 | U4: 1000000 | V4: production, heat storage, 2000l_unit | W4: =1/AA4 -> 0.0078294911 | X4: 0 | Y4: 29.867537 | Z4: 30 | AA4: =2000*(95-40)*(4.18/1000/3.6) -> 127.72222
A5: heat_storage | B5: 0 | C5: bus_th | D5: kWh | E5: 0 | F5: 0 | G5: 0 | H5: 1000000 | I5: 0 | J5: 0.00015850428 | K5: 1 | L5: =0.81^0.5 -> 0.9 | M5: 0 | N5: 0 | O5: 1 | P5: =1/72 -> 0.013888889 | Q5: =1/72 -> 0.013888889 | R5: 0 | S5: 0 | T5: 1000000 | U5: 1000000 | V5: production, heat storage, 2000l_unit | W5: =1/AA5 -> 0.01076555 | X5: 0 | Y5: 41 | Z5: 30 | AA5: =2000*(95-55)*(4.18/1000/3.6) -> 92.888889
A6: hydrogen_storage | B6: 0 | C6: bus_hydrogen | D6: kg | E6: 0 | F6: 0 | G6: 0 | H6: 1000000 | I6: 0 | J6: 0 | K6: 1 | L6: 1 | M6: 0 | N6: 0 | O6: 1 | P6: 0.2 | Q6: 0.2 | R6: 0 | S6: 0 | T6: 1000000 | U6: 1000000 | V6: storage production, 10'000 l, investment_unit | W6: =1/120 -> 0.0083333333 | X6: 1 | Y6: 500 | Z6: 25 | AA6: =3/1000*10000 -> 30
A8: h2_reservoir | B8: 1 | C8: bus_hydrogen_proxy | D8: kg | E8: 0 | F8: 0 | G8: 0 | H8: 1000000 | I8: 0 | J8: 0 | K8: 1 | L8: 1 | M8: 0 | N8: 0 | O8: 0.8 | P8: 0.25 | Q8: 0.25 | R8: 0 | S8: 0 | T8: 1000000 | U8: 1000000 | V8: storage production, 10'000 l | W8: =1/(10*0.0899)/30 -> 0.037078235 | X8: =0.03*Y8 -> 30 | Y8: 1000 | Z8: 30 | AA8: actually, exponential electricity demand for compression is necessary
A10: batt_LFP | B10: 1 | C10: bus_el-stor | D10: kWh | E10: 0 | F10: 0 | G10: 0 | H10: 1000000 | I10: 0 | J10: =0.01/24 -> 0.00041666667 | K10: 0.96 | L10: 0.96 | M10: 0 | N10: 0 | O10: 0.8 | P10: 0.5 | Q10: 3 | R10: 0 | S10: 0 | T10: 1000000 | U10: 1000000 | V10: market for battery cell, Li-ion, LFP | W10: =1/0.159 -> 6.2893082 | X10: =0.03*Y10 -> 15 | Y10: 500 | Z10: 15 | AA10: taken from Kost2024

Sheet converters_in
A1: label | B1: active | C1: unit | D1: initial_existance | E1: initially_installed_capacity | F1: year_of_availability | G1: end_of_availability | H1: from1 | I1: conversion_factor_f1 | J1: var_from1_costs | K1: to1 | L1: conversion_factor_t1 | M1: var_to1_costs | N1: var_env1 | O1: var_env1_conversion | P1: to2 | Q1: conversion_factor_t2 | R1: var_env2 | S1: var_env2_conversion | T1: om | U1: invest | V1: invest_kWel | W1: lifetime | X1: max_capacity_invest | Y1: max_total_capacity | Z1: inv1 | AA1: inv1_conversion | AB1: fuel_based | AD1: comment
A2: CHP_nat_gas_m_gas_turb | B2: 0 | C2: kWin | D2: 0 | E2: 0 | F2: 0 | G2: 100000 | H2: bus_nat_gas | I2: 1 | J2: 0 | K2: bus_el | L2: 0.29 | M2: 0 | N2: electricity, CHP, natural gas, burned in micro gas turbine, 345 kW, 100kWe, variable_kWh | O2: 1 | P2: bus_th | Q2: 0.46 | R2: heat, central or small-scale, CHP, natural gas, low pressure, burned in micro gas turbine, 345 kW, 100kWe - variable_MJ | S2: 3.6 | T2: =0.0035/L2 -> 0.012068966 | U2: =V2*L2 -> 431.23 | V2: 1487 | W2: 15 | X2: 100000 | Y2: 100000 | Z2: construction, CHP, micro gas turbine, 345 kW, 160 kWth, 100kWe, investment_kW | AA2: 1 | AB2: 1
A3: CHP_biometh_m_gas_turb | B3: 0 | C3: kWin | D3: 0 | E3: 0 | F3: 0 | G3: 100000 | H3: bus_biometh | I3: 1 | J3: 0 | K3: bus_el | L3: 0.29 | M3: 0 | N3: electricity, CHP, biomethane, low pressure burned in micro gas turbine 345 kW, 100kWe, variable_kWh | O3: 1 | P3: bus_th | Q3: 0.46 | R3: heat, central or small-scale, CHP, biomethane, low pressure burned in micro gas turbine, 345 kW, 100kWe, variable_MJ | S3: 3.6 | T3: =0.0069/L3 -> 0.023793103 | U3: =V3*L3 -> 455.59 | V3: 1571 | W3: 15 | X3: 100000 | Y3: 100000 | Z3: construction, CHP, micro gas turbine, 345 kW, 160 kWth, 100kWe, investment_kW | AA3: 1 | AB3: 1
A4: CHP_biometh_PEM_FC | B4: 0 | C4: kWin | D4: 0 | E4: 0 | F4: 0 | G4: 100000 | H4: bus_biometh | I4: 1 | J4: 0 | K4: bus_el | L4: 0.32 | M4: 0 | N4: electricity, CHP, biomethane, low pressure burned in polymer electrolyte membrane fuel cell 2kWe, future, variable_kWh | O4: 1 | P4: bus_th | Q4: 0.55 | R4: heat, central or small-scale, CHP, biomethane, low pressure burned in polymer electrolyte membrane fuel cell 2kWe, future, variable_MJ | S4: 3.6 | T4: 0 | U4: =V4*L4 -> 1532.8 | V4: 4790 | W4: 15 | X4: 100000 | Y4: 100000 | Z4: construction, CHP, fuel cell, polymer electrolyte membrane, 6.25kW, 2kWe, 3.44 kWth, future, investment_kW | AA4: 1 | AB4: 1
A5: CHP_biometh_SO_FC | B5: 0 | C5: kWin | D5: 0 | E5: 0 | F5: 0 | G5: 100000 | H5: bus_biometh | I5: 1 | J5: 0 | K5: bus_el | L5: 0.47 | M5: 0 | N5: electricity, CHP, biomethane, low pressure burned in solid oxide fuel cell 266 kW, 125kWe, future, variable_kWh | O5: 1 | P5: bus_th | Q5: 0.33 | R5: heat, central or small-scale, CHP, biomethane, low pressure burned in solid oxide fuel cell, 266 kW, 125kWe, future, variable_MJ | S5: 3.6 | T5: 0 | U5: =V5*L5 -> 864.8 | V5: 1840 | W5: 15 | X5: 100000 | Y5: 100000 | Z5: construction, CHP, fuel cell, solid oxide, 266 kW, 125kWe, future, investment_kW | AA5: 1 | AB5: 1
A6: CHP_biometh_SO_FC_mGT | B6: 0 | C6: kWin | D6: 0 | E6: 0 | F6: 0 | G6: 100000 | H6: bus_biometh | I6: 1 | J6: 0 | K6: bus_el | L6: 0.58 | M6: 0 | N6: electricity, CHP, biomethane, low pressure burned in solid oxide fuel cell, with micro gas turbine, 327 kW, 180kWe, future, variable_kWh | O6: 1 | P6: bus_th | Q6: 0.22 | R6: heat, central or small-scale, CHP, biomethane, low pressure burned in solid oxide fuel cell, with micro gas turbine, 327 kW, 180kWe, future, variable_MJ | S6: 3.6 | T6: =0.014/L6 -> 0.024137931 | U6: =V6*L6 -> 2181.38 | V6: 3761 | W6: 15 | X6: 100000 | Y6: 100000 | Z6: construction, CHP, fuel cell, solid oxide, with micro gas turbine, 327kW, 180kWe, 92kWth, future, investment_kW | AA6: 1 | AB6: 1
A7: CHP_2000_w_chips | B7: 0 | C7: kWin | D7: 0 | E7: 0 | F7: 0 | G7: 100000 | H7: bus_w_chips | I7: 1 | J7: 0 | K7: bus_el | L7: =1/(0.9*0.8*18.9/3.6) -> 0.26455026 | M7: 0.034 | N7: electricity, CHP, wood chips, 2000 kW, 1200 kWth, 530 kWel, variable_kWh | O7: 1 | P7: bus_th | Q7: =(111.3/49)/(0.9*0.8*18.9/3.6) -> 0.60090703 | R7: heat, district or industrial, CHP, wood chips, 2000 kW, 1200 kWth, 530 kWel, variable_kWh | S7: 1 | T7: 0 | U7: =V7*L7 -> 1239.9471 | V7: 4687 | W7: 15 | X7: 100000 | Y7: 100000 | Z7: construction, CHP, wood chips, 2000 kW, investment_kW | AA7: 1 | AB7: 1
A8: CHP_6667_w_chips | B8: 0 | C8: kWin | D8: 0 | E8: 0 | F8: 0 | G8: 100000 | H8: bus_w_chips | I8: 1 | J8: 0 | K8: bus_el | L8: 0.15 | M8: 0.034 | N8: electricity, CHP, wood chips, wet, 6667 kW, state-of-the-art 2014, variable_kWh | O8: 1 | P8: bus_th | Q8: 0.45 | R8: heat, district or industrial, CHP, wood chips, wet, 6667 kW, state-of-the-art 2014, variable_MJ | S8: 3.6 | T8: 0 | U8: =V8*L8 -> 703.05 | V8: 4687 | W8: 15 | X8: 100000 | Y8: 100000 | Z8: construction, CHP, wood chips, 6667 kW, state-of-the-art 2014, investment_kW | AA8: 1 | AB8: 1
A9: electrolyzer | B9: 0 | C9: kWin | D9: 0 | E9: 0 | F9: 0 | G9: 100000 | H9: bus_el | I9: 1 | J9: 0 | K9: bus_hydrogen | L9: =0.7/33.3 -> 0.021021021 | M9: 0 | N9: empty | O9: 1 | P9: bus_oxygen | Q9: =L9/2*18/2 -> 0.094594595 | R9: empty | S9: 1 | T9: 0 | U9: 1 | W9: 15 | X9: 100000 | Y9: 100000 | Z9: construction, CHP, fuel cell, polymer electrolyte membrane, 6.25kW, 2kWe, 3.44 kWth, future, investment_kW | AA9: 1 | AB9: 0
A10: hydrogen_fuel_cell | B10: 0 | C10: kg | D10: 0 | E10: 0 | F10: 0 | G10: 100000 | H10: bus_hydrogen | I10: 1 | J10: 0 | K10: bus_el | L10: =0.5*33.3 -> 16.65 | M10: 0 | N10: empty | O10: 1 | T10: 0 | U10: 1 | W10: 15 | X10: 100000 | Y10: 100000 | Z10: construction, CHP, fuel cell, polymer electrolyte membrane, 6.25kW, 2kWe, 3.44 kWth, future, investment_kW | AA10: 33.3 | AB10: 0
A12: boiler_nat_gas | B12: 0 | C12: kWth | D12: 0 | E12: 0 | F12: 0 | G12: 100000 | H12: bus_nat_gas | I12: 1 | J12: 0 | K12: bus_co2_emission | L12: 0.20031363 | M12: 0 | N12: empty | O12: 1 | P12: bus_th_households | Q12: 1.02 | R12: empty | S12: 1 | T12: =0.03*U12 -> 6.579 | U12: =215*Q12 -> 219.3 | V12: 0 | W12: 20 | X12: 100000 | Y12: 100000 | Z12: gas boiler production, 10kWgas | AA12: =1/10 -> 0.1 | AB12: 1 | AD12: reference: KEA Technikkatalog
A15: smre_proxy_o1 | B15: 1 | C15: kg/h | D15: 0 | E15: 0 | F15: 0 | G15: 100000 | H15: bus_smre | I15: 1 | J15: 0 | K15: bus_smr-exhaust | L15: =2751.64/89.93 -> 30.597576 | M15: 0 | N15: empty | O15: 1 | P15: bus_smre_po1 | Q15: 1 | R15: empty | S15: 1 | T15: 0 | U15: 0 | V15: 0 | W15: 100 | X15: 1000 | Y15: 1000 | Z15: empty | AA15: 1 | AB15: 1
A16: smre_proxy_o2 | B16: 1 | C16: kg/h | D16: 0 | E16: 0 | F16: 0 | G16: 100000 | H16: bus_smre_po1 | I16: 1 | J16: 0 | K16: bus_steam7,5bar | L16: =(440.46*1/1.3)/89.93 -> 3.7675457 | M16: 0 | N16: empty | O16: 1 | P16: bus_hydrogen | Q16: 1 | R16: empty | S16: 1 | T16: 0 | U16: 0 | V16: 0 | W16: 100 | X16: 1000 | Y16: 1000 | Z16: empty | AA16: 1 | AB16: 1
A18: smr_proxy_o1 | B18: 1 | C18: kg/h | D18: 0 | E18: 0 | F18: 2025 | G18: 2030 | H18: bus_smr_pi2 | I18: 1 | J18: 0 | K18: bus_smr-exhaust | L18: =2751.64/89.93 -> 30.597576 | M18: 0 | N18: empty | O18: 1 | P18: bus_smr_po1 | Q18: 1 | R18: empty | S18: 1 | T18: 0 | U18: 0 | V18: 0 | W18: 100 | X18: 1000 | Y18: 1000 | Z18: empty | AA18: 1 | AB18: 1
A19: steam_methane_reformer_25 | B19: 1 | C19: kg/h | D19: 0 | E19: 0 | F19: 2025 | G19: 2030 | H19: bus_smr_po1 | I19: 1 | J19: 0 | K19: bus_steam7,5bar | L19: =(440.46*1/1.3)/89.93 -> 3.7675457 | M19: 0 | N19: empty | O19: 1 | P19: bus_hydrogen | Q19: 1 | R19: empty | S19: 1 | T19: =$T$28 -> 805 | U19: 29667 | V19: 0 | W19: =$W$28 -> 25 | X19: 1000 | Y19: =$Y$28 -> 1000 | Z19: SMR_cons_2025 | AA19: =1/9000.9 -> 0.0001111 | AB19: 1
A20: steam_methane_reformer_30 | B20: 1 | C20: kg/h | D20: 0 | E20: 0 | F20: 2030 | G20: 2035 | H20: bus_smr_po1 | I20: 1 | J20: 0 | K20: bus_steam7,5bar | L20: =(440.46*1/1.3)/89.93 -> 3.7675457 | M20: 0 | N20: empty | O20: 1 | P20: bus_hydrogen | Q20: 1 | R20: empty | S20: 1 | T20: =$T$28 -> 805 | U20: 28183 | V20: 0 | W20: =$W$28 -> 25 | X20: 1000 | Y20: =$Y$28 -> 1000 | Z20: SMR_cons_2030 | AA20: =1/9000.9 -> 0.0001111 | AB20: 1
A21: steam_methane_reformer_35 | B21: 1 | C21: kg/h | D21: 0 | E21: 0 | F21: 2035 | G21: 2040 | H21: bus_smr_po1 | I21: 1 | J21: 0 | K21: bus_steam7,5bar | L21: =(440.46*1/1.3)/89.93 -> 3.7675457 | M21: 0 | N21: empty | O21: 1 | P21: bus_hydrogen | Q21: 1 | R21: empty | S21: 1 | T21: =$T$28 -> 805 | U21: 26774 | V21: 0 | W21: =$W$28 -> 25 | X21: 1000 | Y21: =$Y$28 -> 1000 | Z21: SMR_cons_2035 | AA21: =1/9000.9 -> 0.0001111 | AB21: 1
A22: steam_methane_reformer_40 | B22: 1 | C22: kg/h | D22: 0 | E22: 0 | F22: 2040 | G22: 2045 | H22: bus_smr_po1 | I22: 1 | J22: 0 | K22: bus_steam7,5bar | L22: =(440.46*1/1.3)/89.93 -> 3.7675457 | M22: 0 | N22: empty | O22: 1 | P22: bus_hydrogen | Q22: 1 | R22: empty | S22: 1 | T22: =$T$28 -> 805 | U22: 25435 | V22: 0 | W22: =$W$28 -> 25 | X22: 1000 | Y22: =$Y$28 -> 1000 | Z22: SMR_cons_2040 | AA22: =1/9000.9 -> 0.0001111 | AB22: 1
A23: steam_methane_reformer_45 | B23: 1 | C23: kg/h | D23: 0 | E23: 0 | F23: 2045 | G23: 2050 | H23: bus_smr_po1 | I23: 1 | J23: 0 | K23: bus_steam7,5bar | L23: =(440.46*1/1.3)/89.93 -> 3.7675457 | M23: 0 | N23: empty | O23: 1 | P23: bus_hydrogen | Q23: 1 | R23: empty | S23: 1 | T23: =$T$28 -> 805 | U23: 24164 | V23: 0 | W23: =$W$28 -> 25 | X23: 1000 | Y23: =$Y$28 -> 1000 | Z23: SMR_cons_2045 | AA23: =1/9000.9 -> 0.0001111 | AB23: 1
A24: steam_methane_reformer_50 | B24: 1 | C24: kg/h | D24: 0 | E24: 0 | F24: 2050 | G24: 2055 | H24: bus_smr_po1 | I24: 1 | J24: 0 | K24: bus_steam7,5bar | L24: =(440.46*1/1.3)/89.93 -> 3.7675457 | M24: 0 | N24: empty | O24: 1 | P24: bus_hydrogen | Q24: 1 | R24: empty | S24: 1 | T24: =$T$28 -> 805 | U24: 24164 | V24: 0 | W24: =$W$28 -> 25 | X24: 1000 | Y24: =$Y$28 -> 1000 | Z24: SMR_cons_2045 | AA24: =1/9000.9 -> 0.0001111 | AB24: 1
A25: steam_methane_reformer_55 | B25: 1 | C25: kg/h | D25: 0 | E25: 0 | F25: 2055 | G25: 2060 | H25: bus_smr_po1 | I25: 1 | J25: 0 | K25: bus_steam7,5bar | L25: =(440.46*1/1.3)/89.93 -> 3.7675457 | M25: 0 | N25: empty | O25: 1 | P25: bus_hydrogen | Q25: 1 | R25: empty | S25: 1 | T25: =$T$28 -> 805 | U25: 24164 | V25: 0 | W25: =$W$28 -> 25 | X25: 1000 | Y25: =$Y$28 -> 1000 | Z25: SMR_cons_2045 | AA25: =1/9000.9 -> 0.0001111 | AB25: 1
A26: steam_methane_reformer_60 | B26: 1 | C26: kg/h | D26: 0 | E26: 0 | F26: 2060 | G26: 2065 | H26: bus_smr_po1 | I26: 1 | J26: 0 | K26: bus_steam7,5bar | L26: =(440.46*1/1.3)/89.93 -> 3.7675457 | M26: 0 | N26: empty | O26: 1 | P26: bus_hydrogen | Q26: 1 | R26: empty | S26: 1 | T26: =$T$28 -> 805 | U26: 24164 | V26: 0 | W26: =$W$28 -> 25 | X26: 1000 | Y26: =$Y$28 -> 1000 | Z26: SMR_cons_2045 | AA26: =1/9000.9 -> 0.0001111 | AB26: 1
A27: steam_methane_reformer_65 | B27: 1 | C27: kg/h | D27: 0 | E27: 0 | F27: 2065 | G27: 2070 | H27: bus_smr_po1 | I27: 1 | J27: 0 | K27: bus_steam7,5bar | L27: =(440.46*1/1.3)/89.93 -> 3.7675457 | M27: 0 | N27: empty | O27: 1 | P27: bus_hydrogen | Q27: 1 | R27: empty | S27: 1 | T27: =$T$28 -> 805 | U27: 24164 | V27: 0 | W27: =$W$28 -> 25 | X27: 1000 | Y27: =$Y$28 -> 1000 | Z27: SMR_cons_2045 | AA27: =1/9000.9 -> 0.0001111 | AB27: 1
A28: steam_methane_reformer_70 | B28: 1 | C28: kg/h | D28: 0 | E28: 0 | F28: 2070 | G28: 2075 | H28: bus_smr_po1 | I28: 1 | J28: 0 | K28: bus_steam7,5bar | L28: =(440.46*1/1.3)/89.93 -> 3.7675457 | M28: 0 | N28: empty | O28: 1 | P28: bus_hydrogen | Q28: 1 | R28: empty | S28: 1 | T28: 805 | U28: 24164 | V28: 0 | W28: 25 | X28: 1000 | Y28: 1000 | Z28: SMR_cons_2045 | AA28: =1/9000.9 -> 0.0001111 | AB28: 1 | AD28: om actually 3% per year of invest costs
A30: smr_refurbish_25 | B30: 1 | C30: kg/h | D30: 0 | E30: 0 | F30: 2025 | G30: 2030 | H30: bus_smr_po1 | I30: 1 | J30: 0 | K30: bus_steam7,5bar | L30: =(440.46*1/1.3)/89.93 -> 3.7675457 | M30: 0 | N30: empty | O30: 1 | P30: bus_hydrogen | Q30: 1 | R30: empty | S30: 1 | T30: =$T$39 -> 805 | U30: =29667/5 -> 5933.4 | V30: 0 | W30: =$W$39 -> 5 | X30: 0 | Y30: =$Y$39 -> 1000 | Z30: empty | AA30: =1/9000.9 -> 0.0001111 | AB30: 1
A31: smr_refurbish_30 | B31: 1 | C31: kg/h | D31: 0 | E31: 0 | F31: 2030 | G31: 2035 | H31: bus_smr_po1 | I31: 1 | J31: 0 | K31: bus_steam7,5bar | L31: =(440.46*1/1.3)/89.93 -> 3.7675457 | M31: 0 | N31: empty | O31: 1 | P31: bus_hydrogen | Q31: 1 | R31: empty | S31: 1 | T31: =$T$39 -> 805 | U31: =28183/5 -> 5636.6 | V31: 0 | W31: =$W$39 -> 5 | X31: 1000 | Y31: =$Y$39 -> 1000 | Z31: empty | AA31: =1/9000.9 -> 0.0001111 | AB31: 1
A32: smr_refurbish_35 | B32: 1 | C32: kg/h | D32: 0 | E32: 0 | F32: 2035 | G32: 2040 | H32: bus_smr_po1 | I32: 1 | J32: 0 | K32: bus_steam7,5bar | L32: =(440.46*1/1.3)/89.93 -> 3.7675457 | M32: 0 | N32: empty | O32: 1 | P32: bus_hydrogen | Q32: 1 | R32: empty | S32: 1 | T32: =$T$39 -> 805 | U32: 26774 | V32: 0 | W32: =$W$39 -> 5 | X32: 0 | Y32: =$Y$39 -> 1000 | Z32: empty | AA32: =1/9000.9 -> 0.0001111 | AB32: 1
A33: smr_refurbish_40 | B33: 1 | C33: kg/h | D33: 0 | E33: 0 | F33: 2040 | G33: 2045 | H33: bus_smr_po1 | I33: 1 | J33: 0 | K33: bus_steam7,5bar | L33: =(440.46*1/1.3)/89.93 -> 3.7675457 | M33: 0 | N33: empty | O33: 1 | P33: bus_hydrogen | Q33: 1 | R33: empty | S33: 1 | T33: =$T$39 -> 805 | U33: 25435 | V33: 0 | W33: =$W$39 -> 5 | X33: 0 | Y33: =$Y$39 -> 1000 | Z33: empty | AA33: =1/9000.9 -> 0.0001111 | AB33: 1
A34: smr_refurbish_45 | B34: 1 | C34: kg/h | D34: 0 | E34: 0 | F34: 2045 | G34: 2050 | H34: bus_smr_po1 | I34: 1 | J34: 0 | K34: bus_steam7,5bar | L34: =(440.46*1/1.3)/89.93 -> 3.7675457 | M34: 0 | N34: empty | O34: 1 | P34: bus_hydrogen | Q34: 1 | R34: empty | S34: 1 | T34: =$T$39 -> 805 | U34: 24164 | V34: 0 | W34: =$W$39 -> 5 | X34: 0 | Y34: =$Y$39 -> 1000 | Z34: empty | AA34: =1/9000.9 -> 0.0001111 | AB34: 1
A35: smr_refurbish_50 | B35: 1 | C35: kg/h | D35: 0 | E35: 0 | F35: 2050 | G35: 2055 | H35: bus_smr_po1 | I35: 1 | J35: 0 | K35: bus_steam7,5bar | L35: =(440.46*1/1.3)/89.93 -> 3.7675457 | M35: 0 | N35: empty | O35: 1 | P35: bus_hydrogen | Q35: 1 | R35: empty | S35: 1 | T35: =$T$39 -> 805 | U35: 24164 | V35: 0 | W35: =$W$39 -> 5 | X35: 0 | Y35: =$Y$39 -> 1000 | Z35: empty | AA35: =1/9000.9 -> 0.0001111 | AB35: 1
A36: smr_refurbish_55 | B36: 1 | C36: kg/h | D36: 0 | E36: 0 | F36: 2055 | G36: 2060 | H36: bus_smr_po1 | I36: 1 | J36: 0 | K36: bus_steam7,5bar | L36: =(440.46*1/1.3)/89.93 -> 3.7675457 | M36: 0 | N36: empty | O36: 1 | P36: bus_hydrogen | Q36: 1 | R36: empty | S36: 1 | T36: =$T$39 -> 805 | U36: 24164 | V36: 0 | W36: =$W$39 -> 5 | X36: 0 | Y36: =$Y$39 -> 1000 | Z36: empty | AA36: =1/9000.9 -> 0.0001111 | AB36: 1
A37: smr_refurbish_60 | B37: 1 | C37: kg/h | D37: 0 | E37: 0 | F37: 2060 | G37: 2065 | H37: bus_smr_po1 | I37: 1 | J37: 0 | K37: bus_steam7,5bar | L37: =(440.46*1/1.3)/89.93 -> 3.7675457 | M37: 0 | N37: empty | O37: 1 | P37: bus_hydrogen | Q37: 1 | R37: empty | S37: 1 | T37: =$T$39 -> 805 | U37: 24164 | V37: 0 | W37: =$W$39 -> 5 | X37: 0 | Y37: =$Y$39 -> 1000 | Z37: empty | AA37: =1/9000.9 -> 0.0001111 | AB37: 1
A38: smr_refurbish_65 | B38: 1 | C38: kg/h | D38: 0 | E38: 0 | F38: 2065 | G38: 2070 | H38: bus_smr_po1 | I38: 1 | J38: 0 | K38: bus_steam7,5bar | L38: =(440.46*1/1.3)/89.93 -> 3.7675457 | M38: 0 | N38: empty | O38: 1 | P38: bus_hydrogen | Q38: 1 | R38: empty | S38: 1 | T38: =$T$39 -> 805 | U38: 24164 | V38: 0 | W38: =$W$39 -> 5 | X38: 0 | Y38: =$Y$39 -> 1000 | Z38: empty | AA38: =1/9000.9 -> 0.0001111 | AB38: 1
A39: smr_refurbish_70 | B39: 1 | C39: kg/h | D39: 0 | E39: 0 | F39: 2070 | G39: 2075 | H39: bus_smr_po1 | I39: 1 | J39: 0 | K39: bus_steam7,5bar | L39: =(440.46*1/1.3)/89.93 -> 3.7675457 | M39: 0 | N39: empty | O39: 1 | P39: bus_hydrogen | Q39: 1 | R39: empty | S39: 1 | T39: 805 | U39: 24164 | V39: 0 | W39: 5 | X39: 0 | Y39: 1000 | Z39: empty | AA39: =1/9000.9 -> 0.0001111 | AB39: 1 | AD39: om actually 3% per year of invest costs
A41: smr_exhaust-co2-ratio | B41: 1 | C41: kg/h | D41: 0 | E41: 0 | F41: 0 | G41: 100000 | H41: bus_smr-exhaust | I41: 1 | J41: 0 | K41: bus_co2_emission | L41: =815.99/2751.64 -> 0.29654679 | M41: 0 | N41: empty | O41: 1 | R41: empty | S41: 1 | T41: 0 | U41: 0 | V41: 0 | W41: 100 | X41: 100000 | Y41: 100000 | Z41: empty | AA41: 1 | AB41: 1
A43: ael_proxy_o1 | B43: 0 | C43: kg/h | D43: 0 | E43: 0 | F43: 0 | G43: 100000 | H43: bus_ael | I43: 1 | J43: 0 | K43: bus_oxygen | L43: =713.79/89.93 -> 7.9371734 | M43: 0 | N43: empty | O43: 1 | P43: bus_ael_po1 | Q43: =I43 -> 1 | R43: empty | S43: 1 | T43: 0 | U43: 0 | V43: 0 | W43: 100 | X43: 100000 | Y43: 100000 | Z43: empty | AA43: 1 | AB43: 0
A44: ael_proxy_o2 | B44: 0 | C44: kg/h | D44: 0 | E44: 0 | F44: 0 | G44: 100000 | H44: bus_ael_po1 | I44: 1 | J44: 0 | K44: bus_th60 | L44: =1145/89.93 -> 12.732125 | M44: 0 | N44: empty | O44: 1 | P44: bus_hydrogen | Q44: =I44 -> 1 | R44: empty | S44: 1 | T44: 0 | U44: 0 | V44: 0 | W44: 100 | X44: 100000 | Y44: 100000 | Z44: empty | AA44: 1 | AB44: 0
A46: pem_proxy_o1 | B46: 1 | C46: kg/h | D46: 0 | E46: 0 | F46: 0 | G46: 100000 | H46: bus_pem | I46: 1 | J46: 0 | K46: bus_oxygen | L46: =713.79/89.93 -> 7.9371734 | M46: 0 | N46: empty | O46: 1 | P46: bus_pem_po1 | Q46: =I46 -> 1 | R46: empty | S46: 1 | T46: 0 | U46: 0 | V46: 0 | W46: 100 | X46: 100000 | Y46: 100000 | Z46: empty | AA46: 1 | AB46: 0
A47: pem_proxy_o2 | B47: 1 | C47: kg/h | D47: 0 | E47: 0 | F47: 0 | G47: 100000 | H47: bus_pem_po1 | I47: 1 | J47: 0 | K47: bus_th60 | L47: =1325/89.93 -> 14.733682 | M47: 0 | N47: empty | O47: 1 | P47: bus_hydrogen | Q47: =I47 -> 1 | R47: empty | S47: 1 | T47: 0 | U47: 0 | V47: 0 | W47: 100 | X47: 100000 | Y47: 100000 | Z47: empty | AA47: 1 | AB47: 0
A49: aem_proxy_o1 | B49: 0 | C49: kg/h | D49: 0 | E49: 0 | F49: 0 | G49: 100000 | H49: bus_aem | I49: 1 | J49: 0 | K49: bus_oxygen | L49: =713.79/89.93 -> 7.9371734 | M49: 0 | N49: empty | O49: 1 | P49: bus_aem_po1 | Q49: =I49 -> 1 | R49: empty | S49: 1 | T49: 0 | U49: 0 | V49: 0 | W49: 100 | X49: 100000 | Y49: 100000 | Z49: empty | AA49: 1 | AB49: 0
A50: aem_proxy_o2 | B50: 0 | C50: kg/h | D50: 0 | E50: 0 | F50: 0 | G50: 100000 | H50: bus_aem_po1 | I50: 1 | J50: 0 | K50: bus_th60 | L50: =1805/89.93 -> 20.071166 | M50: 0 | N50: empty | O50: 1 | P50: bus_hydrogen | Q50: =I50 -> 1 | R50: empty | S50: 1 | T50: 0 | U50: 0 | V50: 0 | W50: 100 | X50: 100000 | Y50: 100000 | Z50: empty | AA50: 1 | AB50: 0
A52: soec_proxy_o1 | B52: 1 | C52: kg/h | D52: 0 | E52: 0 | F52: 0 | G52: 100000 | H52: bus_soec | I52: 1 | J52: 0 | K52: bus_oxygen | L52: =713.79/89.93 -> 7.9371734 | M52: 0 | N52: empty | O52: 1 | P52: bus_soec_po1 | Q52: 1 | R52: empty | S52: 1 | T52: 0 | U52: 0 | V52: 0 | W52: 100 | X52: 100000 | Y52: 100000 | Z52: empty | AA52: 1 | AB52: 0
A53: soec_proxy_o2 | B53: 1 | C53: kg/h | D53: 0 | E53: 0 | F53: 0 | G53: 100000 | H53: bus_soec_po1 | I53: 1 | J53: 0 | K53: bus_th120 | L53: =538.8/89.93 -> 5.9913266 | M53: 0 | N53: empty | O53: 1 | P53: bus_soec_po2 | Q53: 1 | R53: empty | S53: 1 | T53: 0 | U53: 0 | V53: 0 | W53: 100 | X53: 100000 | Y53: 100000 | Z53: empty | AA53: 1 | AB53: 0
A54: soec_proxy_o3 | B54: 1 | C54: kg/h | D54: 0 | E54: 0 | F54: 0 | G54: 100000 | H54: bus_soec_po2 | I54: 1 | J54: 0 | K54: bus_th60 | L54: =499.5/89.93 -> 5.55432 | M54: 0 | N54: empty | O54: 1 | P54: bus_hydrogen | Q54: 1 | R54: empty | S54: 1 | T54: 0 | U54: 0 | V54: 0 | W54: 100 | X54: 100000 | Y54: 100000 | Z54: empty | AA54: 1 | AB54: 0
A56: atr_proxy_o1 | B56: 0 | C56: kg/h | D56: 0 | E56: 0 | F56: 2025 | G56: 100000 | H56: bus_atr | I56: 1 | J56: 0 | K56: bus_atr-exhaust | L56: =3433.99/89.93 -> 38.185144 | M56: 0 | N56: empty | O56: 1 | P56: bus_atr_po1 | Q56: 1 | R56: empty | S56: 1 | T56: 0 | U56: 0 | V56: 0 | W56: 100 | X56: 100000 | Y56: 100000 | Z56: empty | AA56: 1 | AB56: 0
A57: atr_proxy_o2 | B57: 0 | C57: kg/h | D57: 0 | E57: 0 | F57: 2025 | G57: 100000 | H57: bus_atr_po1 | I57: 1 | J57: 0 | K57: bus_th120 | L57: =176/89.93 -> 1.9570777 | M57: 0 | N57: empty | O57: 1 | P57: bus_atr_po2 | Q57: 1 | R57: empty | S57: 1 | T57: 0 | U57: 0 | V57: 0 | W57: 100 | X57: 100000 | Y57: 100000 | Z57: empty | AA57: 1 | AB57: 0
A58: atr_proxy_o3 | B58: 0 | C58: kg/h | D58: 0 | E58: 0 | F58: 2025 | G58: 100000 | H58: bus_atr_po2 | I58: 1 | J58: 0 | K58: bus_th200 | L58: =666.8/89.93 -> 7.4146558 | M58: 0 | N58: empty | O58: 1 | P58: bus_hydrogen | Q58: 1 | R58: empty | S58: 1 | T58: 0 | U58: 0 | V58: 0 | W58: 100 | X58: 100000 | Y58: 100000 | Z58: empty | AA58: 1 | AB58: 0
A60: atr_exhaust-co2_ratio | B60: 0 | C60: kg/h | D60: 0 | E60: 0 | F60: 0 | G60: 100000 | H60: bus_atr-exhaust | I60: 1 | J60: 0 | K60: bus_co2_emission | L60: =1399.51/3433.99 -> 0.40754632 | M60: 0 | N60: empty | O60: 1 | R60: empty | S60: 1 | T60: 0 | U60: 0 | V60: 0 | W60: 100 | X60: 100000 | Y60: 100000 | Z60: empty | AA60: 1 | AB60: 0
A62: sepuran-membrane_proxy_o1 | B62: 0 | C62: kg/h | D62: 0 | E62: 0 | F62: 2025 | G62: 100000 | H62: bus_sepuran | I62: 1 | J62: 0 | K62: bus_co2 | L62: =709/(315.78*12.9) -> 0.17404915 | M62: 0 | N62: empty | O62: 1 | P62: bus_biometh | Q62: 1 | R62: empty | S62: 1 | T62: 0 | U62: 0 | V62: 0 | W62: 100 | X62: 100000 | Y62: 100000 | Z62: empty | AA62: 1 | AB62: 0
A64: kvaerner_proxy_o1 | B64: 0 | C64: kg/h | D64: 0 | E64: 0 | F64: 0 | G64: 100000 | H64: bus_kvaerner_pi1 | I64: 1 | J64: 0 | K64: bus_carbon | L64: =267.69/89.93 -> 2.9766485 | M64: 0 | N64: empty | O64: 1 | P64: bus_kvaerner_po1 | Q64: =I64 -> 1 | R64: empty | S64: 1 | T64: 0 | U64: 0 | V64: 0 | W64: 100 | X64: 100000 | Y64: 100000 | Z64: empty | AA64: 1 | AB64: 0
A65: kvaerner_proxy_o2 | B65: 0 | C65: kg/h | D65: 0 | E65: 0 | F65: 0 | G65: 100000 | H65: bus_kvaerner_po1 | I65: 1 | J65: 0 | K65: bus_th400 | L65: =638.4/89.93 -> 7.0988547 | M65: 0 | N65: empty | O65: 1 | P65: bus_kvaerner_po2 | Q65: =I65 -> 1 | R65: empty | S65: 1 | T65: 0 | U65: 0 | V65: 0 | W65: 100 | X65: 100000 | Y65: 100000 | Z65: empty | AA65: 1 | AB65: 0
A66: kvaerner_proxy_o3 | B66: 0 | C66: kg/h | D66: 0 | E66: 0 | F66: 0 | G66: 100000 | H66: bus_kvaerner_po2 | I66: 1 | J66: 0 | K66: bus_th200 | L66: =89.5/89.93 -> 0.9952185 | M66: 0 | N66: empty | O66: 1 | P66: bus_kvaerner_po3 | Q66: =I66 -> 1 | R66: empty | S66: 1 | T66: 0 | U66: 0 | V66: 0 | W66: 100 | X66: 100000 | Y66: 100000 | Z66: empty | AA66: 1 | AB66: 0
A67: kvaerner_25 | B67: 0 | C67: kg/h | D67: 0 | E67: 0 | F67: 2025 | G67: 2030 | H67: bus_kvaerner_po3 | I67: 1 | J67: 0 | K67: bus_th120 | L67: =61.8/89.93 -> 0.68720116 | M67: 0 | N67: empty | O67: 1 | P67: bus_hydrogen | Q67: =I67 -> 1 | R67: empty | S67: 1 | T67: =$T$76 -> 1926 | U67: 77846 | V67: 0 | W67: =$W$76 -> 25 | X67: 0 | Y67: =$Y$76 -> 100000 | Z67: SMR_cons_2025 | AA67: =1/9000.9 -> 0.0001111 | AB67: 0
A68: kvaerner_30 | B68: 0 | C68: kg/h | D68: 0 | E68: 0 | F68: 2030 | G68: 2035 | H68: bus_kvaerner_po3 | I68: 1 | J68: 0 | K68: bus_th120 | L68: =61.8/89.93 -> 0.68720116 | M68: 0 | N68: empty | O68: 1 | P68: bus_hydrogen | Q68: =I68 -> 1 | R68: empty | S68: 1 | T68: =$T$76 -> 1926 | U68: 77443 | V68: 0 | W68: =$W$76 -> 25 | X68: 0 | Y68: =$Y$76 -> 100000 | Z68: SMR_cons_2030 | AA68: =1/9000.9 -> 0.0001111 | AB68: 0
A69: kvaerner_35 | B69: 0 | C69: kg/h | D69: 0 | E69: 0 | F69: 2035 | G69: 2040 | H69: bus_kvaerner_po3 | I69: 1 | J69: 0 | K69: bus_th120 | L69: =61.8/89.93 -> 0.68720116 | M69: 0 | N69: empty | O69: 1 | P69: bus_hydrogen | Q69: =I69 -> 1 | R69: empty | S69: 1 | T69: =$T$76 -> 1926 | U69: 71826 | V69: 0 | W69: =$W$76 -> 25 | X69: 0 | Y69: =$Y$76 -> 100000 | Z69: SMR_cons_2035 | AA69: =1/9000.9 -> 0.0001111 | AB69: 0
A70: kvaerner_40 | B70: 0 | C70: kg/h | D70: 0 | E70: 0 | F70: 2040 | G70: 2045 | H70: bus_kvaerner_po3 | I70: 1 | J70: 0 | K70: bus_th120 | L70: =61.8/89.93 -> 0.68720116 | M70: 0 | N70: empty | O70: 1 | P70: bus_hydrogen | Q70: =I70 -> 1 | R70: empty | S70: 1 | T70: =$T$76 -> 1926 | U70: 66621 | V70: 0 | W70: =$W$76 -> 25 | X70: 100000 | Y70: =$Y$76 -> 100000 | Z70: SMR_cons_2040 | AA70: =1/9000.9 -> 0.0001111 | AB70: 0
A71: kvaerner_45 | B71: 0 | C71: kg/h | D71: 0 | E71: 0 | F71: 2045 | G71: 2050 | H71: bus_kvaerner_po3 | I71: 1 | J71: 0 | K71: bus_th120 | L71: =61.8/89.93 -> 0.68720116 | M71: 0 | N71: empty | O71: 1 | P71: bus_hydrogen | Q71: =I71 -> 1 | R71: empty | S71: 1 | T71: =$T$76 -> 1926 | U71: 61797 | V71: 0 | W71: =$W$76 -> 25 | X71: 100000 | Y71: =$Y$76 -> 100000 | Z71: SMR_cons_2045 | AA71: =1/9000.9 -> 0.0001111 | AB71: 0
A72: kvaerner_50 | B72: 0 | C72: kg/h | D72: 0 | E72: 0 | F72: 2050 | G72: 2055 | H72: bus_kvaerner_po3 | I72: 1 | J72: 0 | K72: bus_th120 | L72: =61.8/89.93 -> 0.68720116 | M72: 0 | N72: empty | O72: 1 | P72: bus_hydrogen | Q72: =I72 -> 1 | R72: empty | S72: 1 | T72: =$T$76 -> 1926 | U72: 61797 | V72: 0 | W72: =$W$76 -> 25 | X72: 100000 | Y72: =$Y$76 -> 100000 | Z72: SMR_cons_2045 | AA72: =1/9000.9 -> 0.0001111 | AB72: 0
A73: kvaerner_55 | B73: 0 | C73: kg/h | D73: 0 | E73: 0 | F73: 2055 | G73: 2060 | H73: bus_kvaerner_po3 | I73: 1 | J73: 0 | K73: bus_th120 | L73: =61.8/89.93 -> 0.68720116 | M73: 0 | N73: empty | O73: 1 | P73: bus_hydrogen | Q73: =I73 -> 1 | R73: empty | S73: 1 | T73: =$T$76 -> 1926 | U73: 61797 | V73: 0 | W73: =$W$76 -> 25 | X73: 100000 | Y73: =$Y$76 -> 100000 | Z73: SMR_cons_2045 | AA73: =1/9000.9 -> 0.0001111 | AB73: 0
A74: kvaerner_60 | B74: 0 | C74: kg/h | D74: 0 | E74: 0 | F74: 2060 | G74: 2065 | H74: bus_kvaerner_po3 | I74: 1 | J74: 0 | K74: bus_th120 | L74: =61.8/89.93 -> 0.68720116 | M74: 0 | N74: empty | O74: 1 | P74: bus_hydrogen | Q74: =I74 -> 1 | R74: empty | S74: 1 | T74: =$T$76 -> 1926 | U74: 61797 | V74: 0 | W74: =$W$76 -> 25 | X74: 100000 | Y74: =$Y$76 -> 100000 | Z74: SMR_cons_2045 | AA74: =1/9000.9 -> 0.0001111 | AB74: 0
A75: kvaerner_65 | B75: 0 | C75: kg/h | D75: 0 | E75: 0 | F75: 2065 | G75: 2070 | H75: bus_kvaerner_po3 | I75: 1 | J75: 0 | K75: bus_th120 | L75: =61.8/89.93 -> 0.68720116 | M75: 0 | N75: empty | O75: 1 | P75: bus_hydrogen | Q75: =I75 -> 1 | R75: empty | S75: 1 | T75: =$T$76 -> 1926 | U75: 61797 | V75: 0 | W75: =$W$76 -> 25 | X75: 100000 | Y75: =$Y$76 -> 100000 | Z75: SMR_cons_2045 | AA75: =1/9000.9 -> 0.0001111 | AB75: 0
A76: kvaerner_70 | B76: 0 | C76: kg/h | D76: 0 | E76: 0 | F76: 2070 | G76: 2075 | H76: bus_kvaerner_po3 | I76: 1 | J76: 0 | K76: bus_th120 | L76: =61.8/89.93 -> 0.68720116 | M76: 0 | N76: empty | O76: 1 | P76: bus_hydrogen | Q76: =I76 -> 1 | R76: empty | S76: 1 | T76: 1926 | U76: 61797 | V76: 0 | W76: 25 | X76: 100000 | Y76: 100000 | Z76: SMR_cons_2045 | AA76: =1/9000.9 -> 0.0001111 | AB76: 0 | AD76: om actually 3% per year of invest costs
A78: grid-el_converter-el | B78: 1 | C78: kW | D78: 0 | E78: 0 | F78: 0 | G78: 2100 | H78: bus_el-grid | I78: 1 | J78: 0.04 | K78: bus_el-out | L78: 1 | M78: 0 | N78: empty | O78: 1 | P78: bus_el | Q78: 1 | R78: empty | S78: 1 | T78: 0 | U78: 0 | V78: 0 | W78: 100 | X78: 100000 | Y78: 100000 | Z78: empty | AA78: 1 | AB78: 0
A80: overreg-el_converter-h2 | B80: 1 | C80: kW | D80: 0 | E80: 0 | F80: 0 | G80: 2100 | H80: bus_el-over | I80: 1 | J80: 0.04 | K80: bus_el-out | L80: 1 | M80: 0 | N80: empty | O80: 1 | P80: bus_el-h2 | Q80: 1 | R80: empty | S80: 1 | T80: 0 | U80: 0 | V80: 0 | W80: 100 | X80: 100000 | Y80: 100000 | Z80: empty | AA80: 1 | AB80: 0
A81: overreg-el_converter-stor | B81: 1 | C81: kW | D81: 0 | E81: 0 | F81: 0 | G81: 2100 | H81: bus_el-over | I81: 1 | J81: 0.04 | K81: bus_el-out | L81: 1 | M81: 0 | N81: empty | O81: 1 | P81: bus_el-stor | Q81: 1 | R81: empty | S81: 1 | T81: 0 | U81: 0 | V81: 0 | W81: 100 | X81: 100000 | Y81: 100000 | Z81: empty | AA81: 1 | AB81: 0
A82: overreg-el_converter-el | B82: 1 | C82: kW | D82: 0 | E82: 0 | F82: 0 | G82: 2100 | H82: bus_el-over | I82: 1 | J82: 0.04 | K82: bus_el-out | L82: 1 | M82: 0 | N82: empty | O82: 1 | P82: bus_el | Q82: 1 | R82: empty | S82: 1 | T82: 0 | U82: 0 | V82: 0 | W82: 100 | X82: 100000 | Y82: 100000 | Z82: empty | AA82: 1 | AB82: 0
A84: regional-el_converter-h2 | B84: 1 | C84: kW | D84: 0 | E84: 0 | F84: 0 | G84: 2100 | H84: bus_el-re | I84: 1 | J84: 0.02 | K84: bus_el-out | L84: 1 | M84: 0 | N84: empty | O84: 1 | P84: bus_el-h2 | Q84: 1 | R84: empty | S84: 1 | T84: 0 | U84: 0 | V84: 0 | W84: 100 | X84: 100000 | Y84: 100000 | Z84: empty | AA84: 1 | AB84: 0
A85: regional-el_converter-el | B85: 1 | C85: kW | D85: 0 | E85: 0 | F85: 0 | G85: 2100 | H85: bus_el-re | I85: 1 | J85: 0.02 | K85: bus_el-out | L85: 1 | M85: 0 | N85: empty | O85: 1 | P85: bus_el | Q85: 1 | R85: empty | S85: 1 | T85: 0 | U85: 0 | V85: 0 | W85: 100 | X85: 100000 | Y85: 100000 | Z85: empty | AA85: 1 | AB85: 0
A86: regional-el_converter-stor | B86: 1 | C86: kW | D86: 0 | E86: 0 | F86: 0 | G86: 2100 | H86: bus_el-re | I86: 1 | J86: 0.02 | K86: bus_el-out | L86: 1 | M86: 0 | N86: empty | O86: 1 | P86: bus_el-stor | Q86: 1 | R86: empty | S86: 1 | T86: 0 | U86: 0 | V86: 0 | W86: 100 | X86: 100000 | Y86: 100000 | Z86: empty | AA86: 1 | AB86: 0
A88: chp-exist_proxy_o1 | B88: 1 | C88: kW | D88: 0 | E88: 0 | F88: 0 | G88: 100000 | H88: bus_chp_exist | I88: 1 | J88: 0 | K88: bus_co2_emission | L88: =900.45/1000 -> 0.90045 | M88: 0 | N88: empty | O88: 1 | P88: bus_chp-e_po1 | Q88: 1 | R88: empty | S88: 1 | T88: 0 | U88: 0 | V88: 0 | W88: 100 | X88: 100000 | Y88: 100000 | Z88: empty | AA88: 1 | AB88: 1
A89: chp-exist_proxy_o2 | B89: 1 | C89: kW | D89: 0 | E89: 0 | F89: 0 | G89: 100000 | H89: bus_chp-e_po1 | I89: 1 | J89: 0 | K89: bus_steam7,5bar | L89: =2420.26/1000 -> 2.42026 | M89: 0 | N89: empty | O89: 1 | P89: bus_el | Q89: 1 | R89: empty | S89: 1 | T89: 0 | U89: 0 | V89: 0 | W89: 100 | X89: 100000 | Y89: 100000 | Z89: empty | AA89: 1 | AB89: 1
A90: chp-new_proxy_o1 | B90: 0 | C90: kW | D90: 0 | E90: 0 | F90: 0 | G90: 100000 | H90: bus_chp_new | I90: 1 | J90: 0 | K90: bus_co2_emission | L90: =0.2/0.45 -> 0.44444444 | M90: 0 | N90: empty | O90: 1 | P90: bus_chp-n_po1 | Q90: 1 | R90: empty | S90: 1 | T90: 0 | U90: 0 | V90: 0 | W90: 100 | X90: 100000 | Y90: 100000 | Z90: empty | AA90: 1 | AB90: 1
A91: chp-new_proxy_o2 | B91: 0 | C91: kW | D91: 0 | E91: 0 | F91: 0 | G91: 100000 | H91: bus_chp-n_po1 | I91: 1 | J91: 0 | K91: bus_steam7,5bar | L91: 1 | M91: 0 | N91: empty | O91: 1 | P91: bus_el | Q91: 1 | R91: empty | S91: 1 | T91: 0 | U91: 0 | V91: 0 | W91: 100 | X91: 100000 | Y91: 100000 | Z91: empty | AA91: 1 | AB91: 1
A92: chp-h2_proxy_o1 | B92: 1 | C92: kW | D92: 0 | E92: 0 | F92: 0 | G92: 100000 | H92: bus_chp-h2 | I92: 1 | J92: 0 | K92: bus_th400 | L92: 1 | M92: 0 | N92: empty | O92: 1 | P92: bus_el | Q92: 1 | R92: empty | S92: 1 | T92: 0 | U92: 0 | V92: 0 | W92: 100 | X92: 100000 | Y92: 100000 | Z92: empty | AA92: 1 | AB92: 1
A94: gas-boiler_existing | B94: 1 | C94: kW | D94: 1 | E94: 1000 | F94: 0 | G94: 2100 | H94: bus_nat_gas | I94: 1 | J94: 0 | K94: bus_steam7,5bar | L94: 0.98 | M94: 0 | N94: empty | O94: 1 | P94: bus_co2_emission | Q94: 0.2 | R94: empty | S94: 1 | T94: 0 | U94: 0 | V94: 0 | W94: 5 | X94: 100000 | Y94: 100000 | Z94: empty | AA94: 1 | AB94: 1
A95: gas-boiler_reinvest | B95: 1 | C95: kW | D95: 0 | E95: 0 | F95: 0 | G95: 2100 | H95: bus_nat_gas | I95: 1 | J95: 0 | K95: bus_steam7,5bar | L95: 0.98 | M95: 0 | N95: empty | O95: 1 | P95: bus_co2_emission | Q95: 0.2 | R95: empty | S95: 1 | T95: =0.02*U95 -> 1.372 | U95: =70*L95 -> 68.6 | V95: 0 | W95: 20 | X95: 100000 | Y95: 100000 | Z95: empty | AA95: 1 | AB95: 1
A97: gas-boiler_refurbish_25 | B97: 1 | C97: kW | D97: 0 | E97: 0 | F97: 0 | G97: 2100 | H97: bus_nat_gas | I97: 1 | J97: 0 | K97: bus_steam7,5bar | L97: 0.98 | M97: 0 | N97: empty | O97: 1 | P97: bus_co2_emission | Q97: 0.2 | R97: empty | S97: 1 | T97: =$T$95 -> 1.372 | U97: =$U$95/4 -> 17.15 | V97: 0 | W97: 5 | X97: 0 | Y97: 1000 | Z97: empty | AA97: 1 | AB97: 1
A98: gas-boiler_refurbish_30 | B98: 1 | C98: kW | D98: 0 | E98: 0 | F98: 0 | G98: 2100 | H98: bus_nat_gas | I98: 1 | J98: 0 | K98: bus_steam7,5bar | L98: 0.98 | M98: 0 | N98: empty | O98: 1 | P98: bus_co2_emission | Q98: 0.2 | R98: empty | S98: 1 | T98: =$T$95 -> 1.372 | U98: =$U$95/4 -> 17.15 | V98: 0 | W98: 5 | X98: 1000 | Y98: 1000 | Z98: empty | AA98: 1 | AB98: 1
A99: gas-boiler_refurbish_35 | B99: 1 | C99: kW | D99: 0 | E99: 0 | F99: 0 | G99: 2100 | H99: bus_nat_gas | I99: 1 | J99: 0 | K99: bus_steam7,5bar | L99: 0.98 | M99: 0 | N99: empty | O99: 1 | P99: bus_co2_emission | Q99: 0.2 | R99: empty | S99: 1 | T99: =$T$95 -> 1.372 | U99: =$U$95/4 -> 17.15 | V99: 0 | W99: 5 | X99: 0 | Y99: 1000 | Z99: empty | AA99: 1 | AB99: 1
A100: gas-boiler_refurbish_40 | B100: 1 | C100: kW | D100: 0 | E100: 0 | F100: 0 | G100: 2100 | H100: bus_nat_gas | I100: 1 | J100: 0 | K100: bus_steam7,5bar | L100: 0.98 | M100: 0 | N100: empty | O100: 1 | P100: bus_co2_emission | Q100: 0.2 | R100: empty | S100: 1 | T100: =$T$95 -> 1.372 | U100: =$U$95/4 -> 17.15 | V100: 0 | W100: 5 | X100: 0 | Y100: 1000 | Z100: empty | AA100: 1 | AB100: 1
A101: gas-boiler_refurbish_45 | B101: 1 | C101: kW | D101: 0 | E101: 0 | F101: 0 | G101: 2100 | H101: bus_nat_gas | I101: 1 | J101: 0 | K101: bus_steam7,5bar | L101: 0.98 | M101: 0 | N101: empty | O101: 1 | P101: bus_co2_emission | Q101: 0.2 | R101: empty | S101: 1 | T101: =$T$95 -> 1.372 | U101: =$U$95/4 -> 17.15 | V101: 0 | W101: 5 | X101: 0 | Y101: 1000 | Z101: empty | AA101: 1 | AB101: 1
A102: gas-boiler_refurbish_50 | B102: 1 | C102: kW | D102: 0 | E102: 0 | F102: 0 | G102: 2100 | H102: bus_nat_gas | I102: 1 | J102: 0 | K102: bus_steam7,5bar | L102: 0.98 | M102: 0 | N102: empty | O102: 1 | P102: bus_co2_emission | Q102: 0.2 | R102: empty | S102: 1 | T102: =$T$95 -> 1.372 | U102: =$U$95/4 -> 17.15 | V102: 0 | W102: 5 | X102: 0 | Y102: 1000 | Z102: empty | AA102: 1 | AB102: 1
A104: H2-boiler | B104: 1 | C104: kW | D104: 0 | E104: 0 | F104: 0 | G104: 2100 | H104: bus_hydrogen | I104: 1 | J104: 0 | K104: bus_th400 | L104: =0.98*33.3 -> 32.634 | M104: 0 | N104: empty | O104: 1 | R104: empty | S104: 1 | T104: =0.02*U104 -> 61.35192 | U104: =94*L104 -> 3067.596 | V104: 0 | W104: 20 | X104: 100000 | Y104: 100000 | Z104: empty | AA104: 1 | AB104: 1

Sheet converters_out
A1: label | B1: active | C1: unit | D1: initial_existance | E1: initially_installed_capacity | F1: year_of_availability | G1: end_of_availability | H1: from1 | I1: conversion_factor_f1 | J1: var_from1_costs | K1: from2 | L1: conversion_factor_f2 | M1: var_from2_costs | N1: to1 | O1: conversion_factor_t1 | P1: fixed_cop | Q1: var_to1_costs | R1: var_env1 | S1: var_env1_conversion | T1: om | U1: invest | V1: lifetime | W1: max_capacity_invest | X1: max_total_capacity | Y1: inv1 | Z1: inv1_conversion | AA1: fuel_based | AB1: T high | AC1: T low | AD1: quality factor_HP | AE1: comment
A2: boiler_nat_gas | B2: 0 | C2: kWth | D2: 0 | E2: 0 | F2: 0 | G2: 2100 | H2: bus_nat_gas | I2: 1 | J2: 0 | N2: bus_th | O2: 1.02 | P2: 0 | Q2: 0 | R2: heat, central or small-scale, natural gas, at boiler condensing modulating max 100kW, variable_MJ | S2: 3.6 | T2: 10.666667 | U2: 733 | V2: 20 | W2: 100000 | X2: 100000 | Y2: production, gas boiler, 10kW, investment_kW | Z2: 1 | AA2: 1
A3: heat_pump_a_w_high | B3: 0 | C3: kWth | D3: 0 | E3: 0 | F3: 0 | G3: 2100 | H3: bus_el | I3: 1 | J3: 0 | N3: bus_th | O3: 2.8 | P3: 1 | Q3: 0 | R3: heat, central or small-scale, air-water heat pump 10kW, variable_MJ | S3: 3.6 | T3: 21.428571 | U3: 708 | V3: 20 | W3: 100000 | X3: 100000 | Y3: production, air-water heat pump 10kW, investment_kW | Z3: 1 | AA3: 0
A4: heat_pump_a_w_low | B4: 0 | C4: kWth | D4: 0 | E4: 0 | F4: 0 | G4: 2100 | H4: bus_el | I4: 1 | J4: 0 | N4: bus_th_low | O4: 2.8 | P4: 1 | Q4: 0 | R4: heat, central or small-scale, air-water heat pump 10kW, variable_MJ | S4: 3.6 | T4: 21.428571 | U4: 708 | V4: 20 | W4: 100000 | X4: 100000 | Y4: production, air-water heat pump 10kW, investment_kW | Z4: 1 | AA4: 0
A5: heat_pump_b_w_high | B5: 0 | C5: kWth | D5: 0 | E5: 0 | F5: 0 | G5: 2100 | H5: bus_el | I5: 1 | J5: 0 | K5: bus_th_ambient | L5: =O5-I5 -> 2.9217391 | M5: 0 | N5: bus_th | O5: =(AB5+273)/(AB5-AC5)*AD5 -> 3.9217391 | P5: 0 | Q5: 0 | R5: heat, central or small-scale, brine-water heat pump 10kW, variable_MJ | S5: 3.6 | T5: 15 | U5: 776 | V5: 20 | W5: 100000 | X5: 100000 | Y5: production, brine-water heat pump 10kW, investment_kW | Z5: 1 | AA5: 0 | AB5: 55 | AC5: 9 | AD5: 0.55
A6: heat_pump_b_w_low | B6: 0 | C6: kWth | D6: 0 | E6: 0 | F6: 0 | G6: 2100 | H6: bus_el | I6: 1 | J6: 0 | K6: bus_th_ambient | L6: =O6-I6 -> 4.5532258 | M6: 0 | N6: bus_th_low | O6: =(AB6+273)/(AB6-AC6)*AD6 -> 5.5532258 | P6: 0 | Q6: 0 | R6: heat, central or small-scale, brine-water heat pump 10kW, variable_MJ | S6: 3.6 | T6: 15 | U6: 776 | V6: 20 | W6: 100000 | X6: 100000 | Y6: production, brine-water heat pump 10kW, investment_kW | Z6: 1 | AA6: 0 | AB6: 40 | AC6: 9 | AD6: 0.55
A7: furnace_25_w_pellet | B7: 0 | C7: kWth | D7: 0 | E7: 0 | F7: 0 | G7: 2100 | H7: bus_pellets | I7: 1 | J7: 0 | N7: bus_th | O7: 0.8 | P7: 0 | Q7: 0 | R7: heat, central or small-scale, wood pellet, at furnace 25kW, state-of-the-art 2014, variable_MJ | S7: 3.6 | T7: 20 | U7: 1333 | V7: 20 | W7: 100000 | X7: 100000 | Y7: production, furnace, pellets, 25kW, investment_kW | Z7: 1 | AA7: 1
A8: furnace_30_logs | B8: 0 | C8: kWth | D8: 0 | E8: 0 | F8: 0 | G8: 2100 | H8: bus_logs | I8: 1 | J8: 0 | N8: bus_th | O8: 0.75 | P8: 0 | Q8: 0 | R8: heat, central or small-scale, mixed logs, at furnace 30kW, state-of-the-art 2014, variable_MJ | S8: 3.6 | T8: 23.666667 | U8: 433 | V8: 15 | W8: 100000 | X8: 100000 | Y8: production, furnace, logs, 30kW, investment_kW | Z8: 1 | AA8: 1
A9: furnace_300_w_chips | B9: 0 | C9: kWth | D9: 0 | E9: 0 | F9: 0 | G9: 2100 | H9: bus_w_chips | I9: 1 | J9: 0 | N9: bus_th | O9: 0.8 | P9: 0 | Q9: 0 | R9: heat, district or industrial, wood chips, at furnace 300kWth, state-of-the-art 2014, variable_MJ | S9: 3.6 | T9: 38 | U9: 975 | V9: 20 | W9: 100000 | X9: 100000 | Y9: production, furnace, wood chips, with silo, 300kW, investment_kW | Z9: 1 | AA9: 1
A10: furnace_100_w_pellet | B10: 0 | C10: kWth | D10: 0 | E10: 0 | F10: 0 | G10: 2100 | H10: bus_pellets | I10: 1 | J10: 0 | N10: bus_th | O10: 0.8 | P10: 0 | Q10: 0 | R10: heat, central or small-scale, wood pellet, at furnace 300kW, state-of-the-art 2014, variable_MJ | S10: 3.6 | T10: 38 | U10: 975 | V10: 20 | W10: 100000 | X10: 100000 | Y10: production, furnace, wood pellet, 300kW, investment_kW | Z10: 1 | AA10: 1
A11: boiler_100_biometh | B11: 0 | C11: kWth | D11: 0 | E11: 0 | F11: 0 | G11: 2100 | H11: bus_biometh | I11: 1 | J11: 0 | N11: bus_th | O11: 1.02 | P11: 0 | Q11: 0 | R11: heat, central or small-scale, biomethane, at boiler condensing modulating max 100kW, variable_MJ | S11: 3.6 | T11: 10.666667 | U11: 733 | V11: 20 | W11: 100000 | X11: 100000 | Y11: production, gas boiler, 10kW, investment_kW | Z11: 1 | AA11: 1
A12: heating_unit | B12: 0 | C12: kWth | D12: 0 | E12: 0 | F12: 0 | G12: 2100 | H12: bus_el | I12: 1 | J12: 0 | N12: bus_th | O12: 1 | P12: 0 | Q12: 0 | R12: empty | S12: 1 | T12: 0 | U12: 36.8 | V12: 20 | W12: 100000 | X12: 100000 | Y12: production, auxiliary heating unit, electric, 5kW, investment_kW | Z12: 1 | AA12: 0
A13: converter_high_low | B13: 0 | C13: kWth | D13: 0 | E13: 0 | F13: 0 | G13: 2100 | H13: bus_th_high | I13: 1 | J13: 0 | N13: bus_th_low | O13: 1 | P13: 0 | Q13: 0 | R13: empty | S13: 1 | T13: 0 | U13: 0 | V13: 20 | W13: 100000 | X13: 100000 | Y13: empty | Z13: 1 | AA13: 0
A14: hydrogen_fuel_cell | B14: 0 | C14: kWel | D14: 0 | E14: 0 | F14: 0 | G14: 2100 | H14: bus_hydrogen | I14: 1 | J14: 0 | N14: bus_el | O14: =0.5*33.3 -> 16.65 | P14: 0 | Q14: 0 | R14: empty | S14: 1 | T14: 0 | U14: 1 | V14: 15 | W14: 100000 | X14: 100000 | Y14: construction, CHP, fuel cell, polymer electrolyte membrane, 6.25kW, 2kWe, 3.44 kWth, future, investment_kW | Z14: 3.125 | AA14: 0
A16: heat_pump_a_w | B16: 0 | C16: kWth | D16: 0 | E16: 0 | F16: 0 | G16: 100000 | H16: bus_el | I16: 1 | J16: 0 | N16: bus_th_households | O16: 2.8 | P16: 0 | Q16: 0 | R16: heat production, air-water heat pump R134a | S16: 3.6 | T16: =0.02*U16 -> 10.714286 | U16: =1500/O16 -> 535.71429 | V16: 20 | W16: 100000 | X16: 100000 | Y16: production, market for heat pump, brine-water, 10kW | Z16: =1/10 -> 0.1 | AA16: 0 | AE16: ref economic: KEA Technikkatalog; ref LCA: BRINE-WATER heat pump; especially var_env1 assumptions probably too pessimistic (cooling medium: R134a)
A19: smr_proxy_i1 | B19: 1 | C19: kg/h | D19: 0 | E19: 0 | F19: 0 | G19: 2100 | H19: bus_el | I19: 1 | J19: 0 | K19: bus_water_deionized | L19: =972.54/12.9 -> 75.390698 | M19: 0 | N19: bus_smr_pi1 | O19: =89.93/12.9 -> 6.9713178 | P19: 0 | Q19: 0 | R19: empty | S19: 1 | T19: 0 | U19: 0 | V19: 100 | W19: 100000 | X19: 100000 | Y19: empty | Z19: 1 | AA19: 0
A21: steam_methane_reformer_existing | B21: 1 | C21: kg/h | D21: 1 | E21: 666 | F21: 0 | G21: 2100 | H21: bus_smr_pi1 | I21: 1 | J21: 0 | K21: bus_nat_gas | L21: =(315.78*12.9)/89.93 -> 45.297031 | M21: 0 | N21: bus_smre | O21: 1 | P21: 0 | Q21: 0 | R21: empty | S21: 1 | T21: 0 | U21: 0 | V21: 5 | W21: 100000 | X21: 100000 | Y21: empty | Z21: 1 | AA21: 1
A23: smr-ng_proxy_i2 | B23: 1 | C23: kg/h | D23: 0 | E23: 0 | F23: 0 | G23: 2100 | H23: bus_smr_pi1 | I23: 1 | J23: 0 | K23: bus_nat_gas | L23: =(315.78*12.9)/89.93 -> 45.297031 | M23: 0 | N23: bus_smr_pi2 | O23: 1 | P23: 0 | Q23: 0 | R23: empty | S23: 1 | T23: 0 | U23: 0 | V23: 100 | W23: 100000 | X23: 100000 | Y23: empty | Z23: 1 | AA23: 1
A24: smr-bio_proxy_i2_25 | B24: 0 | C24: kg/h | D24: 0 | E24: 0 | F24: 2025 | G24: 2030 | H24: bus_smr_pi1 | I24: 1 | J24: 0 | K24: bus_biometh | L24: =(315.78*12.9)/89.93 -> 45.297031 | M24: 0 | N24: bus_smr_pi2 | O24: 1 | P24: 0 | Q24: =-815.99/89.93*buses!N36 -> -0.68052096 | R24: co2_credit | S24: =815.99/89.93 -> 9.0736128 | T24: 0 | U24: 0 | V24: 100 | W24: 100000 | X24: 100000 | Y24: empty | Z24: 1 | AA24: 1
A25: smr-bio_proxy_i2_30 | B25: 0 | C25: kg/h | D25: 0 | E25: 0 | F25: 2030 | G25: 2035 | H25: bus_smr_pi1 | I25: 1 | J25: 0 | K25: bus_biometh | L25: =(315.78*12.9)/89.93 -> 45.297031 | M25: 0 | N25: bus_smr_pi2 | O25: 1 | P25: 0 | Q25: =-815.99/89.93*buses!O36 -> -1.3610419 | R25: co2_credit | S25: =815.99/89.93 -> 9.0736128 | T25: 0 | U25: 0 | V25: 100 | W25: 100000 | X25: 100000 | Y25: empty | Z25: 1 | AA25: 1
A26: smr-bio_proxy_i2_35 | B26: 0 | C26: kg/h | D26: 0 | E26: 0 | F26: 2035 | G26: 2040 | H26: bus_smr_pi1 | I26: 1 | J26: 0 | K26: bus_biometh | L26: =(315.78*12.9)/89.93 -> 45.297031 | M26: 0 | N26: bus_smr_pi2 | O26: 1 | P26: 0 | Q26: =-815.99/89.93*buses!P36 -> -2.0415629 | R26: co2_credit | S26: =815.99/89.93 -> 9.0736128 | T26: 0 | U26: 0 | V26: 100 | W26: 100000 | X26: 100000 | Y26: empty | Z26: 1 | AA26: 1
A27: smr-bio_proxy_i2_40 | B27: 0 | C27: kg/h | D27: 0 | E27: 0 | F27: 2040 | G27: 2045 | H27: bus_smr_pi1 | I27: 1 | J27: 0 | K27: bus_biometh | L27: =(315.78*12.9)/89.93 -> 45.297031 | M27: 0 | N27: bus_smr_pi2 | O27: 1 | P27: 0 | Q27: =-815.99/89.93*buses!Q36 -> -2.7220838 | R27: co2_credit | S27: =815.99/89.93 -> 9.0736128 | T27: 0 | U27: 0 | V27: 100 | W27: 100000 | X27: 100000 | Y27: empty | Z27: 1 | AA27: 1
A28: smr-bio_proxy_i2_45 | B28: 0 | C28: kg/h | D28: 0 | E28: 0 | F28: 2045 | G28: 2050 | H28: bus_smr_pi1 | I28: 1 | J28: 0 | K28: bus_biometh | L28: =(315.78*12.9)/89.93 -> 45.297031 | M28: 0 | N28: bus_smr_pi2 | O28: 1 | P28: 0 | Q28: =-815.99/89.93*buses!R36 -> -2.7220838 | R28: co2_credit | S28: =815.99/89.93 -> 9.0736128 | T28: 0 | U28: 0 | V28: 100 | W28: 100000 | X28: 100000 | Y28: empty | Z28: 1 | AA28: 1
A29: smr-bio_proxy_i2_50 | B29: 0 | C29: kg/h | D29: 0 | E29: 0 | F29: 2050 | G29: 2055 | H29: bus_smr_pi1 | I29: 1 | J29: 0 | K29: bus_biometh | L29: =(315.78*12.9)/89.93 -> 45.297031 | M29: 0 | N29: bus_smr_pi2 | O29: 1 | P29: 0 | Q29: =-815.99/89.93*buses!S36 -> -2.7220838 | R29: co2_credit | S29: =815.99/89.93 -> 9.0736128 | T29: 0 | U29: 0 | V29: 100 | W29: 100000 | X29: 100000 | Y29: empty | Z29: 1 | AA29: 1
A30: smr-bio_proxy_i2_55 | B30: 0 | C30: kg/h | D30: 0 | E30: 0 | F30: 2055 | G30: 2060 | H30: bus_smr_pi1 | I30: 1 | J30: 0 | K30: bus_biometh | L30: =(315.78*12.9)/89.93 -> 45.297031 | M30: 0 | N30: bus_smr_pi2 | O30: 1 | P30: 0 | Q30: =-815.99/89.93*buses!T36 -> -2.7220838 | R30: co2_credit | S30: =815.99/89.93 -> 9.0736128 | T30: 0 | U30: 0 | V30: 100 | W30: 100000 | X30: 100000 | Y30: empty | Z30: 1 | AA30: 1
A31: smr-bio_proxy_i2_60 | B31: 0 | C31: kg/h | D31: 0 | E31: 0 | F31: 2060 | G31: 2065 | H31: bus_smr_pi1 | I31: 1 | J31: 0 | K31: bus_biometh | L31: =(315.78*12.9)/89.93 -> 45.297031 | M31: 0 | N31: bus_smr_pi2 | O31: 1 | P31: 0 | Q31: =-815.99/89.93*buses!U36 -> -2.7220838 | R31: co2_credit | S31: =815.99/89.93 -> 9.0736128 | T31: 0 | U31: 0 | V31: 100 | W31: 100000 | X31: 100000 | Y31: empty | Z31: 1 | AA31: 1
A32: smr-bio_proxy_i2_65 | B32: 0 | C32: kg/h | D32: 0 | E32: 0 | F32: 2065 | G32: 2070 | H32: bus_smr_pi1 | I32: 1 | J32: 0 | K32: bus_biometh | L32: =(315.78*12.9)/89.93 -> 45.297031 | M32: 0 | N32: bus_smr_pi2 | O32: 1 | P32: 0 | Q32: =-815.99/89.93*buses!V36 -> -2.7220838 | R32: co2_credit | S32: =815.99/89.93 -> 9.0736128 | T32: 0 | U32: 0 | V32: 100 | W32: 100000 | X32: 100000 | Y32: empty | Z32: 1 | AA32: 1
A33: smr-bio_proxy_i2_70 | B33: 0 | C33: kg/h | D33: 0 | E33: 0 | F33: 2070 | G33: 2100 | H33: bus_smr_pi1 | I33: 1 | J33: 0 | K33: bus_biometh | L33: =(315.78*12.9)/89.93 -> 45.297031 | M33: 0 | N33: bus_smr_pi2 | O33: 1 | P33: 0 | Q33: =-815.99/89.93*buses!W36 -> -2.7220838 | R33: co2_credit | S33: =815.99/89.93 -> 9.0736128 | T33: 0 | U33: 0 | V33: 100 | W33: 100000 | X33: 100000 | Y33: empty | Z33: 1 | AA33: 1
A35: pem_electrolyzer_25 | B35: 1 | C35: kg/h | D35: 0 | E35: 0 | F35: 2025 | G35: 2030 | H35: bus_el-h2 | I35: 1 | J35: 0 | K35: bus_water_ultrapure | L35: =1238.1/4800 -> 0.2579375 | M35: 0 | N35: bus_pem | O35: =89.93/4800 -> 0.018735417 | P35: 0 | Q35: 0 | R35: empty | S35: 1 | T35: =$T$44 -> 830 | U35: 63281 | V35: =$V$44 -> 20 | W35: 100000 | X35: 100000 | Y35: PEM MWel_cons_2025 | Z35: =+O35/1000 -> 1.8735417e-05 | AA35: 0 | AE35: - all investment costs are based on 20a lifetime (last stack is sold after BoP's end of life - om is average value of year 25 & year 70 - 50% investment funding
A36: pem_electrolyzer_30 | B36: 1 | C36: kg/h | D36: 0 | E36: 0 | F36: 2030 | G36: 2035 | H36: bus_el-h2 | I36: 1 | J36: 0 | K36: bus_water_ultrapure | L36: =1238.1/4800 -> 0.2579375 | M36: 0 | N36: bus_pem | O36: =89.93/4800 -> 0.018735417 | P36: 0 | Q36: 0 | R36: empty | S36: 1 | T36: =$T$44 -> 830 | U36: 50235 | V36: =$V$44 -> 20 | W36: 100000 | X36: 100000 | Y36: PEM MWel_cons_2030 | Z36: =+O36/1000 -> 1.8735417e-05 | AA36: 0
A37: pem_electrolyzer_35 | B37: 1 | C37: kg/h | D37: 0 | E37: 0 | F37: 2035 | G37: 2040 | H37: bus_el-h2 | I37: 1 | J37: 0 | K37: bus_water_ultrapure | L37: =1238.1/4800 -> 0.2579375 | M37: 0 | N37: bus_pem | O37: =89.93/4800 -> 0.018735417 | P37: 0 | Q37: 0 | R37: empty | S37: 1 | T37: =$T$44 -> 830 | U37: 40246 | V37: =$V$44 -> 20 | W37: 100000 | X37: 100000 | Y37: PEM MWel_cons_2035 | Z37: =+O37/1000 -> 1.8735417e-05 | AA37: 0
A38: pem_electrolyzer_40 | B38: 1 | C38: kg/h | D38: 0 | E38: 0 | F38: 2040 | G38: 2045 | H38: bus_el-h2 | I38: 1 | J38: 0 | K38: bus_water_ultrapure | L38: =1238.1/4800 -> 0.2579375 | M38: 0 | N38: bus_pem | O38: =89.93/4800 -> 0.018735417 | P38: 0 | Q38: 0 | R38: empty | S38: 1 | T38: =$T$44 -> 830 | U38: 32514 | V38: =$V$44 -> 20 | W38: 100000 | X38: 100000 | Y38: PEM MWel_cons_2040 | Z38: =+O38/1000 -> 1.8735417e-05 | AA38: 0
A39: pem_electrolyzer_45 | B39: 1 | C39: kg/h | D39: 0 | E39: 0 | F39: 2045 | G39: 2050 | H39: bus_el-h2 | I39: 1 | J39: 0 | K39: bus_water_ultrapure | L39: =1238.1/4800 -> 0.2579375 | M39: 0 | N39: bus_pem | O39: =89.93/4800 -> 0.018735417 | P39: 0 | Q39: 0 | R39: empty | S39: 1 | T39: =$T$44 -> 830 | U39: 28900 | V39: =$V$44 -> 20 | W39: 100000 | X39: 100000 | Y39: PEM MWel_cons_2045 | Z39: =+O39/1000 -> 1.8735417e-05 | AA39: 0
A40: pem_electrolyzer_50 | B40: 1 | C40: kg/h | D40: 0 | E40: 0 | F40: 2050 | G40: 2055 | H40: bus_el-h2 | I40: 1 | J40: 0 | K40: bus_water_ultrapure | L40: =1238.1/4800 -> 0.2579375 | M40: 0 | N40: bus_pem | O40: =89.93/4800 -> 0.018735417 | P40: 0 | Q40: 0 | R40: empty | S40: 1 | T40: =$T$44 -> 830 | U40: 28900 | V40: =$V$44 -> 20 | W40: 100000 | X40: 100000 | Y40: PEM MWel_cons_2045 | Z40: =+O40/1000 -> 1.8735417e-05 | AA40: 0
A41: pem_electrolyzer_55 | B41: 1 | C41: kg/h | D41: 0 | E41: 0 | F41: 2055 | G41: 2060 | H41: bus_el-h2 | I41: 1 | J41: 0 | K41: bus_water_ultrapure | L41: =1238.1/4800 -> 0.2579375 | M41: 0 | N41: bus_pem | O41: =89.93/4800 -> 0.018735417 | P41: 0 | Q41: 0 | R41: empty | S41: 1 | T41: =$T$44 -> 830 | U41: 28900 | V41: =$V$44 -> 20 | W41: 100000 | X41: 100000 | Y41: PEM MWel_cons_2045 | Z41: =+O41/1000 -> 1.8735417e-05 | AA41: 0
A42: pem_electrolyzer_60 | B42: 1 | C42: kg/h | D42: 0 | E42: 0 | F42: 2060 | G42: 2065 | H42: bus_el-h2 | I42: 1 | J42: 0 | K42: bus_water_ultrapure | L42: =1238.1/4800 -> 0.2579375 | M42: 0 | N42: bus_pem | O42: =89.93/4800 -> 0.018735417 | P42: 0 | Q42: 0 | R42: empty | S42: 1 | T42: =$T$44 -> 830 | U42: 28900 | V42: =$V$44 -> 20 | W42: 100000 | X42: 100000 | Y42: PEM MWel_cons_2045 | Z42: =+O42/1000 -> 1.8735417e-05 | AA42: 0
A43: pem_electrolyzer_65 | B43: 1 | C43: kg/h | D43: 0 | E43: 0 | F43: 2065 | G43: 2070 | H43: bus_el-h2 | I43: 1 | J43: 0 | K43: bus_water_ultrapure | L43: =1238.1/4800 -> 0.2579375 | M43: 0 | N43: bus_pem | O43: =89.93/4800 -> 0.018735417 | P43: 0 | Q43: 0 | R43: empty | S43: 1 | T43: =$T$44 -> 830 | U43: 28900 | V43: =$V$44 -> 20 | W43: 100000 | X43: 100000 | Y43: PEM MWel_cons_2045 | Z43: =+O43/1000 -> 1.8735417e-05 | AA43: 0
A44: pem_electrolyzer_70 | B44: 1 | C44: kg/h | D44: 0 | E44: 0 | F44: 2070 | G44: 2075 | H44: bus_el-h2 | I44: 1 | J44: 0 | K44: bus_water_ultrapure | L44: =1238.1/4800 -> 0.2579375 | M44: 0 | N44: bus_pem | O44: =89.93/4800 -> 0.018735417 | P44: 0 | Q44: 0 | R44: empty | S44: 1 | T44: 830 | U44: 28900 | V44: 20 | W44: 100000 | X44: 100000 | Y44: PEM MWel_cons_2045 | Z44: =+O44/1000 -> 1.8735417e-05 | AA44: 0
A46: ael_electrolyzer_25 | B46: 0 | C46: kg/h | D46: 0 | E46: 0 | F46: 2025 | G46: 2030 | H46: bus_el-h2 | I46: 1 | J46: 0 | K46: bus_water_ultrapure | L46: =1221.7/4600 -> 0.26558696 | M46: 0 | N46: bus_ael | O46: =89.93/4600 -> 0.01955 | P46: 0 | Q46: 0 | R46: empty | S46: 1 | T46: =$T$55 -> 905 | U46: 48159.419 | V46: =$V$55 -> 20 | W46: 100000 | X46: 100000 | Y46: AEL MWel_cons_2025 | Z46: =O46/1000 -> 1.955e-05 | AA46: 0 | AE46: - all investment costs are based on 20a lifetime (last stack is sold after BoP's end of life - om is average value of year 25 & year 70
A47: ael_electrolyzer_30 | B47: 0 | C47: kg/h | D47: 0 | E47: 0 | F47: 2030 | G47: 2035 | H47: bus_el-h2 | I47: 1 | J47: 0 | K47: bus_water_ultrapure | L47: =1221.7/4600 -> 0.26558696 | M47: 0 | N47: bus_ael | O47: =89.93/4600 -> 0.01955 | P47: 0 | Q47: 0 | R47: empty | S47: 1 | T47: =$T$55 -> 905 | U47: 46135.482 | V47: =$V$55 -> 20 | W47: 100000 | X47: 100000 | Y47: AEL MWel_cons_2030 | Z47: =O47/1000 -> 1.955e-05 | AA47: 0
A48: ael_electrolyzer_35 | B48: 0 | C48: kg/h | D48: 0 | E48: 0 | F48: 2035 | G48: 2040 | H48: bus_el-h2 | I48: 1 | J48: 0 | K48: bus_water_ultrapure | L48: =1221.7/4600 -> 0.26558696 | M48: 0 | N48: bus_ael | O48: =89.93/4600 -> 0.01955 | P48: 0 | Q48: 0 | R48: empty | S48: 1 | T48: =$T$55 -> 905 | U48: 42944.722 | V48: =$V$55 -> 20 | W48: 100000 | X48: 100000 | Y48: AEL MWel_cons_2035 | Z48: =O48/1000 -> 1.955e-05 | AA48: 0
A49: ael_electrolyzer_40 | B49: 0 | C49: kg/h | D49: 0 | E49: 0 | F49: 2040 | G49: 2045 | H49: bus_el-h2 | I49: 1 | J49: 0 | K49: bus_water_ultrapure | L49: =1221.7/4600 -> 0.26558696 | M49: 0 | N49: bus_ael | O49: =89.93/4600 -> 0.01955 | P49: 0 | Q49: 0 | R49: empty | S49: 1 | T49: =$T$55 -> 905 | U49: 41067.382 | V49: =$V$55 -> 20 | W49: 100000 | X49: 100000 | Y49: AEL MWel_cons_2040 | Z49: =O49/1000 -> 1.955e-05 | AA49: 0
A50: ael_electrolyzer_45 | B50: 0 | C50: kg/h | D50: 0 | E50: 0 | F50: 2045 | G50: 2050 | H50: bus_el-h2 | I50: 1 | J50: 0 | K50: bus_water_ultrapure | L50: =1221.7/4600 -> 0.26558696 | M50: 0 | N50: bus_ael | O50: =89.93/4600 -> 0.01955 | P50: 0 | Q50: 0 | R50: empty | S50: 1 | T50: =$T$55 -> 905 | U50: 39262.287 | V50: =$V$55 -> 20 | W50: 100000 | X50: 100000 | Y50: AEL MWel_cons_2045 | Z50: =O50/1000 -> 1.955e-05 | AA50: 0
A51: ael_electrolyzer_50 | B51: 0 | C51: kg/h | D51: 0 | E51: 0 | F51: 2050 | G51: 2055 | H51: bus_el-h2 | I51: 1 | J51: 0 | K51: bus_water_ultrapure | L51: =1221.7/4600 -> 0.26558696 | M51: 0 | N51: bus_ael | O51: =89.93/4600 -> 0.01955 | P51: 0 | Q51: 0 | R51: empty | S51: 1 | T51: =$T$55 -> 905 | U51: 39262.287 | V51: =$V$55 -> 20 | W51: 100000 | X51: 100000 | Y51: AEL MWel_cons_2045 | Z51: =O51/1000 -> 1.955e-05 | AA51: 0
A52: ael_electrolyzer_55 | B52: 0 | C52: kg/h | D52: 0 | E52: 0 | F52: 2055 | G52: 2060 | H52: bus_el-h2 | I52: 1 | J52: 0 | K52: bus_water_ultrapure | L52: =1221.7/4600 -> 0.26558696 | M52: 0 | N52: bus_ael | O52: =89.93/4600 -> 0.01955 | P52: 0 | Q52: 0 | R52: empty | S52: 1 | T52: =$T$55 -> 905 | U52: 39262.287 | V52: =$V$55 -> 20 | W52: 100000 | X52: 100000 | Y52: AEL MWel_cons_2045 | Z52: =O52/1000 -> 1.955e-05 | AA52: 0
A53: ael_electrolyzer_60 | B53: 0 | C53: kg/h | D53: 0 | E53: 0 | F53: 2060 | G53: 2065 | H53: bus_el-h2 | I53: 1 | J53: 0 | K53: bus_water_ultrapure | L53: =1221.7/4600 -> 0.26558696 | M53: 0 | N53: bus_ael | O53: =89.93/4600 -> 0.01955 | P53: 0 | Q53: 0 | R53: empty | S53: 1 | T53: =$T$55 -> 905 | U53: 39262.287 | V53: =$V$55 -> 20 | W53: 100000 | X53: 100000 | Y53: AEL MWel_cons_2045 | Z53: =O53/1000 -> 1.955e-05 | AA53: 0
A54: ael_electrolyzer_65 | B54: 0 | C54: kg/h | D54: 0 | E54: 0 | F54: 2065 | G54: 2070 | H54: bus_el-h2 | I54: 1 | J54: 0 | K54: bus_water_ultrapure | L54: =1221.7/4600 -> 0.26558696 | M54: 0 | N54: bus_ael | O54: =89.93/4600 -> 0.01955 | P54: 0 | Q54: 0 | R54: empty | S54: 1 | T54: =$T$55 -> 905 | U54: 39262.287 | V54: =$V$55 -> 20 | W54: 100000 | X54: 100000 | Y54: AEL MWel_cons_2045 | Z54: =O54/1000 -> 1.955e-05 | AA54: 0
A55: ael_electrolyzer_70 | B55: 0 | C55: kg/h | D55: 0 | E55: 0 | F55: 2070 | G55: 2075 | H55: bus_el-h2 | I55: 1 | J55: 0 | K55: bus_water_ultrapure | L55: =1221.7/4600 -> 0.26558696 | M55: 0 | N55: bus_ael | O55: =89.93/4600 -> 0.01955 | P55: 0 | Q55: 0 | R55: empty | S55: 1 | T55: 905 | U55: 39262.287 | V55: 20 | W55: 100000 | X55: 100000 | Y55: AEL MWel_cons_2045 | Z55: =O55/1000 -> 1.955e-05 | AA55: 0
A57: aem_electrolyzer_30 | B57: 0 | C57: kg/h | D57: 0 | E57: 0 | F57: 2030 | G57: 2100 | H57: bus_el | I57: 1 | J57: 0 | K57: bus_water_ultrapure | L57: =1238.1/4800 -> 0.2579375 | M57: 0 | N57: bus_aem | O57: =89.93/4800 -> 0.018735417 | P57: 0 | Q57: 0 | R57: empty | S57: 1 | T57: 7000 | U57: 150000 | V57: 20 | W57: 100000 | X57: 100000 | Y57: empty | Z57: 1 | AA57: 0
A58: aem_electrolyzer_35 | B58: 0 | C58: kg/h | D58: 0 | E58: 0 | F58: 2035 | G58: 2040 | H58: bus_el | J58: 0 | K58: bus_water_ultrapure | M58: 0 | N58: bus_aem | P58: 0 | Q58: 0 | R58: empty | S58: 1 | W58: 100000 | X58: 100000 | AA58: 0
A59: aem_electrolyzer_40 | B59: 0 | C59: kg/h | D59: 0 | E59: 0 | F59: 2040 | G59: 2045 | H59: bus_el | J59: 0 | K59: bus_water_ultrapure | M59: 0 | N59: bus_aem | P59: 0 | Q59: 0 | R59: empty | S59: 1 | W59: 100000 | X59: 100000 | AA59: 0
A60: aem_electrolyzer_45 | B60: 0 | C60: kg/h | D60: 0 | E60: 0 | F60: 2045 | G60: 2100 | H60: bus_el | J60: 0 | K60: bus_water_ultrapure | M60: 0 | N60: bus_aem | P60: 0 | Q60: 0 | R60: empty | S60: 1 | W60: 100000 | X60: 100000 | AA60: 0
A62: soec_proxy_i1 | B62: 1 | C62: kg/h | D62: 0 | E62: 0 | F62: 2025 | G62: 2030 | H62: bus_el-h2 | I62: 1 | J62: 0 | K62: bus_water_ultrapure | L62: =1146.67/3573.3 -> 0.32089945 | M62: 0 | N62: bus_soec_pi1 | O62: =89.93/3573.3 -> 0.025167212 | P62: 0 | Q62: 0 | R62: empty | S62: 1 | T62: 0 | U62: 0 | V62: 100 | W62: 100000 | X62: 100000 | Y62: empty | Z62: 1 | AA62: 0 | AE62: - all investment costs are based on 20a lifetime (last stack is sold after BoP's end of life - om is average value of year 25 & year 70 - 50% investmet funding
A63: so_electrolyzer_25 | B63: 1 | C63: kg/h | D63: 0 | E63: 0 | F63: 2025 | G63: 2030 | H63: bus_soec_pi1 | I63: 1 | J63: 0 | K63: bus_th200 | L63: =908/89.93 -> 10.096742 | M63: 0 | N63: bus_soec | O63: 1 | P63: 0 | Q63: 0 | R63: empty | S63: 1 | T63: =$T$72 -> 1127 | U63: 93727.001 | V63: =$V$72 -> 20 | W63: 0 | X63: =$X$72 -> 100000 | Y63: SOEC MWel_cons_2025 | Z63: =+$O$62/1000 -> 2.5167212e-05 | AA63: 0
A64: so_electrolyzer_30 | B64: 1 | C64: kg/h | D64: 0 | E64: 0 | F64: 2030 | G64: 2035 | H64: bus_soec_pi1 | I64: 1 | J64: 0 | K64: bus_th200 | L64: =908/89.93 -> 10.096742 | M64: 0 | N64: bus_soec | O64: 1 | P64: 0 | Q64: 0 | R64: empty | S64: 1 | T64: =$T$72 -> 1127 | U64: 54071.206 | V64: =$V$72 -> 20 | W64: 100000 | X64: =$X$72 -> 100000 | Y64: SOEC MWel_cons_2030 | Z64: =+$O$62/1000 -> 2.5167212e-05 | AA64: 0
A65: so_electrolyzer_35 | B65: 1 | C65: kg/h | D65: 0 | E65: 0 | F65: 2035 | G65: 2040 | H65: bus_soec_pi1 | I65: 1 | J65: 0 | K65: bus_th200 | L65: =908/89.93 -> 10.096742 | M65: 0 | N65: bus_soec | O65: 1 | P65: 0 | Q65: 0 | R65: empty | S65: 1 | T65: =$T$72 -> 1127 | U65: 39055.498 | V65: =$V$72 -> 20 | W65: 100000 | X65: =$X$72 -> 100000 | Y65: SOEC MWel_cons_2035 | Z65: =+$O$62/1000 -> 2.5167212e-05 | AA65: 0
A66: so_electrolyzer_40 | B66: 1 | C66: kg/h | D66: 0 | E66: 0 | F66: 2040 | G66: 2045 | H66: bus_soec_pi1 | I66: 1 | J66: 0 | K66: bus_th200 | L66: =908/89.93 -> 10.096742 | M66: 0 | N66: bus_soec | O66: 1 | P66: 0 | Q66: 0 | R66: empty | S66: 1 | T66: =$T$72 -> 1127 | U66: 28959.898 | V66: =$V$72 -> 20 | W66: 100000 | X66: =$X$72 -> 100000 | Y66: SOEC MWel_cons_2040 | Z66: =+$O$62/1000 -> 2.5167212e-05 | AA66: 0
A67: so_electrolyzer_45 | B67: 1 | C67: kg/h | D67: 0 | E67: 0 | F67: 2045 | G67: 2050 | H67: bus_soec_pi1 | I67: 1 | J67: 0 | K67: bus_th200 | L67: =908/89.93 -> 10.096742 | M67: 0 | N67: bus_soec | O67: 1 | P67: 0 | Q67: 0 | R67: empty | S67: 1 | T67: =$T$72 -> 1127 | U67: 22752.529 | V67: =$V$72 -> 20 | W67: 100000 | X67: =$X$72 -> 100000 | Y67: SOEC MWel_cons_2045 | Z67: =+$O$62/1000 -> 2.5167212e-05 | AA67: 0
A68: so_electrolyzer_50 | B68: 1 | C68: kg/h | D68: 0 | E68: 0 | F68: 2050 | G68: 2055 | H68: bus_soec_pi1 | I68: 1 | J68: 0 | K68: bus_th200 | L68: =908/89.93 -> 10.096742 | M68: 0 | N68: bus_soec | O68: 1 | P68: 0 | Q68: 0 | R68: empty | S68: 1 | T68: =$T$72 -> 1127 | U68: 22752.529 | V68: =$V$72 -> 20 | W68: 100000 | X68: =$X$72 -> 100000 | Y68: SOEC MWel_cons_2045 | Z68: =+$O$62/1000 -> 2.5167212e-05 | AA68: 0
A69: so_electrolyzer_55 | B69: 1 | C69: kg/h | D69: 0 | E69: 0 | F69: 2055 | G69: 2060 | H69: bus_soec_pi1 | I69: 1 | J69: 0 | K69: bus_th200 | L69: =908/89.93 -> 10.096742 | M69: 0 | N69: bus_soec | O69: 1 | P69: 0 | Q69: 0 | R69: empty | S69: 1 | T69: =$T$72 -> 1127 | U69: 22752.529 | V69: =$V$72 -> 20 | W69: 100000 | X69: =$X$72 -> 100000 | Y69: SOEC MWel_cons_2045 | Z69: =+$O$62/1000 -> 2.5167212e-05 | AA69: 0
A70: so_electrolyzer_60 | B70: 1 | C70: kg/h | D70: 0 | E70: 0 | F70: 2060 | G70: 2065 | H70: bus_soec_pi1 | I70: 1 | J70: 0 | K70: bus_th200 | L70: =908/89.93 -> 10.096742 | M70: 0 | N70: bus_soec | O70: 1 | P70: 0 | Q70: 0 | R70: empty | S70: 1 | T70: =$T$72 -> 1127 | U70: 22752.529 | V70: =$V$72 -> 20 | W70: 100000 | X70: =$X$72 -> 100000 | Y70: SOEC MWel_cons_2045 | Z70: =+$O$62/1000 -> 2.5167212e-05 | AA70: 0
A71: so_electrolyzer_65 | B71: 1 | C71: kg/h | D71: 0 | E71: 0 | F71: 2065 | G71: 2070 | H71: bus_soec_pi1 | I71: 1 | J71: 0 | K71: bus_th200 | L71: =908/89.93 -> 10.096742 | M71: 0 | N71: bus_soec | O71: 1 | P71: 0 | Q71: 0 | R71: empty | S71: 1 | T71: =$T$72 -> 1127 | U71: 22752.529 | V71: =$V$72 -> 20 | W71: 100000 | X71: =$X$72 -> 100000 | Y71: SOEC MWel_cons_2045 | Z71: =+$O$62/1000 -> 2.5167212e-05 | AA71: 0
A72: so_electrolyzer_70 | B72: 1 | C72: kg/h | D72: 0 | E72: 0 | F72: 2070 | G72: 2075 | H72: bus_soec_pi1 | I72: 1 | J72: 0 | K72: bus_th200 | L72: =908/89.93 -> 10.096742 | M72: 0 | N72: bus_soec | O72: 1 | P72: 0 | Q72: 0 | R72: empty | S72: 1 | T72: 1127 | U72: 22752.529 | V72: 20 | W72: 100000 | X72: 100000 | Y72: SOEC MWel_cons_2045 | Z72: =+$O$62/1000 -> 2.5167212e-05 | AA72: 0
A74: atr_proxy_i1 | B74: 0 | C74: kg/h | D74: 0 | E74: 0 | F74: 0 | G74: 2100 | H74: bus_water_deionized | I74: 1 | J74: 0 | K74: bus_el | L74: =386.4/687.46 -> 0.56206907 | M74: 0 | N74: bus_atr_pi1 | O74: =89.93/687.46 -> 0.13081488 | P74: 0 | Q74: 0 | R74: empty | S74: 1 | T74: 0 | U74: 0 | V74: 100 | W74: 100000 | X74: =$X$84 -> 100000 | Y74: empty | Z74: 1 | AA74: 0
A75: autothermal_reformer_25 | B75: 0 | C75: kg/h | D75: 0 | E75: 0 | F75: 2025 | G75: 2030 | H75: bus_atr_pi1 | I75: 1 | J75: 0 | K75: bus_biogas | L75: =(865.9*5)/89.93 -> 48.143 | M75: 0 | N75: bus_atr | O75: =I75 -> 1 | P75: 0 | Q75: =-(1399.51/89.93)*buses!N36 -> -1.1671661 | R75: co2_credit | S75: =1399.51/89.93 -> 15.562215 | T75: =$T$84 -> 592 | U75: 25111 | V75: =$V$84 -> 25 | W75: 0 | X75: =$X$84 -> 100000 | Y75: SMR_cons_2025 | Z75: =1/9000.9 -> 0.0001111 | AA75: 0
A76: autothermal_reformer_30 | B76: 0 | C76: kg/h | D76: 0 | E76: 0 | F76: 2030 | G76: 2035 | H76: bus_atr_pi1 | I76: 1 | J76: 0 | K76: bus_biogas | L76: =(865.9*5)/89.93 -> 48.143 | M76: 0 | N76: bus_atr | O76: =I76 -> 1 | P76: 0 | Q76: =-(1399.51/89.93)*buses!O36 -> -2.3343323 | R76: co2_credit | S76: =1399.51/89.93 -> 15.562215 | T76: =$T$84 -> 592 | U76: 23429 | V76: =$V$84 -> 25 | W76: 0 | X76: =$X$84 -> 100000 | Y76: SMR_cons_2030 | Z76: =1/9000.9 -> 0.0001111 | AA76: 0
A77: autothermal_reformer_35 | B77: 0 | C77: kg/h | D77: 0 | E77: 0 | F77: 2035 | G77: 2040 | H77: bus_atr_pi1 | I77: 1 | J77: 0 | K77: bus_biogas | L77: =(865.9*5)/89.93 -> 48.143 | M77: 0 | N77: bus_atr | O77: =I77 -> 1 | P77: 0 | Q77: =-(1399.51/89.93)*buses!P36 -> -3.5014984 | R77: co2_credit | S77: =1399.51/89.93 -> 15.562215 | T77: =$T$84 -> 592 | U77: 21863 | V77: =$V$84 -> 25 | W77: 0 | X77: =$X$84 -> 100000 | Y77: SMR_cons_2035 | Z77: =1/9000.9 -> 0.0001111 | AA77: 0
A78: autothermal_reformer_40 | B78: 0 | C78: kg/h | D78: 0 | E78: 0 | F78: 2040 | G78: 2045 | H78: bus_atr_pi1 | I78: 1 | J78: 0 | K78: bus_biogas | L78: =(865.9*5)/89.93 -> 48.143 | M78: 0 | N78: bus_atr | O78: =I78 -> 1 | P78: 0 | Q78: =-(1399.51/89.93)*buses!Q36 -> -4.6686645 | R78: co2_credit | S78: =1399.51/89.93 -> 15.562215 | T78: =$T$84 -> 592 | U78: 20405 | V78: =$V$84 -> 25 | W78: 100000 | X78: =$X$84 -> 100000 | Y78: SMR_cons_2040 | Z78: =1/9000.9 -> 0.0001111 | AA78: 0
A79: autothermal_reformer_45 | B79: 0 | C79: kg/h | D79: 0 | E79: 0 | F79: 2045 | G79: 2050 | H79: bus_atr_pi1 | I79: 1 | J79: 0 | K79: bus_biogas | L79: =(865.9*5)/89.93 -> 48.143 | M79: 0 | N79: bus_atr | O79: =I79 -> 1 | P79: 0 | Q79: =-(1399.51/89.93)*buses!R36 -> -4.6686645 | R79: co2_credit | S79: =1399.51/89.93 -> 15.562215 | T79: =$T$84 -> 592 | U79: 19047 | V79: =$V$84 -> 25 | W79: 100000 | X79: =$X$84 -> 100000 | Y79: SMR_cons_2045 | Z79: =1/9000.9 -> 0.0001111 | AA79: 0
A80: autothermal_reformer_50 | B80: 0 | C80: kg/h | D80: 0 | E80: 0 | F80: 2050 | G80: 2055 | H80: bus_atr_pi1 | I80: 1 | J80: 0 | K80: bus_biogas | L80: =(865.9*5)/89.93 -> 48.143 | M80: 0 | N80: bus_atr | O80: =I80 -> 1 | P80: 0 | Q80: =-(1399.51/89.93)*buses!S36 -> -4.6686645 | R80: co2_credit | S80: =1399.51/89.93 -> 15.562215 | T80: =$T$84 -> 592 | U80: 19047 | V80: =$V$84 -> 25 | W80: 100000 | X80: =$X$84 -> 100000 | Y80: SMR_cons_2045 | Z80: =1/9000.9 -> 0.0001111 | AA80: 0
A81: autothermal_reformer_55 | B81: 0 | C81: kg/h | D81: 0 | E81: 0 | F81: 2055 | G81: 2060 | H81: bus_atr_pi1 | I81: 1 | J81: 0 | K81: bus_biogas | L81: =(865.9*5)/89.93 -> 48.143 | M81: 0 | N81: bus_atr | O81: =I81 -> 1 | P81: 0 | Q81: =-(1399.51/89.93)*buses!T36 -> -4.6686645 | R81: co2_credit | S81: =1399.51/89.93 -> 15.562215 | T81: =$T$84 -> 592 | U81: 19047 | V81: =$V$84 -> 25 | W81: 100000 | X81: =$X$84 -> 100000 | Y81: SMR_cons_2045 | Z81: =1/9000.9 -> 0.0001111 | AA81: 0
A82: autothermal_reformer_60 | B82: 0 | C82: kg/h | D82: 0 | E82: 0 | F82: 2060 | G82: 2065 | H82: bus_atr_pi1 | I82: 1 | J82: 0 | K82: bus_biogas | L82: =(865.9*5)/89.93 -> 48.143 | M82: 0 | N82: bus_atr | O82: =I82 -> 1 | P82: 0 | Q82: =-(1399.51/89.93)*buses!U36 -> -4.6686645 | R82: co2_credit | S82: =1399.51/89.93 -> 15.562215 | T82: =$T$84 -> 592 | U82: 19047 | V82: =$V$84 -> 25 | W82: 100000 | X82: =$X$84 -> 100000 | Y82: SMR_cons_2045 | Z82: =1/9000.9 -> 0.0001111 | AA82: 0
A83: autothermal_reformer_65 | B83: 0 | C83: kg/h | D83: 0 | E83: 0 | F83: 2065 | G83: 2070 | H83: bus_atr_pi1 | I83: 1 | J83: 0 | K83: bus_biogas | L83: =(865.9*5)/89.93 -> 48.143 | M83: 0 | N83: bus_atr | O83: =I83 -> 1 | P83: 0 | Q83: =-(1399.51/89.93)*buses!V36 -> -4.6686645 | R83: co2_credit | S83: =1399.51/89.93 -> 15.562215 | T83: =$T$84 -> 592 | U83: 19047 | V83: =$V$84 -> 25 | W83: 100000 | X83: =$X$84 -> 100000 | Y83: SMR_cons_2045 | Z83: =1/9000.9 -> 0.0001111 | AA83: 0
A84: autothermal_reformer_70 | B84: 0 | C84: kg/h | D84: 0 | E84: 0 | F84: 2070 | G84: 2075 | H84: bus_atr_pi1 | I84: 1 | J84: 0 | K84: bus_biogas | L84: =(865.9*5)/89.93 -> 48.143 | M84: 0 | N84: bus_atr | O84: =I84 -> 1 | P84: 0 | Q84: =-(1399.51/89.93)*buses!W36 -> -4.6686645 | R84: co2_credit | S84: =1399.51/89.93 -> 15.562215 | T84: 592 | U84: 19047 | V84: 25 | W84: 100000 | X84: 100000 | Y84: SMR_cons_2045 | Z84: =1/9000.9 -> 0.0001111 | AA84: 0 | AE84: om actually 6% per year of invest costs
A86: lohc-dehy_proxy_i1 | B86: 1 | C86: kg/h | D86: 0 | E86: 0 | F86: 0 | G86: 2100 | H86: bus_lohc | I86: 1 | J86: 0 | K86: bus_th400 | L86: =809.4/1445.23 -> 0.56004927 | M86: 0 | N86: bus_lohcdehy_pi1 | O86: =89.93/1445.23 -> 0.06222539 | P86: 0 | Q86: 0 | R86: empty | S86: 1 | T86: 0 | U86: 0 | V86: 100 | W86: 100000 | X86: 100000 | Y86: empty | Z86: 1 | AA86: 0
A87: lohc-dehydrogenation_25 | B87: 1 | C87: kg/h | D87: 0 | E87: 0 | F87: 2025 | G87: 2030 | H87: bus_lohcdehy_pi1 | I87: 1 | J87: 0 | K87: bus_el-h2 | L87: =(33.3+131.4)/89.93 -> 1.8314244 | M87: 0 | N87: bus_hydrogen | O87: 1 | P87: 0 | Q87: 0 | R87: empty | S87: 1 | T87: =$T$96 -> 465 | U87: 13657 | V87: =$V$96 -> 20 | W87: 0 | X87: 100000 | Y87: construction chemical factory 1ha, organics | Z87: =0.4/571 -> 0.00070052539 | AA87: 0
A88: lohc-dehydrogenation_30 | B88: 1 | C88: kg/h | D88: 0 | E88: 0 | F88: 2030 | G88: 2035 | H88: bus_lohcdehy_pi1 | I88: 1 | J88: 0 | K88: bus_el-h2 | L88: =(33.3+131.4)/89.93 -> 1.8314244 | M88: 0 | N88: bus_hydrogen | O88: 1 | P88: 0 | Q88: 0 | R88: empty | S88: 1 | T88: =$T$96 -> 465 | U88: 12911 | V88: =$V$96 -> 20 | W88: 100000 | X88: 100000 | Y88: construction chemical factory 1ha, organics | Z88: =0.4/571 -> 0.00070052539 | AA88: 0
A89: lohc-dehydrogenation_35 | B89: 1 | C89: kg/h | D89: 0 | E89: 0 | F89: 2035 | G89: 2040 | H89: bus_lohcdehy_pi1 | I89: 1 | J89: 0 | K89: bus_el-h2 | L89: =(33.3+131.4)/89.93 -> 1.8314244 | M89: 0 | N89: bus_hydrogen | O89: 1 | P89: 0 | Q89: 0 | R89: empty | S89: 1 | T89: =$T$96 -> 465 | U89: 12207 | V89: =$V$96 -> 20 | W89: 100000 | X89: 100000 | Y89: construction chemical factory 1ha, organics | Z89: =0.4/571 -> 0.00070052539 | AA89: 0
A90: lohc-dehydrogenation_40 | B90: 1 | C90: kg/h | D90: 0 | E90: 0 | F90: 2040 | G90: 2045 | H90: bus_lohcdehy_pi1 | I90: 1 | J90: 0 | K90: bus_el-h2 | L90: =(33.3+131.4)/89.93 -> 1.8314244 | M90: 0 | N90: bus_hydrogen | O90: 1 | P90: 0 | Q90: 0 | R90: empty | S90: 1 | T90: =$T$96 -> 465 | U90: 11543 | V90: =$V$96 -> 20 | W90: 100000 | X90: 100000 | Y90: construction chemical factory 1ha, organics | Z90: =0.4/571 -> 0.00070052539 | AA90: 0
A91: lohc-dehydrogenation_45 | B91: 1 | C91: kg/h | D91: 0 | E91: 0 | F91: 2045 | G91: 2050 | H91: bus_lohcdehy_pi1 | I91: 1 | J91: 0 | K91: bus_el-h2 | L91: =(33.3+131.4)/89.93 -> 1.8314244 | M91: 0 | N91: bus_hydrogen | O91: 1 | P91: 0 | Q91: 0 | R91: empty | S91: 1 | T91: =$T$96 -> 465 | U91: 10916 | V91: =$V$96 -> 20 | W91: 100000 | X91: 100000 | Y91: construction chemical factory 1ha, organics | Z91: =0.4/571 -> 0.00070052539 | AA91: 0
A92: lohc-dehydrogenation_50 | B92: 1 | C92: kg/h | D92: 0 | E92: 0 | F92: 2050 | G92: 2055 | H92: bus_lohcdehy_pi1 | I92: 1 | J92: 0 | K92: bus_el-h2 | L92: =(33.3+131.4)/89.93 -> 1.8314244 | M92: 0 | N92: bus_hydrogen | O92: 1 | P92: 0 | Q92: 0 | R92: empty | S92: 1 | T92: =$T$96 -> 465 | U92: 10916 | V92: =$V$96 -> 20 | W92: 100000 | X92: 100000 | Y92: construction chemical factory 1ha, organics | Z92: =0.4/571 -> 0.00070052539 | AA92: 0
A93: lohc-dehydrogenation_55 | B93: 1 | C93: kg/h | D93: 0 | E93: 0 | F93: 2055 | G93: 2060 | H93: bus_lohcdehy_pi1 | I93: 1 | J93: 0 | K93: bus_el-h2 | L93: =(33.3+131.4)/89.93 -> 1.8314244 | M93: 0 | N93: bus_hydrogen | O93: 1 | P93: 0 | Q93: 0 | R93: empty | S93: 1 | T93: =$T$96 -> 465 | U93: 10916 | V93: =$V$96 -> 20 | W93: 100000 | X93: 100000 | Y93: construction chemical factory 1ha, organics | Z93: =0.4/571 -> 0.00070052539 | AA93: 0
A94: lohc-dehydrogenation_60 | B94: 1 | C94: kg/h | D94: 0 | E94: 0 | F94: 2060 | G94: 2065 | H94: bus_lohcdehy_pi1 | I94: 1 | J94: 0 | K94: bus_el-h2 | L94: =(33.3+131.4)/89.93 -> 1.8314244 | M94: 0 | N94: bus_hydrogen | O94: 1 | P94: 0 | Q94: 0 | R94: empty | S94: 1 | T94: =$T$96 -> 465 | U94: 10916 | V94: =$V$96 -> 20 | W94: 100000 | X94: 100000 | Y94: construction chemical factory 1ha, organics | Z94: =0.4/571 -> 0.00070052539 | AA94: 0
A95: lohc-dehydrogenation_65 | B95: 1 | C95: kg/h | D95: 0 | E95: 0 | F95: 2065 | G95: 2070 | H95: bus_lohcdehy_pi1 | I95: 1 | J95: 0 | K95: bus_el-h2 | L95: =(33.3+131.4)/89.93 -> 1.8314244 | M95: 0 | N95: bus_hydrogen | O95: 1 | P95: 0 | Q95: 0 | R95: empty | S95: 1 | T95: =$T$96 -> 465 | U95: 10916 | V95: =$V$96 -> 20 | W95: 100000 | X95: 100000 | Y95: construction chemical factory 1ha, organics | Z95: =0.4/571 -> 0.00070052539 | AA95: 0
A96: lohc-dehydrogenation_70 | B96: 1 | C96: kg/h | D96: 0 | E96: 0 | F96: 2070 | G96: 2075 | H96: bus_lohcdehy_pi1 | I96: 1 | J96: 0 | K96: bus_el-h2 | L96: =(33.3+131.4)/89.93 -> 1.8314244 | M96: 0 | N96: bus_hydrogen | O96: 1 | P96: 0 | Q96: 0 | R96: empty | S96: 1 | T96: 465 | U96: 10916 | V96: 20 | W96: 100000 | X96: 100000 | Y96: construction chemical factory 1ha, organics | Z96: =0.4/571 -> 0.00070052539 | AA96: 0 | AE96: om actually 3% per year of invest costs
A98: ammonia-decomp_proxy_i1 | B98: 1 | C98: kg/h | D98: 0 | E98: 0 | F98: 0 | G98: 2100 | H98: bus_nh3 | I98: =516.85/516.85 -> 1 | J98: 0 | K98: bus_th400 | L98: =385.2/516.85 -> 0.74528393 | M98: 0 | N98: bus_ammoniadecomp_pi1 | O98: =89.93/516.85 -> 0.17399632 | P98: 0 | Q98: 0 | R98: empty | S98: 1 | T98: 0 | U98: 0 | V98: 100 | W98: 100000 | X98: 100000 | Y98: empty | Z98: 1 | AA98: 0
A99: ammonia-decomposition_25 | B99: 1 | C99: kg/h | D99: 0 | E99: 0 | F99: 2025 | G99: 2030 | H99: bus_ammoniadecomp_pi1 | I99: 1 | J99: 0 | K99: bus_el-h2 | L99: =(30+132.32+113.39)/89.93 -> 3.065829 | M99: 0 | N99: bus_hydrogen | O99: 1 | P99: 0 | Q99: 0 | R99: empty | S99: 1 | T99: =$T$108 -> 1046 | U99: 43014 | V99: =$V$108 -> 25 | W99: 0 | X99: 100000 | Y99: construction chemical factory 1ha, organics | Z99: =0.4/571 -> 0.00070052539 | AA99: 0
A100: ammonia-decomposition_30 | B100: 1 | C100: kg/h | D100: 0 | E100: 0 | F100: 2030 | G100: 2035 | H100: bus_ammoniadecomp_pi1 | I100: 1 | J100: 0 | K100: bus_el-h2 | L100: =(30+132.32+113.39)/89.93 -> 3.065829 | M100: 0 | N100: bus_hydrogen | O100: 1 | P100: 0 | Q100: 0 | R100: empty | S100: 1 | T100: =$T$108 -> 1046 | U100: 40066 | V100: =$V$108 -> 25 | W100: 100000 | X100: 100000 | Y100: construction chemical factory 1ha, organics | Z100: =0.4/571 -> 0.00070052539 | AA100: 0
A101: ammonia-decomposition_35 | B101: 1 | C101: kg/h | D101: 0 | E101: 0 | F101: 2035 | G101: 2040 | H101: bus_ammoniadecomp_pi1 | I101: 1 | J101: 0 | K101: bus_el-h2 | L101: =(30+132.32+113.39)/89.93 -> 3.065829 | M101: 0 | N101: bus_hydrogen | O101: 1 | P101: 0 | Q101: 0 | R101: empty | S101: 1 | T101: =$T$108 -> 1046 | U101: 37326 | V101: =$V$108 -> 25 | W101: 100000 | X101: 100000 | Y101: construction chemical factory 1ha, organics | Z101: =0.4/571 -> 0.00070052539 | AA101: 0
A102: ammonia-decomposition_40 | B102: 1 | C102: kg/h | D102: 0 | E102: 0 | F102: 2040 | G102: 2045 | H102: bus_ammoniadecomp_pi1 | I102: 1 | J102: 0 | K102: bus_el-h2 | L102: =(30+132.32+113.39)/89.93 -> 3.065829 | M102: 0 | N102: bus_hydrogen | O102: 1 | P102: 0 | Q102: 0 | R102: empty | S102: 1 | T102: =$T$108 -> 1046 | U102: 34778 | V102: =$V$108 -> 25 | W102: 100000 | X102: 100000 | Y102: construction chemical factory 1ha, organics | Z102: =0.4/571 -> 0.00070052539 | AA102: 0
A103: ammonia-decomposition_45 | B103: 1 | C103: kg/h | D103: 0 | E103: 0 | F103: 2045 | G103: 2050 | H103: bus_ammoniadecomp_pi1 | I103: 1 | J103: 0 | K103: bus_el-h2 | L103: =(30+132.32+113.39)/89.93 -> 3.065829 | M103: 0 | N103: bus_hydrogen | O103: 1 | P103: 0 | Q103: 0 | R103: empty | S103: 1 | T103: =$T$108 -> 1046 | U103: 32408 | V103: =$V$108 -> 25 | W103: 100000 | X103: 100000 | Y103: construction chemical factory 1ha, organics | Z103: =0.4/571 -> 0.00070052539 | AA103: 0
A104: ammonia-decomposition_50 | B104: 1 | C104: kg/h | D104: 0 | E104: 0 | F104: 2050 | G104: 2055 | H104: bus_ammoniadecomp_pi1 | I104: 1 | J104: 0 | K104: bus_el-h2 | L104: =(30+132.32+113.39)/89.93 -> 3.065829 | M104: 0 | N104: bus_hydrogen | O104: 1 | P104: 0 | Q104: 0 | R104: empty | S104: 1 | T104: =$T$108 -> 1046 | U104: 32408 | V104: =$V$108 -> 25 | W104: 100000 | X104: 100000 | Y104: construction chemical factory 1ha, organics | Z104: =0.4/571 -> 0.00070052539 | AA104: 0
A105: ammonia-decomposition_55 | B105: 1 | C105: kg/h | D105: 0 | E105: 0 | F105: 2055 | G105: 2060 | H105: bus_ammoniadecomp_pi1 | I105: 1 | J105: 0 | K105: bus_el-h2 | L105: =(30+132.32+113.39)/89.93 -> 3.065829 | M105: 0 | N105: bus_hydrogen | O105: 1 | P105: 0 | Q105: 0 | R105: empty | S105: 1 | T105: =$T$108 -> 1046 | U105: 32408 | V105: =$V$108 -> 25 | W105: 100000 | X105: 100000 | Y105: construction chemical factory 1ha, organics | Z105: =0.4/571 -> 0.00070052539 | AA105: 0
A106: ammonia-decomposition_60 | B106: 1 | C106: kg/h | D106: 0 | E106: 0 | F106: 2060 | G106: 2065 | H106: bus_ammoniadecomp_pi1 | I106: 1 | J106: 0 | K106: bus_el-h2 | L106: =(30+132.32+113.39)/89.93 -> 3.065829 | M106: 0 | N106: bus_hydrogen | O106: 1 | P106: 0 | Q106: 0 | R106: empty | S106: 1 | T106: =$T$108 -> 1046 | U106: 32408 | V106: =$V$108 -> 25 | W106: 100000 | X106: 100000 | Y106: construction chemical factory 1ha, organics | Z106: =0.4/571 -> 0.00070052539 | AA106: 0
A107: ammonia-decomposition_65 | B107: 1 | C107: kg/h | D107: 0 | E107: 0 | F107: 2065 | G107: 2070 | H107: bus_ammoniadecomp_pi1 | I107: 1 | J107: 0 | K107: bus_el-h2 | L107: =(30+132.32+113.39)/89.93 -> 3.065829 | M107: 0 | N107: bus_hydrogen | O107: 1 | P107: 0 | Q107: 0 | R107: empty | S107: 1 | T107: =$T$108 -> 1046 | U107: 32408 | V107: =$V$108 -> 25 | W107: 100000 | X107: 100000 | Y107: construction chemical factory 1ha, organics | Z107: =0.4/571 -> 0.00070052539 | AA107: 0
A108: ammonia-decomposition_70 | B108: 1 | C108: kg/h | D108: 0 | E108: 0 | F108: 2070 | G108: 2075 | H108: bus_ammoniadecomp_pi1 | I108: 1 | J108: 0 | K108: bus_el-h2 | L108: =(30+132.32+113.39)/89.93 -> 3.065829 | M108: 0 | N108: bus_hydrogen | O108: 1 | P108: 0 | Q108: 0 | R108: empty | S108: 1 | T108: 1046 | U108: 32408 | V108: 25 | W108: 100000 | X108: 100000 | Y108: construction chemical factory 1ha, organics | Z108: =0.4/571 -> 0.00070052539 | AA108: 0 | AE108: om actually 4% per year of invest costs
A110: kvaerner-ng_proxy_i1 | B110: 0 | C110: kg/h | D110: 0 | E110: 0 | F110: 0 | G110: 2100 | H110: bus_nat_gas | I110: =357.81*12.9/(357.81*12.9) -> 1 | J110: 0 | K110: bus_el | L110: =1558.07/(357.81*12.9) -> 0.33755518 | M110: 0 | N110: bus_kvaerner_pi1 | O110: =89.93/(357.81*12.9) -> 0.019483295 | P110: 0 | Q110: 0 | R110: empty | S110: 1 | T110: 0 | U110: 0 | V110: 100 | W110: 100000 | X110: 100000 | Y110: empty | Z110: 1 | AA110: 0
A112: kvaerner-bio_proxy_i1 | B112: 0 | C112: kg/h | D112: 0 | E112: 0 | F112: 0 | G112: 2100 | H112: bus_biometh | I112: =357.81*12.9/(357.81*12.9) -> 1 | J112: 0 | K112: bus_el | L112: =1558.07/(357.81*12.9) -> 0.33755518 | M112: 0 | N112: bus_kvaerner_pi1 | O112: =89.93/(357.81*12.9) -> 0.019483295 | P112: 0 | Q112: 0 | R112: empty | S112: 1 | T112: 0 | U112: 0 | V112: 100 | W112: 100000 | X112: 100000 | Y112: empty | Z112: 1 | AA112: 0
A114: carbon_capture_atr_25 | B114: 0 | C114: kg/h | D114: 0 | E114: 0 | F114: 2025 | G114: 2030 | H114: bus_atr-exhaust | I114: 1 | J114: 0 | K114: bus_el | L114: =(377.9+125.96)/3433.99 -> 0.14672728 | M114: 0 | N114: bus_co2 | O114: =1259.56/3433.99 -> 0.36679198 | P114: 0 | Q114: 0 | R114: empty | S114: 1 | T114: =$T$123 -> 19.5 | U114: 848 | V114: =$V$123 -> 25 | W114: 0 | X114: 100000 | Y114: CO2 capture_cons_2025 | Z114: =1/(O114*converters_in!$L$56*9000.9) -> 7.9323122e-06 | AA114: 0
A115: carbon_capture_atr_30 | B115: 0 | C115: kg/h | D115: 0 | E115: 0 | F115: 2030 | G115: 2035 | H115: bus_atr-exhaust | I115: 1 | J115: 0 | K115: bus_el | L115: =(377.9+125.96)/3433.99 -> 0.14672728 | M115: 0 | N115: bus_co2 | O115: =1259.56/3433.99 -> 0.36679198 | P115: 0 | Q115: 0 | R115: empty | S115: 1 | T115: =$T$123 -> 19.5 | U115: 784 | V115: =$V$123 -> 25 | W115: 0 | X115: 100000 | Y115: CO2 capture_cons_2030 | Z115: =1/(O115*converters_in!$L$56*9000.9) -> 7.9323122e-06 | AA115: 0
...

Sheet timeseries
A1: hour | B1: solar_thermal_FPC_high.fix | C1: solar_thermal_FPC_low.fix | D1: load_th.fix | E1: load_el.fix | F1: load_el_30.fix | G1: load_el_35.fix | H1: load_el_40.fix | I1: load_el_45.fix | K1: load-households_el.fix | L1: load-households_el_30.fix | M1: load-households_el_35.fix | N1: load-households_el_40.fix | O1: load-households_el_45.fix | Q1: load-households_th.fix | R1: load-households_th_30.fix | S1: load-households_th_35.fix | T1: load-households_th_40.fix | U1: load-households_th_45.fix | V1: PV_flat_roof.fix | W1: PV_og.fix | X1: PV_og_30.fix | Y1: PV_og_35.fix | Z1: PV_og_40.fix | AA1: PV_og_45.fix | AB1: band-pip.fix | AC1: band-nh3.fix | AD1: band-lohc.fix | AE1: band-ch4.fix | AF1: band-el.fix | AG1: heat_pump_a_w_low.cop | AH1: heat_pump_a_w_high.cop | AI1: load_th_low.fix | AJ1: load_th_high.fix | AK1: PV_facade.fix | AL1: windon.fix | AM1: windoff.fix | AN1: load_hydrogen.fix | AO1: load_steamSite.fix | AP1: load_methanol.fix | AQ1: w/o5ct_resource_grid_25.timevariable_costs | AR1: w/o5ct_resource_grid_30.timevariable_costs | AS1: w/o5ct_resource_grid_35.timevariable_costs | AT1: w/o5ct_resource_grid_40.timevariable_costs | AU1: w/o5ct_resource_grid_45.timevariable_costs | AW1: resource_grid_25.timevariable_costs | AX1: resource_grid_30.timevariable_costs | AY1: resource_grid_35.timevariable_costs | AZ1: resource_grid_40.timevariable_costs | BA1: resource_grid_45.timevariable_costs | BC1: grid_converter-h2.timevariable_penalty | BD1: grid_converter-stor.timevariable_penalty | BE1: stor-el-h2_converter.timevariable_penalty | BF1: stor-el_converter.timevariable_penalty | BG1: penalty-h2_reservoir.timevariable_penalty
A2: 1 | E2: 9795.2055 | K2: 3969.7784 | L2: 4349.2634 | M2: 4728.7484 | N2: 5108.2334 | O2: 5487.7184 | Q2: 25589.419 | R2: 24898.08 | S2: 24206.742 | T2: 23515.404 | U2: 22824.066 | W2: 0 | AB2: 1 | AC2: 1 | AD2: 1 | AE2: 1 | AF2: 1 | AL2: 2.27961 | AM2: 8.7762623 | AN2: 570.77626 | AO2: =235000000/8760 -> 26826.484 | AP2: 684.93151 | AQ2: 0.10173 | AR2: 0.0917533 | AS2: 0.0872406 | AT2: 0.11178 | AU2: 0.106009 | AW2: 0.10173 | AX2: 0.0917533 | AY2: 0.0872406 | AZ2: 0.11178 | BA2: 0.106009 | BC2: 0 | BD2: 0 | BE2: 100000 | BF2: 100000 | BG2: 100000
A3: 2 | E3: 9795.2055 | K3: 3048.2434 | L3: 3365.9109 | M3: 3683.5784 | N3: 4001.2459 | O3: 4318.9134 | Q3: 26874.805 | R3: 26148.74 | S3: 25422.676 | T3: 24696.611 | U3: 23970.546 | W3: 0 | AB3: 1 | AC3: 1 | AD3: 1 | AE3: 1 | AF3: 1 | AL3: 1.0751221 | AM3: 8.9204435 | AN3: 570.77626 | AO3: =235000000/8760 -> 26826.484 | AP3: 684.93151 | AQ3: 0.101819 | AR3: 0.0917922 | AS3: 0.0872941 | AT3: 0.111823 | AU3: 0.106042 | AW3: 0.101819 | AX3: 0.0917922 | AY3: 0.0872941 | AZ3: 0.111823 | BA3: 0.106042 | BC3: 0 | BD3: 0 | BE3: 0 | BF3: 0 | BG3: 0
A4: 3 | E4: 9795.2055 | K4: 2248.2676 | L4: 2449.1751 | M4: 2650.0826 | N4: 2850.9901 | O4: 3051.8976 | Q4: 27294.612 | R4: 26557.206 | S4: 25819.799 | T4: 25082.392 | U4: 24344.986 | W4: 0 | AB4: 1 | AC4: 1 | AD4: 1 | AE4: 1 | AF4: 1 | AL4: 0.8122278 | AM4: 8.7921515 | AN4: 570.77626 | AO4: =235000000/8760 -> 26826.484 | AP4: 684.93151 | AQ4: 0.101805 | AR4: 0.0917867 | AS4: 0.087352 | AT4: 0.111924 | AU4: 0.106053 | AW4: 0.101805 | AX4: 0.0917867 | AY4: 0.087352 | AZ4: 0.111924 | BA4: 0.106053 | BC4: 0 | BD4: 0 | BE4: 0 | BF4: 0 | BG4: 0
A5: 4 | E5: 9795.2055 | K5: 1998.2028 | L5: 2097.5278 | M5: 2196.8528 | N5: 2296.1778 | O5: 2395.5028 | Q5: 29651.751 | R5: 28850.663 | S5: 28049.574 | T5: 27248.486 | U5: 26447.397 | W5: 0 | AB5: 1 | AC5: 1 | AD5: 1 | AE5: 1 | AF5: 1 | AL5: 0.45404288 | AM5: 8.441824 | AN5: 570.77626 | AO5: =235000000/8760 -> 26826.484 | AP5: 684.93151 | AQ5: 0.101026 | AR5: 0.0888266 | AS5: 0.0852696 | AT5: 0.109174 | AU5: 0.104037 | AW5: 0.101026 | AX5: 0.0888266 | AY5: 0.0852696 | AZ5: 0.109174 | BA5: 0.104037 | BC5: 0 | BD5: 0 | BE5: 0 | BF5: 0 | BG5: 0
A6: 5 | E6: 9795.2055 | K6: 2115.1313 | L6: 2173.4563 | M6: 2231.7813 | N6: 2290.1063 | O6: 2348.4313 | Q6: 34902.294 | R6: 33959.353 | S6: 33016.413 | T6: 32073.473 | U6: 31130.533 | W6: 0 | AB6: 1 | AC6: 1 | AD6: 1 | AE6: 1 | AF6: 1 | AL6: 0.4262455 | AM6: 8.6129341 | AN6: 570.77626 | AO6: =235000000/8760 -> 26826.484 | AP6: 684.93151 | AQ6: 0.100827 | AR6: 0.0887535 | AS6: 0.0850053 | AT6: 0.109087 | AU6: 0.103517 | AW6: 0.100827 | AX6: 0.0887535 | AY6: 0.0850053 | AZ6: 0.109087 | BA6: 0.103517 | BC6: 0 | BD6: 0 | BE6: 0 | BF6: 0 | BG6: 0
A7: 6 | E7: 9795.2055 | K7: 2468.232 | L7: 2507.5545 | M7: 2546.877 | N7: 2586.1995 | O7: 2625.522 | Q7: 51208.688 | R7: 49825.205 | S7: 48441.722 | T7: 47058.239 | U7: 45674.756 | W7: 0 | AB7: 1 | AC7: 1 | AD7: 1 | AE7: 1 | AF7: 1 | AL7: 0.5346606 | AM7: 8.6257401 | AN7: 570.77626 | AO7: =235000000/8760 -> 26826.484 | AP7: 684.93151 | AQ7: 0.100784 | AR7: 0.088833 | AS7: 0.0849342 | AT7: 0.108657 | AU7: 0.103049 | AW7: 0.100784 | AX7: 0.088833 | AY7: 0.0849342 | AZ7: 0.108657 | BA7: 0.103049 | BC7: 0 | BD7: 0 | BE7: 0 | BF7: 0 | BG7: 0
A8: 7 | E8: 9795.2055 | K8: 2924.3687 | L8: 2965.8912 | M8: 3007.4137 | N8: 3048.9362 | O8: 3090.4587 | Q8: 60707.371 | R8: 59067.266 | S8: 57427.161 | T8: 55787.057 | U8: 54146.952 | W8: 0 | AB8: 1 | AC8: 1 | AD8: 1 | AE8: 1 | AF8: 1 | AL8: 0.66493434 | AM8: 8.4524546 | AN8: 570.77626 | AO8: =235000000/8760 -> 26826.484 | AP8: 684.93151 | AQ8: 0.100922 | AR8: 0.0901184 | AS8: 0.0856071 | AT8: 0.1092 | AU8: 0.104013 | AW8: 0.100922 | AX8: 0.0901184 | AY8: 0.0856071 | AZ8: 0.1092 | BA8: 0.104013 | BC8: 0 | BD8: 0 | BE8: 0 | BF8: 0 | BG8: 0
A9: 8 | E9: 9795.2055 | K9: 4354.1372 | L9: 4396.6222 | M9: 4439.1072 | N9: 4481.5922 | O9: 4524.0772 | Q9: 57105.736 | R9: 55562.935 | S9: 54020.134 | T9: 52477.334 | U9: 50934.533 | W9: 0 | AB9: 1 | AC9: 1 | AD9: 1 | AE9: 1 | AF9: 1 | AL9: 0.72619563 | AM9: 8.2785349 | AN9: 570.77626 | AO9: =235000000/8760 -> 26826.484 | AP9: 684.93151 | AQ9: 0.100855 | AR9: 0.0925084 | AS9: 0.0884511 | AT9: 0.119465 | AU9: 0.107464 | AW9: 0.100855 | AX9: 0.0925084 | AY9: 0.0884511 | AZ9: 0.119465 | BA9: 0.107464 | BC9: 0 | BD9: 0 | BE9: 0 | BF9: 0 | BG9: 0
A10: 9 | E10: 9795.2055 | K10: 5394.9161 | L10: 5436.0261 | M10: 5477.1361 | N10: 5518.2461 | O10: 5559.3561 | Q10: 54581.762 | R10: 53107.151 | S10: 51632.539 | T10: 50157.927 | U10: 48683.315 | W10: 0.0427 | AB10: 1 | AC10: 1 | AD10: 1 | AE10: 1 | AF10: 1 | AL10: 0.94724363 | AM10: 8.0674353 | AN10: 570.77626 | AO10: =235000000/8760 -> 26826.484 | AP10: 684.93151 | AQ10: 0.100859 | AR10: 0.0941465 | AS10: 0.0913174 | AT10: 0.122626 | AU10: 0.110402 | AW10: 0.100859 | AX10: 0.0941465 | AY10: 0.0913174 | AZ10: 0.122626 | BA10: 0.110402 | BC10: 0 | BD10: 0 | BE10: 0 | BF10: 0 | BG10: 0
A11: 10 | E11: 9795.2055 | K11: 6373.1788 | L11: 6429.0013 | M11: 6484.8238 | N11: 6540.6463 | O11: 6596.4688 | Q11: 52987.117 | R11: 51555.587 | S11: 50124.057 | T11: 48692.527 | U11: 47260.997 | W11: 0.18166 | AB11: 1 | AC11: 1 | AD11: 1 | AE11: 1 | AF11: 1 | AL11: 1.5847316 | AM11: 7.7827625 | AN11: 570.77626 | AO11: =235000000/8760 -> 26826.484 | AP11: 684.93151 | AQ11: 0.101525 | AR11: 0.0948499 | AS11: 0.0913216 | AT11: 0.123017 | AU11: 0.110251 | AW11: 0.101525 | AX11: 0.0948499 | AY11: 0.0913216 | AZ11: 0.123017 | BA11: 0.110251 | BC11: 0 | BD11: 0 | BE11: 0 | BF11: 0 | BG11: 0
A12: 11 | E12: 9795.2055 | K12: 7152.3158 | L12: 7225.3258 | M12: 7298.3358 | N12: 7371.3458 | O12: 7444.3558 | Q12: 51108.403 | R12: 49727.629 | S12: 48346.856 | T12: 46966.082 | U12: 45585.309 | W12: 0.09057 | AB12: 1 | AC12: 1 | AD12: 1 | AE12: 1 | AF12: 1 | AL12: 0.95835024 | AM12: 7.374505 | AN12: 570.77626 | AO12: =235000000/8760 -> 26826.484 | AP12: 684.93151 | AQ12: 0.102142 | AR12: 0.0950538 | AS12: 0.0914367 | AT12: 0.123043 | AU12: 0.110305 | AW12: 0.102142 | AX12: 0.0950538 | AY12: 0.0914367 | AZ12: 0.123043 | BA12: 0.110305 | BC12: 0 | BD12: 0 | BE12: 0 | BF12: 0 | BG12: 0
A13: 12 | E13: 9795.2055 | K13: 8263.7148 | L13: 8378.0548 | M13: 8492.3948 | N13: 8606.7348 | O13: 8721.0748 | Q13: 48958.213 | R13: 47635.53 | S13: 46312.847 | T13: 44990.165 | U13: 43667.482 | W13: 0.11462 | AB13: 1 | AC13: 1 | AD13: 1 | AE13: 1 | AF13: 1 | AL13: 1.4356672 | AM13: 6.6416545 | AN13: 570.77626 | AO13: =235000000/8760 -> 26826.484 | AP13: 684.93151 | AQ13: 0.102547 | AR13: 0.0944389 | AS13: 0.0917869 | AT13: 0.123137 | AU13: 0.110143 | AW13: 0.102547 | AX13: 0.0944389 | AY13: 0.0917869 | AZ13: 0.123137 | BA13: 0.110143 | BC13: 0 | BD13: 0 | BE13: 0 | BF13: 0 | BG13: 0
... A8761: 8760 | E8761: 9795.2055 | K8761: 5008.5389 | L8761: 5353.8706 | M8761: 5699.2022 | N8761: 6044.5339 | O8761: 6389.8656 | Q8761: 33356.567 | R8761: 32455.387 | S8761: 31554.207 | T8761: 30653.027 | U8761: 29751.847 | W8761: 0 | AB8761: 1 | AC8761: 1 | AD8761: 1 | AE8761: 1 | AF8761: 1 | AL8761: 2.6094935 | AM8761: 17.717545 | AN8761: 570.77626 | AO8761: =235000000/8760 -> 26826.484 | AP8761: 684.93151 | AQ8761: 0.0714329 | AR8761: 0.0481604 | AS8761: 0.0568919 | AT8761: 0.051489 | AU8761: 0.0476596 | AW8761: 0.0714329 | AX8761: 0.0481604 | AY8761: 0.0568919 | AZ8761: 0.051489 | BA8761: 0.0476596 | BC8761: 100000 | BD8761: 100000 | BE8761: 0 | BF8761: 0 | BG8761: 0
